#######################################################################################################################################
<poster>HackerMil</poster>
<fanart>http://farm4.staticflickr.com/3678/10216833154_eab0f31a67_o.png</fanart>
#######################################################################################################################################

<info>
<message>[COLOR red]**[/COLOR] [COLOR aqua]IN ALPHABETICAL ORDER, SEQUELS TOGETHER[/COLOR] [COLOR red]**[/COLOR]</message>
<thumbnail>http://farm8.staticflickr.com/7436/10216924005_94fb74c943_o.png</thumbnail>
</info>

##############################################################################################################


<item>
<title>21 Jump Street (2012)</title>
<link>
<sublink>http://75.126.196.132/index.php?file=284&start=0&hd=0&auth=37173551f877bf4854313fe84e&type=flv&tv=0</sublink>
<sublink>http://billionuploads.com/f7kfn6xrbbd0</sublink>
<sublink>http://movreel.com/t441rohlal3o</sublink>  
</link>
<thumbnail>http://d3gtl9l2a4fn1j.cloudfront.net/t/p/original/z7DKa3R4J34AFsWQz8LXwGFwaec.jpg</thumbnail>
</item>

<item>
<title>27 Dresses (2008)</title>
<link>
<sublink>http://75.126.196.132/index.php?file=402&start=0&hd=0&auth=37173551f877bf4854313fe84e&type=flv&tv=0</sublink>
<sublink>http://yify.tv/27-dresses/</sublink>
<sublink>http://billionuploads.com/4tk69p6fpbi2</sublink>
<sublink>http://hugefiles.net/e6tktbp8ucsu</sublink>
<sublink>http://180upload.com/hqf2mxm9ly5n</sublink>
</link>
<thumbnail>http://image.tmdb.org/t/p/original/bCSaeV65w2A2WLEjp5LcTk9EKyA.jpg</thumbnail>
</item>

<item>
<title>30 Minutes or Less (2011)</title>
<link>
<sublink>http://75.126.196.132/index.php?file=1143&start=0&hd=0&auth=37173551f877bf4854313fe84e&type=flv&tv=0</sublink>
<sublink>http://billionuploads.com/9037icprmx80</sublink>
<sublink>http://180upload.com/5nvx3do851v6</sublink>  
</link>
<thumbnail>http://d3gtl9l2a4fn1j.cloudfront.net/t/p/original/rY80CLR3dWsOzRlxVyupEUsYAhn.jpg</thumbnail>
</item>

<item>
<title>50 First Dates (2004)</title>
<link>
<sublink>http://75.126.196.132/index.php?file=411&start=0&hd=0&auth=37173551f877bf4854313fe84e&type=flv&tv=0</sublink>
<sublink>http://billionuploads.com/1ypt2blwlp6c</sublink>
<sublink>http://hugefiles.net/0oe9c8s3zjia</sublink>
<sublink>http://180upload.com/rj63tkhcj1ei</sublink>
</link>
<thumbnail>http://d3gtl9l2a4fn1j.cloudfront.net/t/p/original/kIvolfg9RRZxwuAqRZ1K9BYSe3V.jpg</thumbnail>
</item>2004-02-13

<item>
<title>A Case of You (2013)</title>
<link>
<sublink>http://75.126.196.132/index.php?file=2945&start=0&hd=0&auth=37173551f877bf4854313fe84e&type=flv&tv=0</sublink>
<sublink>http://billionuploads.com/kxadx6iem7wv</sublink>
<sublink>http://hugefiles.net/nuwb0yq3qsni</sublink>
<sublink>http://180upload.com/gtpb2rkc3uqb</sublink>
<sublink>http://yify.tv/a-case-of-you/</sublink>
</link>
<thumbnail>http://image.tmdb.org/t/p/original/1Yg9gMDxApehhbDkk11NQKD82Ms.jpg</thumbnail>
</item>

<item>
<title>A.C.O.D. (2013)</title>
<link>
<sublink>http://hugefiles.net/9maa9jmjlbo6</sublink>
<sublink>http://hugefiles.net/9vjgm3cbmfwn</sublink>
<sublink>http://180upload.com/p6hvomm5binu</sublink>
<sublink>http://180upload.com/eqom0fhvjmum</sublink>
<sublink>http://movreel.com/bfh0grtevfl6</sublink>
<sublink>http://movreel.com/40hw28bh6hsm</sublink>
<sublink></sublink>
<sublink></sublink>
</link>
<thumbnail>http://image.tmdb.org/t/p/original/cO87I4zTfEGyKqeTiMNRkYjmdzK.jpg</thumbnail>
</item>2013-10-04

<item>
<title>Accepted (2006)</title>
<link>
<sublink>http://75.126.196.132/index.php?file=2268&start=0&hd=0&auth=37173551f877bf4854313fe84e&type=flv&tv=0</sublink>
<sublink>http://www.putlocker.com/file/51595EB54A13BB73</sublink>
<sublink>http://www.sockshare.com/file/3C36120136E32850</sublink>
</link>
<thumbnail>http://d3gtl9l2a4fn1j.cloudfront.net/t/p/original/7wrkCQFxMwnOAUnsXK6oEFzhOOp.jpg</thumbnail>
</item>2006-11-10

<item>
<title>Ace Ventura: Pet Detective (1994)</title>
<link>
<sublink>http://75.126.196.132/index.php?file=2080&start=0&hd=0&auth=37173551f877bf4854313fe84e&type=flv&tv=0</sublink>
<sublink>http://180upload.com/n7r5gpzra3xr</sublink>
<sublink>http://epicshare.net/geq07ur2ut6a</sublink>
<sublink>http://movreel.com/ayk4ul11unm9</sublink>  
</link>
<thumbnail>http://d3gtl9l2a4fn1j.cloudfront.net/t/p/original/nZirljb8XYbKTWsRQTplDGhx39Q.jpg</thumbnail>
</item>1994-02-04

<item>
<title>Ace Ventura: When Nature Calls (1995)</title>
<link>
<sublink>http://75.126.196.132/index.php?file=1615&start=0&hd=0&auth=37173551f877bf4854313fe84e&type=flv&tv=0</sublink>
<sublink>http://veehd.com/video/4595633_Ace-Ventura-When-Nature-Calls</sublink>  
</link>
<thumbnail>http://ia.media-imdb.com/images/M/MV5BNzMzODY1ODAzNl5BMl5BanBnXkFtZTYwODEzNjE5._V1_SY317_CR8,0,214,317_.jpg</thumbnail>
</item>1995-11-10

<item>
<title>Admission (2013)</title>
<link>
<sublink>http://yify.tv/admission/</sublink>
<sublink>http://75.126.196.132/index.php?file=1768&start=0&hd=0&auth=37173551f877bf4854313fe84e&type=flv&tv=0</sublink>
<sublink>http://epicshare.net/347594hg5171</sublink>
<sublink>http://180upload.com/3zicg8hcwxpr</sublink>
</link>
<thumbnail>http://ia.media-imdb.com/images/M/MV5BOTE2OTkwNzg5Ml5BMl5BanBnXkFtZTcwOTY0NzQ3OA@@._V1._SX640_SY999_.jpg</thumbnail>
</item>

<item>
<title>Alan Partridge: Alpha Papa (2013)</title>
<link>
<sublink>http://billionuploads.com/jkrviopgiacf</sublink>
<sublink>http://hugefiles.net/8ohgdmgxztm6</sublink>
<sublink>http://hugefiles.net/nnkot9yd26vh</sublink>
<sublink>http://180upload.com/o979y6ss93y3</sublink>
<sublink>http://epicshare.net/5ji0eh1rufbm</sublink>
</link>
<thumbnail>http://d3gtl9l2a4fn1j.cloudfront.net/t/p/original/2ad6PXTg2WHANUQBAViB1CDAlFF.jpg</thumbnail>
</item>

<item>
<title>American Pie (1999)</title>
<link>http://75.126.196.132/index.php?file=373&start=0&hd=0&auth=37173551f877bf4854313fe84e&type=flv&tv=0</link>
<thumbnail>http://d3gtl9l2a4fn1j.cloudfront.net/t/p/original/5AP00ZFAbP3sMPZZqLXSg3Deq0s.jpg</thumbnail>
</item>1999-07-09

<item>
<title>American Pie 2 (2001)</title>
<link>http://75.126.196.132/index.php?file=372&start=0&hd=0&auth=37173551f877bf4854313fe84e&type=flv&tv=0</link>
<thumbnail>http://d3gtl9l2a4fn1j.cloudfront.net/t/p/original/xigrZMnKAhcmXAApechtjaTsSTk.jpg</thumbnail>
</item>2001-08-06

<item>
<title>American Wedding (2003)</title>
<link>http://75.126.196.132/index.php?file=371&start=0&hd=0&auth=37173551f877bf4854313fe84e&type=flv&tv=0</link>
<thumbnail>http://d3gtl9l2a4fn1j.cloudfront.net/t/p/original/qw1bRBiXjg0eMGEL7ijq6iBHNfv.jpg</thumbnail>
</item>2003-07-24

<item>
<title>American Pie Presents Band Camp (2005)</title>
<link>http://75.126.196.132/index.php?file=936&start=0&hd=0&auth=37173551f877bf4854313fe84e&type=flv&tv=0</link>
<thumbnail>http://d3gtl9l2a4fn1j.cloudfront.net/t/p/original/vmotXwFXRpQ1H9iT0dF5BtMf7tU.jpg</thumbnail>
</item>2005-12-30

<item>
<title>American Pie Presents The Naked Mile (2006)</title>
<link>http://75.126.196.132/index.php?file=937&start=0&hd=0&auth=37173551f877bf4854313fe84e&type=flv&tv=0</link>
<thumbnail>http://d3gtl9l2a4fn1j.cloudfront.net/t/p/original/vuXjrGeTw52Wysln13hI83gmMKM.jpg</thumbnail>
</item>2006-12-21

<item>
<title>American Pie Presents Beta House (2007)</title>
<link>http://75.126.196.132/index.php?file=938&start=0&hd=0&auth=37173551f877bf4854313fe84e&type=flv&tv=0</link>
<thumbnail>http://d3gtl9l2a4fn1j.cloudfront.net/t/p/original/9mTFjBanVsZBI7ebx6pEfXghj54.jpg</thumbnail>
</item>2007-12-10

<item>
<title>American Pie Presents: The Book of Love (2009)</title>
<link>http://75.126.196.132/index.php?file=939&start=0&hd=0&auth=37173551f877bf4854313fe84e&type=flv&tv=0</link>
<thumbnail>http://d3gtl9l2a4fn1j.cloudfront.net/t/p/original/drWGgcvkzgEDWiVwTI22FkPHZmd.jpg</thumbnail>
</item>2009-12-04

<item>
<title>American Reunion (2012)</title>
<link>
<sublink>http://75.126.196.132/index.php?file=391&start=0&hd=0&auth=37173551f877bf4854313fe84e&type=flv&tv=0</sublink>
<sublink>http://movreel.com/iv1o55b733w4</sublink>
<sublink>http://www.putlocker.com/file/D0514413001B0D7B</sublink>
<sublink>http://www.sockshare.com/file/301C8DEF764E7378</sublink>
</link>
<thumbnail>http://d3gtl9l2a4fn1j.cloudfront.net/t/p/original/yfOZaUh08d1YtLCtgvfRRAssrR7.jpg</thumbnail>
</item>

<item>
<title>Anchorman 2: The Legend Continues (2013) >>></title>
<link>
<sublink>http://lemuploads.com/zzusihceaggz</sublink>
<sublink>http://BillionUploads.com/6enc9qw91b68</sublink>
<sublink>http://hugefiles.net/e9vxap4x6st9</sublink>
<sublink>http://180upload.com/z4u0jtvvlv3i</sublink>
<sublink>http://epicshare.net/zzusihceaggz</sublink>
</link>
<thumbnail>http://image.tmdb.org/t/p/original/8HweezekJmUn4Rth0CoHa1pVKdC.jpg</thumbnail>
</item>

<item>
<title>Anchorman: The Legend of Ron Burgundy (2004)</title>
<link>
<sublink>http://75.126.196.132/index.php?file=1312&start=0&hd=0&auth=37173551f877bf4854313fe84e&type=flv&tv=0</sublink>
<sublink>http://billionuploads.com/gh621xuum190</sublink>
<sublink>http://movreel.com/r4988ldr4g4m</sublink>
<sublink>http://180upload.com/gx9dd9t554as</sublink>  
</link>
<thumbnail>http://d3gtl9l2a4fn1j.cloudfront.net/t/p/original/pdy6TWKUbSC9vtmxsFA73FZBVP3.jpg</thumbnail>
</item>

<item>
<title>As Good as It Gets (1997)</title>
<link>
<sublink>http://75.126.196.132/index.php?file=752&start=0&hd=0&auth=37173551f877bf4854313fe84e&type=flv&tv=0</sublink>
<sublink>http://hugefiles.net/dgvect73ooqy</sublink>
<sublink>http://180upload.com/zzx23in0vd9g</sublink>
<sublink>http://movreel.com/wayynne5uxx8</sublink>
</link>
<thumbnail>http://image.tmdb.org/t/p/original/q2645aW8vgg1g7RL5lil6K93yaA.jpg</thumbnail>
</item>

<item>
<title>Austin Powers: International Man of Mystery (1997)</title>
<link>
<sublink>http://75.126.196.132/index.php?file=1270&start=0&hd=0&auth=37173551f877bf4854313fe84e&type=flv&tv=0</sublink>
<sublink>http://billionuploads.com/uimqwictmkt7</sublink>
<sublink>http://hugefiles.net/ggg857ee3f3v</sublink>
<sublink>http://180upload.com/h5x0kh3musxi</sublink>  
</link>
<thumbnail>http://d3gtl9l2a4fn1j.cloudfront.net/t/p/original/oFJVZWh0VaGbYQe1sKJmRQUpjdh.jpg</thumbnail>
</item>1997-05-02

<item>
<title>Austin Powers: The Spy Who Shagged Me (1999)</title>
<link>
<sublink>http://75.126.196.132/index.php?file=1271&start=0&hd=0&auth=37173551f877bf4854313fe84e&type=flv&tv=0</sublink>
<sublink>http://billionuploads.com/gypuou7bdy18</sublink>
<sublink>http://hugefiles.net/ridgd5z3mo6c</sublink>
<sublink>http://180upload.com/kvqfx4xug12e</sublink>  
</link>
<thumbnail>http://d3gtl9l2a4fn1j.cloudfront.net/t/p/original/lxHaK18YSXBfE2oTseAFjHt1u6M.jpg</thumbnail>
</item>

<item>
<title>Austin Powers in Goldmember (2002)</title>
<link>
<sublink>http://75.126.196.132/index.php?file=1272&start=0&hd=0&auth=37173551f877bf4854313fe84e&type=flv&tv=0</sublink>
<sublink>http://billionuploads.com/1n5lwv952tj7</sublink>
<sublink>http://hugefiles.net/giaqqkivrsg5</sublink>
<sublink>http://180upload.com/zsbs863adg93</sublink>  
</link>
<thumbnail>http://d3gtl9l2a4fn1j.cloudfront.net/t/p/original/wdH7LaF3RQ2NFjKrrzndntBdNC7.jpg</thumbnail>
</item>2002-07-22

<item>
<title>Away We Go (2009)</title>
<link>http://75.126.196.132/index.php?file=3085&start=0&hd=0&auth=37173551f877bf4854313fe84e&type=flv&tv=0</link>
<thumbnail>http://image.tmdb.org/t/p/original/usltzOrkKVeh5KpEv98XwSsHi5G.jpg</thumbnail>
</item>

<item>
<title>Baggage Claim (2013)</title>
<link>
<sublink>http://yify.tv/baggage-claim/</sublink>
<sublink>http://75.126.196.132/index.php?file=2844&start=0&hd=0&auth=37173551f877bf4854313fe84e&type=flv&tv=0</sublink>
<sublink>http://hugefiles.net/7zpp2rutdf9a</sublink>
<sublink>http://billionuploads.com/bwplk16jajsa</sublink>
<sublink>http://180upload.com/62kr53q4g20h</sublink>
<sublink>http://movreel.com/f0l519noabnz</sublink>
</link>
<thumbnail>http://image.tmdb.org/t/p/original/vk6MnZgFdIJIxlOwDvdcPqd54lw.jpg</thumbnail>
</item>

<item>
<title>Balls of Fury (2007)</title>
<link>http://veehd.com/video/4656386_Balls-Of-Fury-2007-avi</link>
<thumbnail>http://d3gtl9l2a4fn1j.cloudfront.net/t/p/original/ouNyskL3MjSr1SZe5rIfxmQ1E4M.jpg</thumbnail>
</item>2007-08-29

<item>
<title>Beerfest (2006)</title>
<link>
<sublink>http://75.126.196.132/index.php?file=781&start=0&hd=0&auth=37173551f877bf4854313fe84e&type=flv&tv=0</sublink>
<sublink>http://yify.tv/beerfest/</sublink>
<sublink>http://hugefiles.net/tfu4yy8kfl83</sublink>
<sublink>http://180upload.com/rol60skd8zx3</sublink>
<sublink>http://movreel.com/lklxvh7l8nlz</sublink>
</link>
<thumbnail>http://image.tmdb.org/t/p/original/q0AbXSzM8YBurd3e4TueJmPdPG6.jpg</thumbnail>
</item>

<item>
<title>Blades of Glory (2007)</title>
<link>
<sublink>http://75.126.196.132/index.php?file=546&start=0&hd=0&auth=37173551f877bf4854313fe84e&type=flv&tv=0</sublink>
<sublink>http://veehd.com/video/4672403_Blades-of-Glory-2007</sublink>
<sublink>http://veehd.com/video/4608955_Blades-of-Glory-2007</sublink>
<sublink>http://veehd.com/video/4585061_Blades-of-Glory-2007-PG13-Will-Ferrell</sublink>  
</link>
<thumbnail>http://d3gtl9l2a4fn1j.cloudfront.net/t/p/original/4zUjsgL27bceM6U2wpj3c8EKU6p.jpg</thumbnail>
</item>

<item>
<title>Bridesmaids (2011)</title>
<link>
<sublink>http://75.126.196.132/index.php?file=808&start=0&hd=0&auth=37173551f877bf4854313fe84e&type=flv&tv=0</sublink>
<sublink>http://yify.tv/bridesmaids/</sublink>
<sublink>http://billionuploads.com/iqtkcrxlhzx9</sublink>
<sublink>http://hugefiles.net/i3ntop5p3u1t</sublink>
<sublink>http://180upload.com/vh9375vzjoam</sublink>
</link>
<thumbnail>http://image.tmdb.org/t/p/original/kXlR7q5Xzf0mBWDwtrcc5IJqzuJ.jpg</thumbnail>
</item>

<item>
<title>Casa de mi Padre (2012)</title>
<link>http://75.126.196.132/index.php?file=1377&start=0&hd=0&auth=37173551f877bf4854313fe84e&type=flv&tv=0</link>
<thumbnail>http://ia.media-imdb.com/images/M/MV5BODE1MDYzNjA0NF5BMl5BanBnXkFtZTcwNjY2MTgyNw@@._V1._SX640_SY923_.jpg</thumbnail>
</item>

<item>
<title>Cedar Rapids (2011)</title>
<link>
<sublink>http://75.126.196.132/index.php?file=2272&start=0&hd=0&auth=37173551f877bf4854313fe84e&type=flv&tv=0</sublink>
<sublink>http://veehd.com/video/4620742_Cedar-Rapids-BRrip-R</sublink>
</link>
<thumbnail>http://d3gtl9l2a4fn1j.cloudfront.net/t/p/original/165VIONWTaciBczNZxXQes7MGOe.jpg</thumbnail>
</item> 2011-02-11

<item>
<title>Christmas with the Kranks (2004)</title>
<link>
<sublink>http://hugefiles.net/nkfo24lh05t1</sublink>
<sublink>http://epicshare.net/1m2napvyx3pp/Puevfgznf.jvgu.gur.Xenaxf.720.divx.html</sublink>
<sublink>http://bayfiles.net/file/12gur/QqnFYp/Puevfgznf.jvgu.gur.Xenaxf.720.divx</sublink>
</link>
<thumbnail>http://image.tmdb.org/t/p/original/cJoqypqEax2iAuLpZnLFMQPtEbh.jpg</thumbnail>
</item>

<item>
<title>Clueless (1995)</title>
<link>
<sublink>http://yify.tv/clueless/</sublink>
<sublink>http://www.firedrive.com/file/8027B0C10C19DA70</sublink>
<sublink>http://www.sockshare.com/file/B4416C04678CA653</sublink>
</link>
<thumbnail>http://image.tmdb.org/t/p/original/i8gEHh2sszB6YWLC0jl559sxAeN.jpg</thumbnail>
</item>

<item>
<title>Coming to America (1988)</title>
<link>
<sublink>http://75.126.196.132/index.php?file=1877&start=0&hd=0&auth=37173551f877bf4854313fe84e&type=flv&tv=0</sublink>
<sublink>http://veehd.com/video/4745922_Coming-To-America-1988-BRRip</sublink>
</link>
<thumbnail>http://d3gtl9l2a4fn1j.cloudfront.net/t/p/original/jjqjN6Z8RMxVniuSw6h0mtsihKj.jpg</thumbnail>
</item>1988-06-28

<item>
<title>Crazy, Stupid, Love. (2011)</title>
<link>
<sublink>http://75.126.196.132/index.php?file=809&start=0&hd=0&auth=37173551f877bf4854313fe84e&type=flv&tv=0</sublink>
<sublink>http://yify.tv/crazy-stupid-love/</sublink>
<sublink>http://billionuploads.com/yoc59ys44grf</sublink>
<sublink>http://hugefiles.net/3s9r7ieoufw3</sublink>
<sublink>http://180upload.com/9s3g4xnxke4q</sublink>
</link>
<thumbnail>http://image.tmdb.org/t/p/original/n97V1WcpoJ8gBA0pM48Om05o2fN.jpg</thumbnail>
</item>

<item>
<title>Dazed and Confused (1993)</title>
<link>
<sublink>http://75.126.196.132/index.php?file=2630&start=0&hd=0&auth=37173551f877bf4854313fe84e&type=flv&tv=0</sublink>
<sublink>http://yify.tv/dazed-confused/</sublink>
<sublink>http://hugefiles.net/vl8boywfief8</sublink>
<sublink>http://180upload.com/cyys37oq3lb0</sublink>
</link>
<thumbnail>http://image.tmdb.org/t/p/original/bJitPryAQPxmzEAW4mNq0TtNeWQ.jpg</thumbnail>
</item>

<item>
<title>Deck The Halls (2006)</title>
<link>
<sublink>ttp://hugefiles.net/qwpphsvtv4sd</sublink>
<sublink>http://180upload.com/gb3navb5s0ds</sublink>
<sublink>http://epicshare.net/lzlr03p2hjni/Qrpx_Gur_Unyyf_720.divx.html</sublink>
<sublink>http://bayfiles.net/file/12gzf/zojozN/Qrpx_Gur_Unyyf_720.divx</sublink>
</link>
<thumbnail>http://image.tmdb.org/t/p/original/jfqrZpzrxP4ETR5WyoaUvEi65El.jpg</thumbnail>
</item>

<item>
<title>Delivery Man (2013)</title>
<link>
<sublink>http://75.126.196.132/index.php?file=3123&start=0&hd=0&auth=37173551f877bf4854313fe84e&type=flv&tv=0</sublink>
<sublink>http://yify.tv/delivery-man/</sublink>
<sublink>http://billionuploads.com/azpb5ml1kuq2</sublink>
<sublink>http://180upload.com/3f06g4fbpl8u</sublink>
<sublink>http://movreel.com/v1mk5052i1vv</sublink>
</link>
<thumbnail>http://image.tmdb.org/t/p/original/2l4qtlW6UDnfpD7Iy2XyZHedZ7S.jpg</thumbnail>
</item>

<item>Stories CC
<title>Deuce Bigalow: Male Gigolo (1999)</title>
<link>
<sublink>http://billionuploads.com/mxvl0y3z4hft</sublink>
<sublink>http://hugefiles.net/z7qisonlqj0s</sublink>
<sublink>http://180upload.com/egxgc7b7a6o3</sublink>
<sublink></sublink>
</link>
<thumbnail>http://d3gtl9l2a4fn1j.cloudfront.net/t/p/original/2tbD3pIF5lAa1irSQoUr3tW7RKq.jpg</thumbnail>
</item>1999-12-10

<item>Stories CC
<title>Deuce Bigalow: European Gigolo (2005)</title>
<link>
<sublink>http://billionuploads.com/3u64lbmjp3is</sublink>
<sublink>http://hugefiles.net/478p0fzqnlq3</sublink>
<sublink>http://180upload.com/6grbjl6ec2lg</sublink>
<sublink></sublink>
</link>
<thumbnail>http://d3gtl9l2a4fn1j.cloudfront.net/t/p/original/1P8fWex0NzgtPE4cgIUDHrVSARM.jpg</thumbnail>
</item>2005-08-12

<item>
<title>Don Jon (2013)</title>
<link>
<sublink>http://75.126.196.132/index.php?file=2651&start=0&hd=0&auth=37173551f877bf4854313fe84e&type=flv&tv=0</sublink>
<sublink>http://billionuploads.com/jsr8z68qaeqx</sublink>
<sublink>http://billionuploads.com/gbykr7mxpaa0</sublink>
<sublink>http://billionuploads.com/gcbxoxavcpgb</sublink>
<sublink>http://hugefiles.net/9nubu59wmtt2</sublink>
<sublink>http://hugefiles.net/q93llxn3f2w5</sublink>
<sublink>http://hugefiles.net/pdb29dcrwuwm</sublink>
<sublink>http://hugefiles.net/5amor11108sm</sublink>
<sublink>http://180upload.com/blv4hw2q168c</sublink>
<sublink>http://180upload.com/oj2ipvmyi5q8</sublink>
<sublink>http://180upload.com/2r8zn2jehkax</sublink>
<sublink>http://180upload.com/o0z96bctenu7</sublink>
</link>
<thumbnail>http://image.tmdb.org/t/p/original/px0ytgK92aTQ8u7kn04rR2l6uJ5.jpg</thumbnail>
</item>

<item>
<title>Dumb and Dumber (1994)</title>
<link>
<sublink>http://75.126.196.132/index.php?file=1880&start=0&hd=0&auth=37173551f877bf4854313fe84e&type=flv&tv=0</sublink>
<sublink>http://movreel.com/2lcd38eo6v4n</sublink>
<sublink>http://www.putlocker.com/file/0D6937B5251EC99E</sublink>
</link>
<thumbnail>http://d3gtl9l2a4fn1j.cloudfront.net/t/p/original/9KUcIUi0vZ0ctUePKeBouo9dqmN.jpg</thumbnail>
</item>1994-12-16

<item>
<title>Easy A (2010)</title>
<link>
<sublink>http://yify.tv/easy-a/</sublink>
<sublink>http://75.126.196.132/index.php?file=398&start=0&hd=0&auth=37173551f877bf4854313fe84e&type=flv&tv=0</sublink>
<sublink>http://hugefiles.net/bi4hcipelt4u</sublink>
<sublink>http://billionuploads.com/38h4y3df2hpw</sublink>
<sublink>http://180upload.com/8x381tap1r6b</sublink>  
</link>
<thumbnail>http://d3gtl9l2a4fn1j.cloudfront.net/t/p/original/4H8g55l51JFdM1TRWKTyieIle54.jpg</thumbnail>
</item>

<item>
<title>Elf (2003)</title>
<link>
<sublink>http://75.126.196.132/index.php?file=919&start=0&hd=0&auth=37173551f877bf4854313fe84e&type=flv&tv=0</sublink>
<sublink>http://billionuploads.com/csm9t9c1sj5j</sublink>  
</link>
<thumbnail>http://d3gtl9l2a4fn1j.cloudfront.net/t/p/original/2BCvh9w8YXP30Jst8PkMngEo619.jpg</thumbnail>
</item>

<item>
<title>Fletch (1985)</title>
<link>
<sublink>http://75.126.196.132/index.php?file=1876&start=0&hd=0&auth=37173551f877bf4854313fe84e&type=flv&tv=0</sublink>
<sublink>http://megarelease.org/ljocviyfhlxs</sublink>
<sublink>http://lemuploads.com/ljocviyfhlxs</sublink>
<sublink>http://billionuploads.com/renv3612942x</sublink>
<sublink>http://hugefiles.net/y29ap03au9st</sublink>
<sublink>http://180upload.com/lpqvu5ofwp9t</sublink>
<sublink>http://epicshare.net/ljocviyfhlxs</sublink>
<sublink></sublink>
</link>
<thumbnail>http://image.tmdb.org/t/p/original/t8VjThRC6uKvjR5jVlhj5bBBUUy.jpg</thumbnail>
</item>

<item>
<title>Flypaper (2011)</title> 
<link>
<sublink>http://75.126.196.132/index.php?file=2733&start=0&hd=0&auth=37173551f877bf4854313fe84e&type=flv&tv=0</sublink>
<sublink>http://BillionUploads.com/otoqczispfa1</sublink>
<sublink>http://hugefiles.net/nzrtvj3bv7vr</sublink>
<sublink>http://www.putlocker.com/file/756EB29890CB2445</sublink>
<sublink>http://mightyupload.com/hl58f3wkwpk6</sublink>
<sublink>http://180upload.com/q9ibm8l1jr36</sublink>
<sublink>http://epicshare.net/rxpb9amrtcqm</sublink>
<sublink>http://lemuploads.com/rxpb9amrtcqm</sublink>
</link>
<thumbnail>http://d3gtl9l2a4fn1j.cloudfront.net/t/p/original/seYUPkTnd4BAFZEqxWuByEXmUOK.jpg</thumbnail>
</item>2011-08-19

<item>
<title>Forgetting Sarah Marshall (2008)</title>
<link>
<sublink>http://yify.tv/forgetting-sarah-marshall/</sublink>
<sublink>http://75.126.196.132/index.php?file=1153&start=0&hd=0&auth=37173551f877bf4854313fe84e&type=flv&tv=0</sublink>
<sublink>http://hugefiles.net/tevtczozsgy3</sublink>
<sublink>http://180upload.com/vjhoingk202b</sublink>
<sublink>http://movreel.com/5op9klbo17yb</sublink>
</link>
<thumbnail>http://d3gtl9l2a4fn1j.cloudfront.net/t/p/original/wOy0wKHIWpQ94BgpF4SR74TdYrN.jpg</thumbnail>
</item>

<item>
<title>Four Christmases (2008)</title>
<link>
<sublink>http://yify.tv/four-christmases/</sublink>
<sublink>http://hugefiles.net/74eeeojg4osq</sublink>
<sublink>http://180upload.com/sf9qfhcj4drq</sublink>
</link>
<thumbnail>http://d3gtl9l2a4fn1j.cloudfront.net/t/p/original/mdx9zrZQMKVJDI8l2Mtn6lZjEga.jpg</thumbnail>
</item>

<item>
<title>Fred Claus (2007)</title>
<link>
<sublink>http://180upload.com/xfgsq5l0tjyd</sublink>
<sublink>http://billionuploads.com/z6ab8czcbjt9</sublink>
<sublink>http://hugefiles.net/0888ev3hyx5g</sublink>
<sublink>http://180upload.com/19ddq1q3gl8y</sublink>
<sublink>http://www.putlocker.com/file/62E65290442185FB</sublink>
<sublink></sublink>
<sublink></sublink>
<sublink></sublink>
</link>
<thumbnail>http://image.tmdb.org/t/p/original/sgLgHXrpHp2hgqzvFTPH0C6CWhv.jpg</thumbnail>
</item>

<item>Comedy || HD
<title>Freddy Got Fingered (2001)</title>
<link>
<sublink>http://hugefiles.net/er21emwehjxs</sublink>
<sublink>http://www.putlocker.com/file/83DDC9E0AA9B9C3A</sublink>
<sublink>http://180upload.com/p01d0ie38srd</sublink>
<sublink></sublink>
</link>
<thumbnail>http://d3gtl9l2a4fn1j.cloudfront.net/t/p/original/j9OW0LoLHxTokSssf1gGe5P1GUY.jpg</thumbnail>
</item>2001-04-18

<item>
<title>Friday (1995)</title>
<link>http://75.126.196.132/index.php?file=1970&start=0&hd=0&auth=37173551f877bf4854313fe84e&type=flv&tv=0</link>
<thumbnail>http://d3gtl9l2a4fn1j.cloudfront.net/t/p/w500/vqwGmTHPkuonKY0KnUeyJWdKWz4.jpg</thumbnail>
</item>

<item>
<title>Friday After Next (2002)</title>
<link>
<sublink>http://hugefiles.net/g55xoywgij5e</sublink>
<sublink>http://180upload.com/afx5o99n46m4</sublink>
<sublink>http://epicshare.net/1sk2rfvabivw/Sevqnl_Nsgre_Arkg_720.divx.html</sublink>
<sublink>http://bayfiles.net/file/12gAZ/DPobAh/Sevqnl_Nsgre_Arkg_720.divx</sublink>
</link>
<thumbnail>http://image.tmdb.org/t/p/original/31xIR4n1F1yJlGBe8ZFXGOFQ11e.jpg</thumbnail>
</item>

<item>
<title>Friends With Benefits (2011)</title>
<link>
<sublink>http://yify.tv/friends-benefits/</sublink>
<sublink>http://75.126.196.132/index.php?file=1176&start=0&hd=0&auth=37173551f877bf4854313fe84e&type=flv&tv=0</sublink>
<sublink>http://billionuploads.com/59uru2kue08d</sublink>
<sublink>http://movreel.com/1mnakj3svfj2</sublink>
<sublink>http://180upload.com/442qoqv6hsi3</sublink>  
</link>
<thumbnail>http://d3gtl9l2a4fn1j.cloudfront.net/t/p/original/tmVuyRSS9RYFs73YGbMnFous7DH.jpg</thumbnail>
</item>

<item>
<title>Fun With Dick and Jane (2005)</title>
<link>
<sublink>http://hugefiles.net/aw30nh2pnh7o</sublink>
<sublink>http://www.putlocker.com/file/A3AC02C38AE6D64A</sublink>
<sublink>http://180upload.nl/qzopxzgalnsj</sublink>  
</link>
<thumbnail>http://d3gtl9l2a4fn1j.cloudfront.net/t/p/original/nevy1DCIpEOqeuqrBjeSHCrNLQ9.jpg</thumbnail>
</item>2005-12-21

<item>
<title>Get Smart (2008)</title>
<link>
<sublink>http://75.126.196.132/index.php?file=2560&start=0&hd=0&auth=37173551f877bf4854313fe84e&type=flv&tv=0</sublink>
<sublink>http://180upload.com/9tekz6yzrita</sublink>
<sublink>http://movreel.com/6guzxnvtwsfx</sublink>
<sublink></sublink>
</link>
<thumbnail>http://d3gtl9l2a4fn1j.cloudfront.net/t/p/original/zS3UhYJvy6oLTBgNckpoyAa0qNs.jpg</thumbnail>
</item>2008-06-19

<item>
<title>Grown Ups (2010)</title>
<link>
<sublink>http://75.126.196.132/index.php?file=1318&start=0&hd=0&auth=37173551f877bf4854313fe84e&type=flv&tv=0</sublink>
<sublink>http://billionuploads.com/acepa98xkjh6</sublink>
<sublink>http://180upload.com/yau530kl01eu</sublink>
<sublink>http://epicshare.net/88jp368ghsg1</sublink>
</link>
<thumbnail>http://d3gtl9l2a4fn1j.cloudfront.net/t/p/original/rKPU178ngGRXPYnuO3cpCnZP6wJ.jpg</thumbnail>
</item>

<item>
<title>Grown Ups 2 (2013)</title>
<link>
<sublink>http://75.126.196.132/index.php?file=2346&start=0&hd=0&auth=37173551f877bf4854313fe84e&type=flv&tv=0</sublink>
<sublink>http://billionuploads.com/qtkid4my7qwh</sublink>
<sublink>http://billionuploads.com/6yhxgtbcjdef</sublink>
<sublink>http://hugefiles.net/91k7ab1kt3f8</sublink>
<sublink>http://hugefiles.net/micyggyf9vuu</sublink>
<sublink>http://180upload.com/hgmfydgu0s1v</sublink>
<sublink>http://180upload.com/9ic66wr3srkk</sublink>
<sublink>http://epicshare.net/d27u9lhb2tsi</sublink>
<sublink>http://epicshare.net/5suba6f1rh05</sublink>
</link>
<thumbnail>http://d3gtl9l2a4fn1j.cloudfront.net/t/p/original/t4K0XdjYkhd9BXXpGVVIj0DXBgV.jpg</thumbnail>
</item>

<item>
<title>Harold & Kumar Go to White Castle (2004)</title>
<link>
<sublink>http://75.126.196.132/index.php?file=790&start=0&hd=0&auth=37173551f877bf4854313fe84e&type=flv&tv=0</sublink>
<sublink>http://billionuploads.com/trqnp3gz4ulh</sublink>
<sublink>http://hugefiles.net/dvxr3xbswi89</sublink>
<sublink>http://180upload.com/d3n5k0s72i4j</sublink>
</link>
<thumbnail>http://d3gtl9l2a4fn1j.cloudfront.net/t/p/original/1YwdPBFdDHUNtqizm7cojoZdys9.jpg</thumbnail>
</item>2004-05-30

<item>
<title>Harold & Kumar Escape from Guantanamo Bay (2008)</title>
<link>
<sublink>http://75.126.196.132/index.php?file=791&start=0&hd=0&auth=37173551f877bf4854313fe84e&type=flv&tv=0</sublink>
<sublink>http://billionuploads.com/1joodjp8a722</sublink>
<sublink>http://hugefiles.net/zisqbobz1269</sublink>
<sublink>http://180upload.com/buernin0gnhn</sublink>
</link>
<thumbnail>http://d3gtl9l2a4fn1j.cloudfront.net/t/p/original/z4lpTfIhZAhjDofn0poJk8EUuyg.jpg</thumbnail>
</item>2008-04-25

<item>
<title>A Very Harold & Kumar Christmas (2011)</title>
<link>
<sublink>http://75.126.196.132/index.php?file=792&start=0&hd=0&auth=37173551f877bf4854313fe84e&type=flv&tv=0</sublink>
<sublink>http://billionuploads.com/yjdd6r4psn84</sublink>
<sublink>http://hugefiles.net/rwxnbg8ghv6y</sublink>
<sublink>http://180upload.com/cl5mgu3f044x</sublink>
</link>
<thumbnail>http://d3gtl9l2a4fn1j.cloudfront.net/t/p/original/8zdGMb5lfq2JB5OpipASK85URHC.jpg</thumbnail>
</item>2011-11-04

<item>Comedy || HD
<title>Here Comes the Boom (2012)</title>
<link>
<sublink>http://75.126.196.132/index.php?file=706&start=0&hd=0&auth=37173551f877bf4854313fe84e&type=flv&tv=0</sublink>
<sublink>http://billionuploads.com/lmavw1a840wj</sublink>
<sublink>http://billionuploads.com/mduv6yztkch0</sublink>
<sublink>http://billionuploads.com/aerfh9c6mlw9</sublink>
<sublink>http://hugefiles.net/a81iip3jrbfx</sublink>
<sublink>http://180upload.com/k0mojmkqp0ly</sublink>
<sublink>http://180upload.com/4dnrxhhomx4f</sublink>
</link>
<thumbnail>http://d3gtl9l2a4fn1j.cloudfront.net/t/p/original/agIDCekE8390PnKoAxCeMnBn37X.jpg</thumbnail>
</item>2012-10-12

<item>
<title>Horrible Bosses (2011)</title>
<link>
<sublink>http://75.126.196.132/index.php?file=1144&start=0&hd=0&auth=37173551f877bf4854313fe84e&type=flv&tv=0</sublink>
<sublink>http://billionuploads.com/d57ccrh3a3cv</sublink>  
</link>
<thumbnail>http://d3gtl9l2a4fn1j.cloudfront.net/t/p/original/upWyIFvbOHEnhvvjdQvYXQp2xvT.jpg</thumbnail>
</item>

<item>
<title>How Do You Know (2010)</title>
<link>
<sublink>http://75.126.196.132/index.php?file=1727&start=0&hd=0&auth=37173551f877bf4854313fe84e&type=flv&tv=0</sublink>
<sublink>http://yify.tv/know/</sublink>
<sublink>http://hugefiles.net/7hc30844j1gu</sublink>
<sublink>http://180upload.com/40b2k4540al5</sublink>
<sublink>http://movreel.com/wyhmaey9j68v</sublink>
</link>
<thumbnail>http://image.tmdb.org/t/p/original/xt0Qa0HZvMd70tU2AD49HmEWXUx.jpg</thumbnail>
</item>

<item>
<title>Identity Thief (2013)</title>
<link>http://75.126.196.132/index.php?file=1575&start=0&hd=0&auth=37173551f877bf4854313fe84e&type=flv&tv=0</link>
<thumbnail>http://ia.media-imdb.com/images/M/MV5BMTY3NzM5MTk2Nl5BMl5BanBnXkFtZTcwMDQ4MjQ3OA@@._V1._SX640_SY1013_.jpg</thumbnail>
</item>

<item>
<title>Inglourious Basterds (2009)</title>
<link>
<sublink>http://75.126.196.132/index.php?file=771&start=0&hd=0&auth=37173551f877bf4854313fe84e&type=flv&tv=0</sublink>
<sublink>http://billionuploads.com/c4r5kdepzn97</sublink>
<sublink>http://movreel.com/f0w0zn3uil32</sublink>
<sublink>http://180upload.com/weps2pjhh6ie</sublink>  
</link>
<thumbnail>http://d3gtl9l2a4fn1j.cloudfront.net/t/p/original/vDwqPyhkzFPRDmwz9KbzN2ouEPe.jpg</thumbnail>
</item>

<item>
<title>It's Kind of a Funny Story (2010)</title>
<link>
<sublink>http://75.126.196.132/index.php?file=545&start=0&hd=0&auth=37173551f877bf4854313fe84e&type=flv&tv=0</sublink>
<sublink>http://billionuploads.com/j9lgvn4588p0</sublink>
<sublink>http://hugefiles.net/kn2z7exw3xkc</sublink>
<sublink>http://180upload.com/sfsmhnfhg34l</sublink>
<sublink>http://movreel.com/z0np3ke6w903</sublink>
</link>
<thumbnail>http://image.tmdb.org/t/p/original/gByFsMLAMAJCfm7sZKVXxYzT4mJ.jpg</thumbnail>
</item>

<item>
<title>Just Friends (2005)</title>
<link>http://75.126.196.132/index.php?file=775&start=0&hd=0&auth=37173551f877bf4854313fe84e&type=flv&tv=0</link>
<thumbnail>http://image.tmdb.org/t/p/original/ezMxdtz5xUtnAva8bYJeHcfnhpD.jpg</thumbnail>
</item>

<item>
<title>Just Married (2003)</title>
<link>
<sublink>http://75.126.196.132/index.php?file=328&start=0&hd=0&auth=37173551f877bf4854313fe84e&type=flv&tv=0</sublink>
<sublink>http://yify.tv/just-married/</sublink>
<sublink>http://billionuploads.com/8d4h1xj2ndvx</sublink>
<sublink>http://hugefiles.net/hhbvhk4d42h8</sublink>
<sublink>http://180upload.com/56pixf5rdk22</sublink>
<sublink>http://movreel.com/q1p66y5kbude</sublink>
</link>
<thumbnail>http://image.tmdb.org/t/p/original/71S7RIiZsOh1PWM0RruQUPlMP7t.jpg</thumbnail>
</item>


<item>DVD
<title>Kicking & Screaming (2005)</title>
<link>http://veehd.com/video/4724484_Kicking-And-Screaming-2005-DVDRip-XviD-DiAMOND-avi</link>
<thumbnail>http://d3gtl9l2a4fn1j.cloudfront.net/t/p/original/6348CbPqGwuo2DkNUwtp2VAjAQy.jpg</thumbnail>
</item>

<item>
<title>Knocked Up (2007)</title>
<link>
<sublink>http://75.126.196.132/index.php?file=877&start=0&hd=0&auth=37173551f877bf4854313fe84e&type=flv&tv=0</sublink>
<sublink>http://billionuploads.com/javvoylua4ro</sublink>
<sublink>http://movreel.com/auosonzg8j8t</sublink>
<sublink>http://180upload.com/kjqs24xksm3y</sublink>
</link>
<thumbnail>http://d3gtl9l2a4fn1j.cloudfront.net/t/p/original/1jnXqREQL7Gn1mRnHvG47dgPZuO.jpg</thumbnail>
</item>2007-06-01

<item>
<title>Land of the Lost (2009)</title>
<link>
<sublink>http://75.126.196.132/index.php?file=515&start=0&hd=0&auth=37173551f877bf4854313fe84e&type=flv&tv=0</sublink>
<sublink>http://billionuploads.com/4g89xe3wncp2</sublink>
<sublink>http://hugefiles.net/nprv8ni575i1</sublink>
<sublink>http://180upload.com/wp930z9f9ddz</sublink>
<sublink>http://epicshare.net/l3m39m5k8qyr</sublink>  
</link>
<thumbnail>http://d3gtl9l2a4fn1j.cloudfront.net/t/p/original/3IbnzTz3ll0lMJUonuxjH4x7GyR.jpg</thumbnail>
</item>

<item>
<title>Lay The Favorite (2012)</title>
<link>
<sublink>http://75.126.196.132/index.php?file=1789&start=0&hd=0&auth=37173551f877bf4854313fe84e&type=flv&tv=0</sublink>
<sublink>http://hugefiles.net/qffy9bcmnoeb</sublink>
<sublink>http://180upload.com/kgudg06zz2xv</sublink>
<sublink>http://epicshare.net/tt1pcd0i2vvm</sublink>  
<sublink>http://billionuploads.com/7w6uyv91r9th</sublink>
<sublink>http://movreel.com/at0gmfode5vm</sublink>
</link>
<thumbnail>http://ia.media-imdb.com/images/M/MV5BMTY2MzUyMDAyNF5BMl5BanBnXkFtZTcwMDAyNDg2OA@@._V1._SX365_SY541_.jpg</thumbnail>
</item>

<item>
<title>Love Actually (2003)</title>
<link>
<sublink>http://75.126.196.132/index.php?file=1345&start=0&hd=0&auth=37173551f877bf4854313fe84e&type=flv&tv=0</sublink>
<sublink>http://yify.tv/love-actually/</sublink>
<sublink>http://hugefiles.net/xdyb7k7oixfo</sublink>
<sublink>http://www.putlocker.com/file/61831E4BD98EC613</sublink>
<sublink>http://movreel.com/ntojzm0tip3g</sublink>
</link>
<thumbnail>http://image.tmdb.org/t/p/original/u31LfJTP8FZGnTE3kEDUATYEX00.jpg</thumbnail>
</item>

<item>
<title>Marley & Me (2008)</title>
<link>http://75.126.196.132/index.php?file=2376&start=0&hd=0&auth=37173551f877bf4854313fe84e&type=flv&tv=0</link>
<thumbnail>http://image.tmdb.org/t/p/original/rArV0zJfHYwpLuaMmswhpDShrSo.jpg</thumbnail>
</item>

<item>
<title>Me, Myself & Irene (2000)</title>
<link>
<sublink>http://75.126.196.132/index.php?file=414&start=0&hd=0&auth=37173551f877bf4854313fe84e&type=flv&tv=0</sublink>
<sublink>http://billionuploads.com/bexebygg76yt</sublink>
<sublink>http://hugefiles.net/8ul1dx0r9ljp</sublink>
<sublink>http://180upload.com/oesl6v2y317e</sublink>
<sublink>http://movreel.com/tu6hm4ii3r5z</sublink>
<sublink>http://yify.tv/me-myself-irene/</sublink>
</link>
<thumbnail>http://image.tmdb.org/t/p/original/6wuDQ4LbWymk6NtQAItH0qlAxBU.jpg</thumbnail>
</item>


<item>
<title>Mixed Nuts (1994)</title>
<link>
<sublink>http://veehd.com/video/4569510_Mixed-Nuts-1994-PG13</sublink>
<sublink>http://veehd.com/video/4281576_Mixed-Nuts-1994-divx</sublink>
</link>
<thumbnail>http://image.tmdb.org/t/p/original/l7bDeD6JAxOsMlb8luOukVihnp2.jpg</thumbnail>
</item>

<item>
<title>Mo' Money (1992)</title>
<link>
<sublink>http://yify.tv/mo-money/</sublink>
<sublink>http://sharesix.com/my1fn0iiotme</sublink>
</link>
<thumbnail>http://image.tmdb.org/t/p/original/6gSsuEJfZx7p0iu3Ymiyx0vo1EF.jpg</thumbnail>
</item>

<item>
<title>National Lampoon's Christmas Vacation (1989)</title>
<link>http://75.126.196.132/index.php?file=2088&start=0&hd=0&auth=37173551f877bf4854313fe84e&type=flv&tv=0</link>
<thumbnail>http://image.tmdb.org/t/p/original/waDdzvM4iFrVWUaIm3CdSLptDvb.jpg</thumbnail>
</item>

<item>
<title>Nick and Norah's Infinite Playlist (2008)</title>
<link>http://75.126.196.132/index.php?file=3100&start=0&hd=0&auth=37173551f877bf4854313fe84e&type=flv&tv=0</link>
<thumbnail>http://image.tmdb.org/t/p/original/sggr48vcHCp2Q9M23PEVP4zUQl9.jpg</thumbnail>
</item>

<item>
<title>Night at the Roxbury (1998)</title>
<link>http://75.126.196.132/index.php?file=2259&start=0&hd=0&auth=37173551f877bf4854313fe84e&type=flv&tv=0</link>
<thumbnail>http://d3gtl9l2a4fn1j.cloudfront.net/t/p/original/2FtgYPCD47IZ1yUgr05Zn87M98o.jpg</thumbnail>
</item>

<item>
<title>Nine Months (1995)</title>
<link>
<sublink>http://www.firedrive.com/file/BCEF270F3DBFE31B</sublink>
<sublink>http://www.sockshare.com/file/2FFF182427FF1EC0</sublink>
<sublink>http://veehd.com/video/2473036_NINE-MONTHS-1995-Hugh-Grant-Julianne-Moore</sublink>
</link>
<thumbnail>http://image.tmdb.org/t/p/original/dOFI47473NLppWseV2kSRcEmL3Z.jpg</thumbnail>
</item>

<item>
<title>Old School (2003)</title>
<link>
<sublink>http://75.126.196.132/index.php?file=1254&start=0&hd=0&auth=37173551f877bf4854313fe84e&type=flv&tv=0</sublink>
<sublink>http://billionuploads.com/fp24tsfae0y0</sublink>
<sublink>http://movreel.com/3ss3t17szavq</sublink>  
<sublink>http://180upload.com/x1squvp56amd</sublink>
</link>
<thumbnail>http://d3gtl9l2a4fn1j.cloudfront.net/t/p/original/9m8C8xJSj6pSKnzek3RKPZkvcUr.jpg</thumbnail>
</item>

<item>
<title>Paul (2011)</title>
<link>
<sublink>http://75.126.196.132/index.php?file=1754&start=0&hd=0&auth=37173551f877bf4854313fe84e&type=flv&tv=0</sublink>
<sublink>http://billionuploads.com/8o0itj3amv5u</sublink>
<sublink>http://180upload.com/p0zai81s932g</sublink>
<sublink>http://epicshare.net/nkq2yttn68jj</sublink>
</link>
<thumbnail>http://image.tmdb.org/t/p/original/297N75COL0NsJJY5k5U8VTJ1DCe.jpg</thumbnail>
</item>

<item>
<title>Paul Blart: Mall Cop (2009)</title>
<link>http://75.126.196.132/index.php?file=88&start=0&hd=0&auth=37173551f877bf4854313fe84e&type=flv&tv=0</link>
<thumbnail>http://image.tmdb.org/t/p/original/1NC8lXx5u8L6H3CsdySYnZPt85R.jpg</thumbnail>
</item>

<item>
<title>Pineapple Express (2008)</title>
<link>
<sublink>http://75.126.196.132/index.php?file=18&start=0&hd=0&auth=37173551f877bf4854313fe84e&type=flv&tv=0</sublink>
<sublink>http://billionuploads.com/4wxzo8hprxvv</sublink>
<sublink>http://movreel.com/hzsfnz8dp4zu</sublink>
<sublink>http://180upload.com/n2g5v9pwdj75</sublink>
</link>
<thumbnail>http://d3gtl9l2a4fn1j.cloudfront.net/t/p/original/azuRBzuTOCSMXoy7sXJPNbSIOzD.jpg</thumbnail>
</item>

<item>
<title>Robin Hood: Men in Tights (1993)</title>
<link>
<sublink>http://75.126.196.132/index.php?file=3156&start=0&hd=0&auth=37173551f877bf4854313fe84e&type=flv&tv=0</sublink>
<sublink>http://yify.tv/robin-hood-men-tights/</sublink>
</link>
<thumbnail>http://image.tmdb.org/t/p/original/3pd3sdot0HfQTFzqgTUzaF4kcxP.jpg</thumbnail>
</item>

<item>
<title>Semi-Pro (2008)</title>
<link>http://75.126.196.132/index.php?file=609&start=0&hd=0&auth=37173551f877bf4854313fe84e&type=flv&tv=0</link>
<thumbnail>hhttp://d3gtl9l2a4fn1j.cloudfront.net/t/p/original/pwFUCEBf0wdFeqE0tprA8XYSjNS.jpg</thumbnail>
</item>

<item>
<title>Silver Linings Playbook (2012)</title>
<link>
<sublink>http://yify.tv/silver-linings-playbook/</sublink>
<sublink>http://75.126.196.132/index.php?file=1273&start=0&hd=0&auth=37173551f877bf4854313fe84e&type=flv&tv=0</sublink>
<sublink>http://hugefiles.net/i7w1e2ow34t2</sublink>
<sublink>http://180upload.com/vmtq50ucndg5</sublink>
<sublink>http://billionuploads.com/mwpiril7rypj</sublink>  
</link>
<thumbnail>http://ia.media-imdb.com/images/M/MV5BMTM2MTI5NzA3MF5BMl5BanBnXkFtZTcwODExNTc0OA@@._V1._SX640_SY948_.jpg</thumbnail>
</item>

<item>
<title>Snatch (2000)</title>
<link>
<sublink>http://75.126.196.132/index.php?file=1221&start=0&hd=0&auth=37173551f877bf4854313fe84e&type=flv&tv=0</sublink>
<sublink>http://yify.tv/snatch/</sublink>
<sublink>http://billionuploads.com/7rrecvel6azk</sublink>
<sublink>http://hugefiles.net/vyikbsdmq9c0</sublink>
<sublink>http://180upload.com/0bw8f9p0z8sr</sublink>
</link>
<thumbnail>http://image.tmdb.org/t/p/original/ofQyAPukLmKPcSoJ9y1sbr5tUTZ.jpg</thumbnail>
</item>

<item>
<title>Someone Marry Barry (2014) HD</title>
<link>
<sublink>http://billionuploads.com/ehny87wemh6h</sublink>
<sublink>http://hugefiles.net/68kd2t66gu1b</sublink>
<sublink>http://180upload.com/cktvw6g8o5dt</sublink>
</link>
<thumbnail>http://image.tmdb.org/t/p/original/7qLHSBvML6pzXTIFUglG7awJ8Vx.jpg</thumbnail>
</item>

<item>
<title>Something's Gotta Give (2003)</title>
<link>
<sublink>http://hugefiles.net/veq08wnot2f0</sublink>
<sublink>http://lemuploads.com/9h7fxpu3f1fl</sublink>
<sublink>http://megarelease.org/9h7fxpu3f1fl</sublink>
<sublink>http://epicshare.net/9h7fxpu3f1fl</sublink>
</link>
<thumbnail>http://image.tmdb.org/t/p/original/n3DgWqXkAmQigx5Y4BgcdkCmBJp.jpg</thumbnail>
</item>

<item>
<title>Step Brothers (2008)</title>
<link>
<sublink>http://75.126.196.132/index.php?file=899&start=0&hd=0&auth=37173551f877bf4854313fe84e&type=flv&tv=0</sublink>
<sublink>http://billionuploads.com/be797tcph2w9</sublink>
<sublink>http://movreel.com/n4jvwu8kkbhb</sublink>
<sublink>http://180upload.com/gsyipdv3euej</sublink>  
</link>
<thumbnail>http://d3gtl9l2a4fn1j.cloudfront.net/t/p/original/tDFNUuYkQ4ZeAlrBHeTtimAumXo.jpg</thumbnail>
</item>

<item>
<title>Superbad (2007)</title>
<link>
<sublink>http://75.126.196.132/index.php?file=1939&start=0&hd=0&auth=37173551f877bf4854313fe84e&type=flv&tv=0</sublink>
<sublink>http://billionuploads.com/s6gegmoogoge</sublink>
<sublink>http://hugefiles.net/czulcj7rqx1f</sublink>
</link>
<thumbnail>http://d3gtl9l2a4fn1j.cloudfront.net/t/p/original/AhAyjWZcyEkkhlVpTw9XMnxmWOx.jpg</thumbnail>
</item>

<item>
<title>Super Troopers (2001)</title>
<link>
<sublink>http://75.126.196.132/index.php?file=1753&start=0&hd=0&auth=37173551f877bf4854313fe84e&type=flv&tv=0</sublink>
<sublink>http://yify.tv/super-troopers/</sublink>
<sublink>http://billionuploads.com/w8gy47pd3hn3</sublink>
<sublink>http://hugefiles.net/xi4w9fy87or2</sublink>
<sublink>http://180upload.com/v6idvhw8omyz</sublink>
<sublink>http://movreel.com/i1zo7jekqdox</sublink>
</link>
<thumbnail>http://image.tmdb.org/t/p/original/4SxDHZIFJzNC0Vxvb7tayrrxiyG.jpg</thumbnail>
</item>

<item>
<title>Surviving Christmas (2004)</title>
<link>
<sublink>http://75.126.196.132/index.php?file=2534&start=0&hd=0&auth=37173551f877bf4854313fe84e&type=flv&tv=0</sublink>
<sublink>http://hugefiles.net/xnmvq24rl198</sublink>
<sublink>http://hugefiles.net/ybvppxx0iv3c</sublink>
<sublink>http://180upload.com/u6ii1kesjwlq</sublink>
</link>
<thumbnail>http://image.tmdb.org/t/p/original/yLvm5bfd2NGeRETB7G5ks0eWnhv.jpg</thumbnail>
</item>

<item>
<title>Talladega Nights: The Ballad of Ricky Bobby (2006)</title>
<link>
<sublink>http://75.126.196.132/index.php?file=1289&start=0&hd=0&auth=37173551f877bf4854313fe84e&type=flv&tv=0</sublink>
<sublink>http://veehd.com/video/4672026_Talladega-Nights-The-Ballad-of-Ricky-Bobby-2006</sublink>  
</link>
<thumbnail>http://d3gtl9l2a4fn1j.cloudfront.net/t/p/original/iDK2dXKAfU77Yh9urBysCFqEVxQ.jpg</thumbnail>
</item>

<item>
<title>Ted (2012)</title>
<link>
<sublink>http://75.126.196.132/index.php?file=4&start=0&hd=0&auth=37173551f877bf4854313fe84e&type=flv&tv=0</sublink>
<sublink>http://billionuploads.com/9xcms31vv041</sublink>
<sublink>http://hugefiles.net/6hcfrpmqdvi2</sublink>
<sublink>http://movreel.com/tobb4kiewpqv</sublink>
<sublink>http://180upload.com/zfidpjelu1wp</sublink>
<sublink>http://epicshare.net/3fy2hklo9eex</sublink>  
</link>
<thumbnail>http://d3gtl9l2a4fn1j.cloudfront.net/t/p/original/eaYvlraJipjdJjePZeUXkj7qO60.jpg</thumbnail>
</item>

<item>
<title>The 40 Year Old Virgin (2005)</title>
<link>
<sublink>http://75.126.196.132/index.php?file=876&start=0&hd=0&auth=37173551f877bf4854313fe84e&type=flv&tv=0</sublink>
<sublink>http://billionuploads.com/rgihrm2spbp9</sublink>
<sublink>http://hugefiles.net/qmjsl37ifn3v</sublink>
<sublink>http://movreel.com/p79acp151ttf</sublink>
<sublink>http://180upload.com/yhwp1johfztn</sublink>
<sublink></sublink>
<sublink></sublink>
<sublink></sublink>
<sublink></sublink>
<sublink></sublink>
</link>
<thumbnail>http://d3gtl9l2a4fn1j.cloudfront.net/t/p/original/pHZEtw6YxupuFsSScRFtm20dkDv.jpg</thumbnail>
</item>8/11/05

<item>
<title>The Big Wedding (2013)</title>
<link>
<sublink>http://yify.tv/big-wedding/</sublink>
<sublink>http://75.126.196.132/index.php?file=1958&start=0&hd=0&auth=37173551f877bf4854313fe84e&type=flv&tv=0</sublink>
<sublink>http://180upload.com/wx93690299ot</sublink>
<sublink>http://epicshare.net/i488akfb3gbf</sublink>
<sublink>http://epicshare.net/sohtbi7szyv1</sublink> 
</link>
<thumbnail>http://ia.media-imdb.com/images/M/MV5BMTcwODUwMjg2Ml5BMl5BanBnXkFtZTcwMTc2NzkxOA@@._V1._SX640_SY948_.jpg</thumbnail>
</item>

<item>
<title>The Break-Up (2006)</title>
<link>http://75.126.196.132/index.php?file=1886&start=0&hd=0&auth=37173551f877bf4854313fe84e&type=flv&tv=0</link>
<thumbnail>http://d3gtl9l2a4fn1j.cloudfront.net/t/p/original/wjbKWg1Zcu70mNWo5SzqMkQlQQe.jpg</thumbnail>
</item>2006-06-02

<item>
<title>The Cable Guy (1996)</title>
<link>http://www.putlocker.com/file/B7F1B6B9290B9C76</link>
<thumbnail>http://d3gtl9l2a4fn1j.cloudfront.net/t/p/original/yx3jzfpZE3jeIQxsaHRPttBHXKI.jpg</thumbnail>
</item>

<item>
<title>The Campaign (2012)</title>
<link>
<sublink>http://75.126.196.132/index.php?file=78&start=0&hd=0&auth=37173551f877bf4854313fe84e&type=flv&tv=0</sublink>
<sublink>http://billionuploads.com/fr31imj055fb</sublink>
<sublink>http://movreel.com/qz4ifo3z2093</sublink>  
</link>
<thumbnail>http://d3gtl9l2a4fn1j.cloudfront.net/t/p/original/6uH8BOWN60mu2Vd5z4jCaVWb2ix.jpg</thumbnail>
</item>

<item>
<title>The Family Stone (2005)</title>
<link>
<sublink>http://billionuploads.com/9tpfzgx1vu3v</sublink>
<sublink>http://hugefiles.net/r6fpgiudax5j</sublink>
<sublink>http://180upload.com/1s4oamhymqkm</sublink>
<sublink>http://movreel.com/fdakwksuw3j7.html</sublink>
<sublink>http://www.putlocker.com/file/3B41F75685F96AA4</sublink>
<sublink></sublink>
<sublink></sublink>
<sublink></sublink>
</link>
<thumbnail>http://image.tmdb.org/t/p/original/m9JjA1pPVMZKmJkShq6iTrItkUW.jpg</thumbnail>
</item>

<item>
<title>The Hangover (2009)</title>
<link>
<sublink>http://75.126.196.132/index.php?file=1146&start=0&hd=0&auth=37173551f877bf4854313fe84e&type=flv&tv=0</sublink>
</link>
<thumbnail>http://ia.media-imdb.com/images/M/MV5BMTU1MDA1MTYwMF5BMl5BanBnXkFtZTcwMDcxMzA1Mg@@._V1_SX214_.jpg</thumbnail>
</item>

<item>
<title>The Hangover Part II (2011)</title>
<link>
<sublink>http://75.126.196.132/index.php?file=1147&start=0&hd=0&auth=37173551f877bf4854313fe84e&type=flv&tv=0</sublink>
<sublink>http://180upload.com/ins5g6unmhkx</sublink>
<sublink>http://180upload.com/wr3yflhhtbit</sublink>  
</link>
<thumbnail>http://ia.media-imdb.com/images/M/MV5BMTM2MTM4MzY2OV5BMl5BanBnXkFtZTcwNjQ3NzI4NA@@._V1_SY317_CR0,0,214,317_.jpg</thumbnail>
</item>

<item>
<title>The Hangover Part III (2013)</title>
<link>
<sublink>http://75.126.196.132/index.php?file=2171&start=0&hd=0&auth=37173551f877bf4854313fe84e&type=flv&tv=0</sublink>
<sublink>http://billionuploads.com/8xvact2smk8a</sublink>
<sublink>http://billionuploads.com/g9i5a6c9mcsw</sublink>
<sublink>http://hugefiles.net/3fuucxkk5jgo</sublink>
<sublink>http://hugefiles.net/qt1xvyarcte9</sublink>
<sublink>http://hugefiles.net/zkowip356ito</sublink>
<sublink>http://180upload.com/643v7lu4kg3e</sublink>
<sublink>http://180upload.com/w5n29k67tcqq</sublink>
<sublink>http://180upload.com/8b6b3uuyo5xb</sublink>
</link>
<thumbnail>http://ia.media-imdb.com/images/M/MV5BMTA0NjE1MzMzODheQTJeQWpwZ15BbWU3MDY4MTQ3Mzk@._V1._SX640_SY988_.jpg</thumbnail>
</item>

<item>
<title>The Heartbreak Kid (2007)</title>
<link>
<sublink>http://75.126.196.132/index.php?file=1882&start=0&hd=0&auth=37173551f877bf4854313fe84e&type=flv&tv=0</sublink>
<sublink>http://yify.tv/heartbreak-kid/</sublink>
<sublink>http://hugefiles.net/0bafy4ywl2jy</sublink>
<sublink>http://180upload.com/rge5q785lxje</sublink>
<sublink>http://movreel.com/tbq8mth0u2y3</sublink>
</link>
<thumbnail>http://d3gtl9l2a4fn1j.cloudfront.net/t/p/original/fYUc7bKhhC3uwiFjyeRbu1USKOE.jpg</thumbnail>
</item>1/8/2007

<item>
<title>The Heat (2013)</title>
<link>
<sublink>http://75.126.196.132/index.php?file=2292&start=0&hd=0&auth=37173551f877bf4854313fe84e&type=flv&tv=0</sublink>
<sublink>http://megarelease.org/fghfzbb7brwg</sublink>
<sublink>http://lemuploads.com/fghfzbb7brwg</sublink>
<sublink>http://hugefiles.net/ka3s0wovwdlp</sublink>
<sublink>http://epicshare.net/fghfzbb7brwg</sublink>
<sublink>http://180upload.com/v0u5kqhe9ex5</sublink>
</link>
<thumbnail>http://ia.media-imdb.com/images/M/MV5BNDEwMTg2OTI5MF5BMl5BanBnXkFtZTcwNjgyNjkzOQ@@._V1._SX640_SY946_.jpg</thumbnail>
</item>

<item>
<title>The Hot Chick (2002)</title>
<link>
<sublink>http://www.firedrive.com/file/66345D0EC1CB8ED0#</sublink>
<sublink>http://www.sockshare.com/file/1F91EDA25EB62627</sublink>
<sublink>http://movreel.com/hlfagbiblor0</sublink>
</link>
<thumbnail>http://image.tmdb.org/t/p/original/4x62UrnMRwqyuMO5Io214yjMaUH.jpg</thumbnail>
</item>

<item>
<title>The Incredible Burt Wonderstone (2013)</title>
<link>
<sublink>http://75.126.196.132/index.php?file=1648&start=0&hd=0&auth=37173551f877bf4854313fe84e&type=flv&tv=0</sublink>
<sublink>http://hugefiles.net/x8kbeb9ddkwn</sublink>  
</link>
<thumbnail>http://ia.media-imdb.com/images/M/MV5BMTk3MDkxMDAyN15BMl5BanBnXkFtZTcwODY5NzQyOQ@@._V1._SX640_SY948_.jpg</thumbnail>
</item>

<item>
<title>The Internship (2013)</title>
<link>
<sublink>http://75.126.196.132/index.php?file=2293&start=0&hd=0&auth=37173551f877bf4854313fe84e&type=flv&tv=0</sublink>
<sublink>http://www.putlocker.com/file/79EB156681DE96A9</sublink>
<sublink>http://billionuploads.com/eaqm4hp2oob1</sublink>
<sublink>http://billionuploads.com/qk27khrmodu8</sublink>
<sublink>http://hugefiles.net/yduo1ihcr80i</sublink>
<sublink>http://180upload.com/j04lcl3ff7of</sublink>
<sublink>http://180upload.com/a8g7plmeyl9i</sublink>
<sublink>http://epicshare.net/isnlo0c2qrco</sublink>
<sublink>http://epicshare.net/t5xn7pyze0u5</sublink>
</link>
<thumbnail>http://ia.media-imdb.com/images/M/MV5BMjM1MzczMDgwOV5BMl5BanBnXkFtZTcwMDM4NjM2OQ@@._V1._SX509_SY755_.jpg</thumbnail>
</item>

<item>
<title>The Other Guys (2010)</title>
<link>
<sublink>http://75.126.196.132/index.php?file=1166&start=0&hd=0&auth=37173551f877bf4854313fe84e&type=flv&tv=0</sublink>
<sublink>http://180upload.com/kbd6kaz12074</sublink>
<sublink>http://180upload.com/omqi8vogqdi4</sublink>  
</link>
<thumbnail>http://d3gtl9l2a4fn1j.cloudfront.net/t/p/original/b4mYjC8kKx32BnCNBQeDCA76WBd.jpg</thumbnail>
</item>

<item>
<title>The Watch (2012)</title>
<link>
<sublink>http://75.126.196.132/index.php?file=1&start=0&hd=0&auth=37173551f877bf4854313fe84e&type=flv&tv=0</sublink>
<sublink>http://billionuploads.com/3t1mri2zc8sr</sublink>
</link>
<thumbnail>http://image.tmdb.org/t/p/original/llVq0170tBmPCcqVuFnV7CilrLj.jpg</thumbnail>
</item>

<item>
<title>There's Something About Mary (1998)</title>
<link>
<sublink>http://75.126.196.132/index.php?file=1103&start=0&hd=0&auth=37173551f877bf4854313fe84e&type=flv&tv=0</sublink>
<sublink>http://billionuploads.com/btjr71cuk1xk</sublink>
<sublink>http://180upload.com/je8l2f8kn84l</sublink>
<sublink>http://movreel.com/evdtb1hi5pu2</sublink>
</link>
<thumbnail>http://image.tmdb.org/t/p/original/wXgkEGjxFak5dJ1mBFSuAXOz5OY.jpg</thumbnail>
</item>

<item>
<title>Think Like a Man (2012)</title>
<link>
<sublink>http://yify.tv/think-like-a-man/</sublink>
<sublink>http://75.126.196.132/index.php?file=635&start=0&hd=0&auth=37173551f877bf4854313fe84e&type=flv&tv=0</sublink>
<sublink>http://billionuploads.com/8gvtujsoui52/Think.Like.A.Man.2012.720p.BluRay.x264.YIFY.mp4</sublink>
<sublink>http://hugefiles.net/lecb2k7ikyzd</sublink>
<sublink>http://movreel.com/o34urvovh3z4.html</sublink>
</link>
<thumbnail>http://image.tmdb.org/t/p/original/xNfuh9Ray1wbpn2j5WQbJFBn0K1.jpg</thumbnail>
</item>

<item>
<title>This Is 40 (2012)</title>
<link>
<sublink>http://yify.tv/this-is-40/</sublink>
<sublink>http://75.126.196.132/index.php?file=1119&start=0&hd=0&auth=37173551f877bf4854313fe84e&type=flv&tv=0</sublink>
<sublink>http://hugefiles.net/rnc51km917g7</sublink>
<sublink>http://180upload.com/qsswvapz5lp5</sublink>
<sublink>http://billionuploads.com/m0xu9k7oap7o</sublink>
<sublink>http://movreel.com/wnc116z5oi8y</sublink>
</link>
<thumbnail>http://d3gtl9l2a4fn1j.cloudfront.net/t/p/original/hwmwJ0BHnKfsOwg4EJyNaB0OUpY.jpg</thumbnail>
</item>

<item>
<title>This Is The End (2013)</title>
<link>
<sublink>http://75.126.196.132/index.php?file=2145&start=0&hd=0&auth=37173551f877bf4854313fe84e&type=flv&tv=0</sublink>
<sublink>http://hugefiles.net/mj9sxgecz3tj</sublink>
<sublink>http://hugefiles.net/jz1zuc3qd9zx</sublink>
<sublink>http://hugefiles.net/jppjso5bi82p</sublink>
<sublink>http://mightyupload.com/g4zcnypktj4f</sublink>
</link>
<thumbnail>http://ia.media-imdb.com/images/M/MV5BMTQxODE3NjM1Ml5BMl5BanBnXkFtZTcwMzkzNjc4OA@@._V1._SX640_SY948_.jpg</thumbnail>
</item>

<item>
<title>Trading Places (1983)</title>
<link>
<sublink>http://hugefiles.net/e1c3wzwszs4m</sublink>
<sublink>http://180upload.com/5fv8eumto7d4</sublink>
</link>
<thumbnail>http://image.tmdb.org/t/p/original/zXX8EEAFoe0EKySuZ00Ku55iefh.jpg</thumbnail>
</item>

<item>
<title>Tropic Thunder (2008)</title>
<link>
<sublink>http://75.126.196.132/index.php?file=878&start=0&hd=0&auth=37173551f877bf4854313fe84e&type=flv&tv=0</sublink>
<sublink>http://veehd.com/video/4509751_Tropic-Thunder-2008-Unrated-BRR-p</sublink>
</link>
<thumbnail>http://d3gtl9l2a4fn1j.cloudfront.net/t/p/original/ue9QdvhpcNPvKQyLY5a5Pd0tagS.jpg</thumbnail>
</item>2008-08-13

<item>
<title>Two Weeks Notice (2002)</title>
<link>
<sublink>http://75.126.196.132/index.php?file=3089&start=0&hd=0&auth=37173551f877bf4854313fe84e&type=flv&tv=0</sublink>
<sublink>http://megarelease.org/7e5e42je97ke</sublink>
<sublink>http://hugefiles.net/86r8d89x1rbv</sublink>
<sublink>http://billionuploads.com/6cvd7ugqw39c</sublink>
<sublink>http://180upload.com/64xr1hahzg61</sublink>
<sublink>http://movreel.com/lt9vd3nsaje2</sublink>
</link>
<thumbnail>http://image.tmdb.org/t/p/original/cEQuP9BunbP9EfH5cw7tlrasmrl.jpg</thumbnail>
</item>


<item>
<title>Wedding Crashers (2005)</title>
<link>
<sublink>http://75.126.196.132/index.php?file=1433&start=0&hd=0&auth=37173551f877bf4854313fe84e&type=flv&tv=0</sublink>
<sublink>http://billionuploads.com/glfbnjv084j2</sublink>
<sublink>http://movreel.com/2213va87bp6o</sublink>
</link>
<thumbnail>http://d3gtl9l2a4fn1j.cloudfront.net/t/p/original/vlnDz1Y3IcBhPyQAqAVtNghx4Eq.jpg</thumbnail>
</item>2005-07-14

<item>
<title>We're The Millers (2013)</title>
<link>
<sublink>http://billionuploads.com/17fyzxh4a144</sublink>
<sublink>http://billionuploads.com/c9q5bw4hxshq</sublink>
<sublink>http://billionuploads.com/brfsoczw87i3</sublink>
<sublink>http://billionuploads.com/5x49ulfg8ria</sublink>
<sublink>http://hugefiles.net/qconmx43fthj</sublink>
<sublink>http://hugefiles.net/ry703cazsor2</sublink>
<sublink>http://hugefiles.net/1gxngd62xwj2</sublink>
<sublink>http://180upload.com/1wl7w1r01k92</sublink>
<sublink>http://180upload.com/xarmiy4g94x1</sublink>
<sublink>http://180upload.com/gurm8gs0ri3b</sublink>
<sublink>http://180upload.com/xqilzl84ilud</sublink>
<sublink>http://epicshare.net/d04tpr1uaa78</sublink>
</link>
<thumbnail>http://d3gtl9l2a4fn1j.cloudfront.net/t/p/original/dhtoaYtcphagRZ1w2Li10yYn7Pe.jpg</thumbnail>
</item>

<item>
<title>Wild Wild West (1999)</title>
<link>
<sublink>http://75.126.196.132/index.php?file=1227&start=0&hd=0&auth=37173551f877bf4854313fe84e&type=flv&tv=0</sublink>
<sublink>http://billionuploads.com/0stcztbvipz2</sublink>
<sublink>http://hugefiles.net/vidy54qjm9fi</sublink>
<sublink>http://180upload.com/u0b3zg7csal3</sublink>
</link>
<thumbnail>http://d3gtl9l2a4fn1j.cloudfront.net/t/p/original/xxMELGBWOZTdQoKZfNNAHIbGrv4.jpg</thumbnail>
</item>

<item>
<title>You, Me and Dupree (2006)</title>
<link>
<sublink>http://75.126.196.132/index.php?file=1891&start=0&hd=0&auth=37173551f877bf4854313fe84e&type=flv&tv=0</sublink>
<sublink>http://movreel.com/beiptajgu5pn</sublink>
<sublink>http://www.putlocker.com/file/4CE9CB32C19DED33</sublink>
<sublink>http://www.putlocker.com/file/2EDEFBFF79631B89</sublink>
</link>
<thumbnail>http://d3gtl9l2a4fn1j.cloudfront.net/t/p/original/9x0edmMwT8Wo7yZgb2CTy3nSwen.jpg</thumbnail>
</item> 2006-07-14

<item>
<title>Your Highness (2011)</title>
<link>
<sublink>http://75.126.196.132/index.php?file=2977&start=0&hd=0&auth=37173551f877bf4854313fe84e&type=flv&tv=0</sublink>
<sublink>http://billionuploads.com/26jplrcadbj7/Your.Highness.2011.UNRATED.720p.BluRay.X264.YIFY.mkv</sublink>
<sublink>http://hugefiles.net/mhrwz9pikm25</sublink>
<sublink>http://180upload.com/11n245x7kn5u</sublink>
<sublink>http://movreel.com/xkast1b8hqqd.html</sublink>
</link>
<thumbnail>http://image.tmdb.org/t/p/original/d0P3WWy3Fc3JuORpdkkHhPrhlVc.jpg</thumbnail>
</item>

<item>
<title>Zoolander (2001)</title>
<link>http://75.126.196.132/index.php?file=1617&start=0&hd=0&auth=37173551f877bf4854313fe84e&type=flv&tv=0</link>
<thumbnail>http://d3gtl9l2a4fn1j.cloudfront.net/t/p/original/zNBryDxDAScAgKat8X18K2Jtg6k.jpg</thumbnail>
</item>2001-09-27













