#######################################################################################################################################
<poster>HackerMil</poster>
<fanart>http://d3gtl9l2a4fn1j.cloudfront.net/t/p/original/49L0c5utmm0A4BkeDafM9BOhyBT.jpg</fanart>
#######################################################################################################################################


<item>
<title>Mission: Impossible (1996)</title>
<link>
<sublink>http://37.58.68.221/index.php?file=1035&start=0&hd=0&auth=0&type=flv&tv=0</sublink>
<sublink>http://billionuploads.com/vga7gdau40qh</sublink>
<sublink>http://hugefiles.net/93zko2pm192i</sublink>
<sublink>http://180upload.com/038n70t7kdw3</sublink>
</link>
<thumbnail>http://d3gtl9l2a4fn1j.cloudfront.net/t/p/original/vmj2PzTLC6xJvshpq8SlaYE3gbd.jpg</thumbnail>
</item>1996-05-21

<item>
<title>Mission: Impossible II (2000)</title>
<link>
<sublink>http://37.58.68.221/index.php?file=1032&start=0&hd=0&auth=0&type=flv&tv=0</sublink>
<sublink>http://billionuploads.com/50vod3u1ckzd</sublink>
<sublink>http://hugefiles.net/d157rfiktx3m</sublink>
<sublink>http://180upload.com/q6dvarcv7nm3</sublink>
</link>
<thumbnail>http://d3gtl9l2a4fn1j.cloudfront.net/t/p/original/yaL80VBDnxe2AoqXrXei5lVEIEP.jpg</thumbnail>
</item> 2000-05-23

<item>
<title>Mission: Impossible III (2006)</title>
<link>
<sublink>http://37.58.68.221/index.php?file=1024&start=0&hd=0&auth=0&type=flv&tv=0</sublink>
<sublink>http://billionuploads.com/q959r85agnv6</sublink>
<sublink>http://hugefiles.net/8bogad0uzb10</sublink>
<sublink>http://180upload.com/y3oqjy41qdhn</sublink>
</link>
<thumbnail>http://d3gtl9l2a4fn1j.cloudfront.net/t/p/original/5tMxKlzRSvA6HoPAuFRcEMoEZsY.jpg</thumbnail>
</item>2006-05-04 

<item>
<title>Mission: Impossible - Ghost Protocol (2011)</title>
<link>
<sublink>http://37.58.68.221/index.php?file=1006&start=0&hd=0&auth=0&type=flv&tv=0</sublink>
<sublink>http://billionuploads.com/zs39y04lc0jj</sublink>
<sublink>http://billionuploads.com/b8ff8k5wr6dk</sublink>
<sublink>http://hugefiles.net/376lpqm0jdy3</sublink>
<sublink>http://180upload.com/wriwio8yojwa</sublink>
</link>
<thumbnail>http://d3gtl9l2a4fn1j.cloudfront.net/t/p/original/96k0SkL6bXqKyOj50hYu3fRRbmV.jpg</thumbnail>
</item>2011-12-21 
