#######################################################################################################################################
<poster>HackerMil</poster>
<fanart>http://farm6.staticflickr.com/5460/10217454264_7eda59c6f3_o.png</fanart>
#######################################################################################################################################


<popup>
<name>[COLOR red]CLICK HERE[/COLOR] [COLOR aqua]FOR INFO ON JOINING THE VIP CLUB AND DETAILS[/COLOR]</name>
<popImage>http://farm3.staticflickr.com/2851/10218170123_bb90f51c7e_o.png</popImage>
<thumbnail>http://farm6.staticflickr.com/5510/10217412394_e1da1b6fcc_o.jpg</thumbnail>
</popup>

<info>
<message>[COLOR aqua]H.M. Messenger:[/COLOR] [COLOR red]NEWS 12/30:[/COLOR] [COLOR yellow]Hugefiles Fixed apply on mash home, Billions fixed also but being blocked by some ISPs in UK.. Please visit STASH NEWS at www.HackermilBlog.Blogspot.com for more NEWS        H.M.[/COLOR]</message>
<thumbnail>http://farm6.staticflickr.com/5341/10218059344_b5e64e2da5_o.png</thumbnail>
</info>



#########################################################################


<dir>
<name>[COLOR lime]ALL[/COLOR] [COLOR aqua]New Additions This Week[/COLOR]</name>
<link>https://raw.github.com/HackerMil/HackerMilsMovieStash/master/Freshout/Directories/All%20New%20Additions%20This%20Week.xml</link>
<thumbnail>http://farm6.staticflickr.com/5490/10217412684_f35c62838d_o.jpg</thumbnail>
</dir>

<dir>
<name>[COLOR aqua]This Week's[/COLOR] [COLOR lime]Movies[/COLOR]</name>
<link>https://raw.github.com/HackerMil/HackerMilsMovieStash/master/Freshout/Directories/This%20Week's%20Movies.xml</link>
<thumbnail>http://farm6.staticflickr.com/5490/10217412684_f35c62838d_o.jpg</thumbnail>
</dir>

<dir>
<name>[COLOR aqua]This Week's[/COLOR] [COLOR lime]Episodes[/COLOR]</name>
<link>https://raw.github.com/HackerMil/HackerMilsMovieStash/master/Freshout/Directories/This%20Week's%20Episodes.xml</link>
<thumbnail>http://farm6.staticflickr.com/5490/10217412684_f35c62838d_o.jpg</thumbnail>
</dir>

<dir>
<name>[COLOR aqua]This Week's[/COLOR] [COLOR lime]Fights[/COLOR]</name>
<link>https://raw.github.com/HackerMil/HackerMilsMovieStash/master/Freshout/Directories/This%20Week's%20Fights.xml</link>
<thumbnail>http://farm6.staticflickr.com/5490/10217412684_f35c62838d_o.jpg</thumbnail>
</dir>

<dir>
<name>[COLOR aqua]This Week's[/COLOR] [COLOR lime]Comedy[/COLOR]</name>
<link>https://raw.github.com/HackerMil/HackerMilsMovieStash/master/Freshout/Directories/This%20%20Week's%20Comedy.xml</link>
<thumbnail>http://farm6.staticflickr.com/5490/10217412684_f35c62838d_o.jpg</thumbnail>
</dir>

<dir>
<name>[COLOR aqua]This Week's[/COLOR] [COLOR lime]Documentaries[/COLOR]</name>
<link>https://raw.github.com/HackerMil/HackerMilsMovieStash/master/Freshout/Directories/This%20Week's%20Documentaries.xml</link>
<thumbnail>http://farm6.staticflickr.com/5490/10217412684_f35c62838d_o.jpg</thumbnail>
</dir>

<dir>
<name>[COLOR aqua]This Week's[/COLOR] [COLOR lime]Directories[/COLOR]</name>
<link>https://raw.github.com/HackerMil/HackerMilsMovieStash/master/Freshout/Directories/This%20Week's%20Directories.xml</link>
<thumbnail>http://farm6.staticflickr.com/5490/10217412684_f35c62838d_o.jpg</thumbnail>
</dir>

<dir>
<name>[COLOR aqua]Latest Episodes[/COLOR]  [COLOR red]ON AIR[/COLOR]</name>
<link>https://raw.github.com/HackerMil/HackerMilsMovieStash/master/Shows/Latest%20Shows.xml</link>
<thumbnail>http://i1367.photobucket.com/albums/r795/HackerMil/Posters/latest.png</thumbnail>
</dir>



################################################################################################


<dir>
<name>[COLOR red]------------------------------ Directories ------------------------------[/COLOR]</name>
<link>nill</link>                             Directories
<thumbnail>nill</thumbnail>
</dir>









<item>
<title>[COLOR lime]------------------------------- Movies ----------------------------------[/COLOR]</title>
<link>nill</link>                                                                         >                  
<thumbnail>nill</thumbnail>
</item>

<item>
<title>[COLOR lime]LATEST[/COLOR] Freezer (2014) HD [COLOR lime]PRE-RELEASE[/COLOR]</title>
<link>
<sublink>http://hugefiles.net/aq4aqn9akhd4</sublink>
<sublink>http://180upload.com/3vdsfp8psy7y</sublink>
<sublink>http://movreel.com/lpileyt8ypti</sublink>
<sublink></sublink>
</link>
<thumbnail>http://image.tmdb.org/t/p/original/eELqMf6wWQdHA4cEwUdGshqyHDl.jpg</thumbnail>
</item>2014-01-17

<item>
<title>[COLOR lime]LATEST[/COLOR] American Hustle (2013) SD [COLOR lime]THEATRE PREMIERE[/COLOR]</title>
<link>
<sublink>http://37.58.68.221/index.php?file=2691&start=0&hd=0&auth=0&type=flv&tv=0</sublink>
<sublink>http://billionuploads.com/6gf0nhnfe4uk</sublink>
<sublink>http://billionuploads.com/7j0fh7leo0w0</sublink>
<sublink>http://billionuploads.com/zbmmdghte6ug</sublink>
<sublink>http://billionuploads.com/zbmmdghte6ug</sublink>
<sublink>http://hugefiles.net/a8whbc8m6ie7</sublink>
<sublink>http://hugefiles.net/3zyms612fwgz</sublink>
<sublink>http://180upload.com/rqz6sibpc7cb</sublink>
<sublink>http://180upload.com/oq4idb1up492</sublink>
<sublink>http://180upload.com/9fuc5fybwggq</sublink>
<sublink>http://180upload.com/x0vpkfdreur1</sublink>
<sublink>http://epicshare.net/lm2a3dc0twig</sublink>
<sublink>http://epicshare.net/j186i6r93583</sublink>
<sublink>http://movreel.com/wdn5ei4capsd</sublink>
<sublink>http://movreel.com/u4svn2rfgjew</sublink>
<sublink></sublink>
<sublink></sublink>
</link>
<thumbnail>http://image.tmdb.org/t/p/original/8sar0KkBnJQ2UMMRw9L1spv2qkP.jpg</thumbnail>
</item>

<item>
<title>[COLOR lime]LATEST[/COLOR] Last Vegas (2013) HDCAM [COLOR lime]THEATRE PREMIERE[/COLOR]</title>
<link>
<sublink>http://billionuploads.com/fatjctcbwdvh</sublink>
<sublink>http://hugefiles.net/x3kf7m0ijsd7</sublink>
<sublink>http://www.putlocker.com/file/8B77808E3969E82F</sublink>
<sublink>http://movreel.com/b3s4e4xkyiwh.html</sublink>
<sublink>http://sharesix.com/nzebjw2jwc2x</sublink>
<sublink></sublink>
<sublink></sublink>
<sublink></sublink>
</link>
<thumbnail>http://image.tmdb.org/t/p/original/tBiAdXNAesfe8cpuUd54pgsqGkI.jpg</thumbnail>
</item> 2013-11-01

*TP*
<item>
<title>[COLOR lime]LATEST[/COLOR] Lone Survivor (2014) DVDScr [COLOR lime]THEATRE PREMIERE[/COLOR]</title>
<link>
<sublink>http://37.58.68.221/index.php?file=2727&start=0&hd=0&auth=0&type=flv&tv=0</sublink>
<sublink>http://billionuploads.com/nb84vgen5khc</sublink>
<sublink>http://hugefiles.net/lk473cvr76rx</sublink>
<sublink>http://180upload.com/638f52cg80fm</sublink>
<sublink>http://epicshare.net/o8p9q6ua03pa</sublink>
<sublink>http://movreel.com/cirk0ab2wdtw</sublink>
<sublink></sublink>
<sublink></sublink>
</link>
<thumbnail></thumbnail>
</item>2014-01-10

<item>
<title>[COLOR lime]LATEST[/COLOR] All Is Lost (2013) HDRip [COLOR lime]THEATRE PREMIERE[/COLOR]</title>
<link>
<sublink>http://billionuploads.com/xrbs5c2qbbvb</sublink>
<sublink>http://hugefiles.net/s9ngyw1ocwo2</sublink>
<sublink>http://movreel.com/zb8daslsjp5a.html</sublink>
<sublink>http://www.putlocker.com/file/CEED0A1D19CA68D6</sublink>
<sublink>http://180upload.com/0qleyavpbcdh</sublink>
<sublink></sublink>
<sublink></sublink>
<sublink></sublink>
</link>
<thumbnail>http://image.tmdb.org/t/p/original/wqLXT6Q8BcDWOHdPi0key8IMEmY.jpg</thumbnail>
</item> 2013-10-18

<item>
<title>[COLOR lime]LATEST[/COLOR] Enough Said (2013) DVD [COLOR lime]THEATRE PREMIERE[/COLOR]</title>
<link>
<sublink>http://billionuploads.com/e1t3f7qd2c96</sublink>
<sublink>http://billionuploads.com/k2h72yz3m2f0</sublink>
<sublink>http://hugefiles.net/sex1qi969p58</sublink>
<sublink>http://hugefiles.net/qv9lh8tsvpi8</sublink>
<sublink>http://180upload.com/a3s3hey9al27</sublink>
<sublink>http://180upload.com/a3s3hey9al27</sublink>
<sublink>http://movreel.com/x6lq1etbctu3</sublink>
<sublink>http://movreel.com/x6lq1etbctu3</sublink>
</link>
<thumbnail>http://image.tmdb.org/t/p/original/iwg42td071ROQpfI9T5DEpZYArm.jpg</thumbnail>
</item>

*REG*
<item>
<title>[COLOR lime]LATEST[/COLOR] A.C.O.D. (2013) HD</title>
<link>
<sublink>http://hugefiles.net/9maa9jmjlbo6</sublink>
<sublink>http://hugefiles.net/9vjgm3cbmfwn</sublink>
<sublink>http://180upload.com/p6hvomm5binu</sublink>
<sublink>http://180upload.com/eqom0fhvjmum</sublink>
<sublink>http://movreel.com/bfh0grtevfl6</sublink>
<sublink>http://movreel.com/40hw28bh6hsm</sublink>
<sublink></sublink>
<sublink></sublink>
</link>
<thumbnail>http://image.tmdb.org/t/p/original/cO87I4zTfEGyKqeTiMNRkYjmdzK.jpg</thumbnail>
</item>2013-10-04



<item>
<title>[COLOR lime]LATEST[/COLOR] You're Next (2013) HDRip</title>
<link>
<sublink>http://billionuploads.com/vzmlflpw57b0</sublink>
<sublink>http://hugefiles.net/g2xdtfrdvr6g</sublink>
<sublink>http://180upload.com/7fl2y3y6s8cd</sublink>
</link>
<thumbnail>http://d3gtl9l2a4fn1j.cloudfront.net/t/p/original/iP4NC9Ycj8yKh4ktxjJLWZmBKZK.jpg</thumbnail>
</item>

<item>
<title>[COLOR lime]LATEST[/COLOR] Rush (2013) HD</title>
<link>
<sublink>http://billionuploads.com/fkl5ur2moe1o</sublink>
<sublink>http://hugefiles.net/3w232oq05z0i</sublink>
<sublink>http://180upload.com/bej2a2j6golq</sublink>
<sublink>http://180upload.com/jgou5hmpbgy5</sublink>
<sublink>http://movreel.com/k0g1z1enuxfz</sublink>
</link>
<thumbnail>http://d3gtl9l2a4fn1j.cloudfront.net/t/p/original/cjEepHZOZAwmK6nAj5jis6HV75E.jpg</thumbnail>
</item>

<item>
<title>[COLOR lime]LATEST[/COLOR] Saving Mr. Banks (2013) DVDScr [COLOR lime]THEATRE PREMIERE[/COLOR]</title>
<link>
<sublink>http://37.58.68.221/index.php?file=2679&start=0&hd=0&auth=0&type=flv&tv=0</sublink>
<sublink>http://hugefiles.net/ph11qc5rcquw</sublink>
<sublink>http://hugefiles.net/lcd27s1ui67u</sublink>
<sublink>http://180upload.com/6fr385plc8ex</sublink>
<sublink>http://180upload.com/yzw4swdha1xu</sublink>
<sublink>http://epicshare.net/nssoc6peoifr</sublink>
<sublink>http://movreel.com/6bpd4k5ozbjl</sublink>
<sublink>http://movreel.com/xu3shuveb7mr</sublink>
</link>
<thumbnail>http://image.tmdb.org/t/p/original/aG33huZ8MJJNUsDrBK22cIuiuUM.jpg</thumbnail>
</item>

<item>
<title>[COLOR lime]LATEST[/COLOR] Walking With Dinosaurs (2013) CAM</title>
<link>
<sublink>http://billionuploads.com/r9dqi6171vya</sublink>
<sublink>http://billionuploads.com/0oo6j5vrvhjy/WalkingwithDinosaurs2013CAMx246AAC-Maremaid.mkv</sublink>
<sublink>http://hugefiles.net/fnhdwevnbd09</sublink>
<sublink>http://180upload.com/tailu7jm5of4</sublink>
<sublink>http://mightyupload.com/07atn9c81uc9/Walking_with_Dinosaurs_2013_CAM_x246_AAC.mkv.html</sublink>
</link>
<thumbnail>http://image.tmdb.org/t/p/original/syrPo4XWmrEaA8YeGLaKWOmT2a1.jpg</thumbnail>
</item>

<item>
<title>[COLOR lime]LATEST[/COLOR] The Hobbit: The Desolation of Smaug (2013) DVDScr</title>
<link>
<sublink>http://37.58.68.221/index.php?file=2681&start=0&hd=0&auth=0&type=flv&tv=0</sublink>
<sublink>http://billionuploads.com/su1fx2g2ou55</sublink>
<sublink>http://billionuploads.com/su1fx2g2ou55</sublink>
<sublink>http://billionuploads.com/7s6goddr7umm</sublink>
<sublink>http://billionuploads.com/sw07cvnlmdy7</sublink>
<sublink>http://hugefiles.net/ka8v76a27qtv</sublink>
<sublink>http://hugefiles.net/xaacyl3p8n3w</sublink>
<sublink>http://hugefiles.net/369fn95dj7c6</sublink>
<sublink>http://hugefiles.net/nagnyx22g3sy</sublink>
<sublink>http://epicshare.net/8hc9ymzpy15m</sublink>
<sublink>http://epicshare.net/aposquuernjm</sublink>
<sublink>http://180upload.com/w52rcr5qh7s7</sublink>
<sublink>http://180upload.com/6bsa773ldh6q</sublink>
<sublink>http://180upload.com/96p8rou87hg8</sublink>
<sublink>http://180upload.com/zsy4emvd2nwy</sublink>
<sublink>http://movreel.com/jvkrpvr7wjxe</sublink>
<sublink>http://movreel.com/96jtalom2ffz</sublink>
</link>
<thumbnail>http://image.tmdb.org/t/p/original/ouIvgaSFqBMMailxU9zZiVIXXeV.jpg</thumbnail>
</item>






<item>
<title>[COLOR red]------------------------------ Episodes ---------------------------------[/COLOR]</title>
<link>nill</link>                                                                         >                  
<thumbnail>nill</thumbnail>
</item>



<item>
<title>[COLOR red]------------------------------- Fights -----------------------------------[/COLOR]</title>
<link>nill</link>                                                                            >
<thumbnail>nill</thumbnail>
</item>



<item>
<title>[COLOR red]------------------------------ Comedy ----------------------------------[/COLOR]</title>
<link>nill</link>                                                                          >                  
<thumbnail>nill</thumbnail>
</item>



<item>
<title>[COLOR lime]--------------------------- Documentaries ------------------------------[/COLOR]</title>
<link>nill</link>                                                                         >                  
<thumbnail>nill</thumbnail>
</item>

<item>
<title>[COLOR lime]LATEST[/COLOR] Terms and Conditions May Apply (2013)</title>
<link>
<sublink>http://billionuploads.com/58pw6gvsywdo</sublink>
<sublink>http://180upload.com/jk4xzdg7y7tu</sublink>
<sublink>http://movreel.com/1h4xo28578e2</sublink>
<sublink>http://hugefiles.net/000gc9ws9w8t</sublink>
</link>
<thumbnail>http://image.tmdb.org/t/p/original/72TNDeUsUupWXtw8pCdQhu6yD9.jpg</thumbnail>
</item>



<item>
<title>[COLOR lime]--------------------------- Section Fillers -------------------------------[/COLOR]</title>
<link>nill</link>                                                                        >                  
<thumbnail>nill</thumbnail>
</item>

<item>
<title>[COLOR blue]ComedyCentral || HD[/COLOR] A.C.O.D. (2013) HD</title>
<link>
<sublink>http://hugefiles.net/9maa9jmjlbo6</sublink>
<sublink>http://hugefiles.net/9vjgm3cbmfwn</sublink>
<sublink>http://180upload.com/p6hvomm5binu</sublink>
<sublink>http://180upload.com/eqom0fhvjmum</sublink>
<sublink>http://movreel.com/bfh0grtevfl6</sublink>
<sublink>http://movreel.com/40hw28bh6hsm</sublink>
<sublink></sublink>
<sublink></sublink>
</link>
<thumbnail>http://image.tmdb.org/t/p/original/cO87I4zTfEGyKqeTiMNRkYjmdzK.jpg</thumbnail>
</item>2013-10-04

<item>
<title>[COLOR blue]HD[/COLOR] 300 (2007)</title>
<link>
<sublink>http://37.58.68.221/index.php?file=891&start=0&hd=0&auth=0&type=flv&tv=0</sublink>
<sublink>http://billionuploads.com/em63neing3yc</sublink>
<sublink>http://180upload.com/3ynoqwee2x0d</sublink>
<sublink>http://movreel.com/va6mi349or2w</sublink>
</link>
<thumbnail>http://image.tmdb.org/t/p/original/bYR8O1H1ZlME7Dm9ysfTYZnRDpw.jpg</thumbnail>
</item>

<item>
<title>[COLOR blue]ComedyCentral || HD[/COLOR] Think Like a Man (2012)</title>
<link>
<sublink>http://37.58.68.221/index.php?file=635&start=0&hd=0&auth=0&type=flv&tv=0</sublink>
<sublink>http://billionuploads.com/8gvtujsoui52/Think.Like.A.Man.2012.720p.BluRay.x264.YIFY.mp4</sublink>
<sublink>http://hugefiles.net/lecb2k7ikyzd</sublink>
<sublink>http://movreel.com/o34urvovh3z4.html</sublink>
</link>
<thumbnail>http://image.tmdb.org/t/p/original/xNfuh9Ray1wbpn2j5WQbJFBn0K1.jpg</thumbnail>
</item>

<item>
<title>[COLOR blue]ComedyCentral || HD[/COLOR] Your Highness (2011)</title>
<link>
<sublink>http://billionuploads.com/26jplrcadbj7/Your.Highness.2011.UNRATED.720p.BluRay.X264.YIFY.mkv</sublink>
<sublink>http://hugefiles.net/mhrwz9pikm25</sublink>
<sublink>http://180upload.com/11n245x7kn5u</sublink>
<sublink>http://movreel.com/xkast1b8hqqd.html</sublink>
</link>
<thumbnail>http://image.tmdb.org/t/p/original/d0P3WWy3Fc3JuORpdkkHhPrhlVc.jpg</thumbnail>
</item>

<item>
<title>[COLOR blue]All Timers | HD[/COLOR] No Country for Old Men (2007)</title>
<link>http://37.58.68.221/index.php?file=957&start=0&hd=0&auth=0&type=flv&tv=0</link>
<thumbnail>http://image.tmdb.org/t/p/original/6o0UWX2naW7HK45PDNYmoMIk5qs.jpg</thumbnail>
</item>



##################################################################################################################

<item>
<title>[COLOR lime]------------------------------- Fixes ------------------------------------[/COLOR]</title>
<link>nill</link>             
<thumbnail>nill</thumbnail>
</item>


<item>
<title>Captain Phillips (2013)</title>
<link>
<sublink>http://bayfiles.net/file/12J2F/3O59FI/Pncgnva.Cuvyyvcf.2013.720.divx</sublink>
<sublink>http://180upload.com/gmyvu30b6p3v</sublink>
</link>
<thumbnail>http://d3gtl9l2a4fn1j.cloudfront.net/t/p/original/lILIOfZkVlpx7m503z8t0oPhjCa.jpg</thumbnail>
</item>


[COLOR red]------------------------------ Special -----------------------------------[/COLOR]

<item>
<title></title>
<link>nill</link>                                                                                         
<thumbnail>nill</thumbnail>
</item>

##################################################################################################################



<item>
<title></title>
<link>http://www.purevid.com/v/891OSpokhrrgdjhhj7933/</link>
<thumbnail>http://upload.wikimedia.org/wikipedia/en/7/7c/Work_In_Progress.jpg</thumbnail>
</item>

<item>
<title></title>
<link>
<sublink>http://billionuploads.com/mz52t09a4fl7</sublink>
<sublink>http://billionuploads.com/hqccdit9dqf4/Rush2013WEBRiPHCXviDingStoner.avi</sublink>
<sublink>http://hugefiles.net/z1hahu6egg8x</sublink>
<sublink>http://180upload.com/siolzf4ffko2</sublink>
<sublink>http://180upload.com/t82xfmbch19k</sublink>
<sublink>http://movreel.com/mhdhadm8wcaz.html</sublink>
<sublink>http://www.putlocker.com/file/69EB9EA3F61494D0</sublink>
</link>
<thumbnail>http://upload.wikimedia.org/wikipedia/en/7/7c/Work_In_Progress.jpg</thumbnail>
</item>



