#######################################################################################################################################
<poster>HackerMil</poster>
<fanart>http://i1367.photobucket.com/albums/r795/HackerMil/Fanart/VIP-Fanart_zps661cd758.jpg</fanart>
#######################################################################################################################################

<info>
<message>[COLOR red]*** [/COLOR][COLOR aqua]!ALL Yours Sharktoy![/COLOR][COLOR red] ***[/COLOR]</message>
<thumbnail>http://i1367.photobucket.com/albums/r795/HackerMil/Icons/VIP-thumb_zpsf38de121.jpg</thumbnail>
</info>

################################################################################################################


<item>
<title>300 (2007)</title>
<link>
<sublink>http://75.126.196.132/index.php?file=891&start=0&hd=0&auth=37173551f877bf4854313fe84e&type=flv&tv=0</sublink>
<sublink>http://yify.tv/watch-300-online/</sublink>
<sublink>http://billionuploads.com/em63neing3yc</sublink>
<sublink>http://180upload.com/3ynoqwee2x0d</sublink>
<sublink>http://movreel.com/va6mi349or2w</sublink>
</link>
<thumbnail>http://image.tmdb.org/t/p/original/bYR8O1H1ZlME7Dm9ysfTYZnRDpw.jpg</thumbnail>
</item>

<item>
<title>Shawshank Redemption (1994)</title>
<link>
<sublink>http://75.126.196.132/index.php?file=50&start=0&hd=0&auth=37173551f877bf4854313fe84e&type=flv&tv=0</sublink>
<sublink>http://epicshare.net/66bcf7myv9hk</sublink>
<sublink>http://billionuploads.com/t6vqbua3pp51</sublink>
<sublink>http://180upload.com/8ihasjr94alb</sublink>
</link>
<thumbnail>http://ia.media-imdb.com/images/M/MV5BMTc3NjM4MTY3MV5BMl5BanBnXkFtZTcwODk4Mzg3OA@@._V1._SX352_SY500_.jpg</thumbnail>
</item>

<item>
<title>Unstoppable (2013))</title>
<link>
<sublink>http://billionuploads.com/8ahcwl68jhwe</sublink>
<sublink>http://hugefiles.net/ouhxl0g69fes</sublink>
<sublink>http://mightyupload.com/ufiiwxc8t9na</sublink>
<sublink>180upload.com/jkvbxq1yifk4</sublink>
<sublink>http://movreel.com/s8bp2onyg122</sublink>
</link>
<thumbnail>http://image.tmdb.org/t/p/original/m6va1LxaFiZEV8tzI9i0Mu2LzSt.jpg</thumbnail>
</item>