#######################################################################################################################################
<poster>HackerMil</poster>
<fanart>http://thetvdb.com/banners/fanart/original/73244-1.jpg</fanart>
#######################################################################################################################################


<item>
<title>[COLOR aqua]Series:[/COLOR] [COLOR red]Ended[/COLOR]</title>
<link>nill</link>
<thumbnail>http://www.nextepisodeonline.com/images/next-episode-logo.jpg</thumbnail>
</item>

####################################################################


<item>
<title>The Office (US) S01E01</title>
<link>
<sublink>http://BillionUploads.com/2xo9tdew6hhv</sublink>
<sublink>http://www.putlocker.com/file/7B974CA8ABFF6427</sublink>
</link> 
<thumbnail>http://thetvdb.com/banners/posters/73244-6.jpg</thumbnail>
</item>

<item>
<title>The Office (US) S01E02</title>
<link>
<sublink>http://BillionUploads.com/31x479epcwiu</sublink>
<sublink>http://www.putlocker.com/file/7746F29628E3FF52</sublink>
</link> 
<thumbnail>http://thetvdb.com/banners/posters/73244-6.jpg</thumbnail>
</item>

<item>
<title>The Office (US) S01E03</title>
<link>
<sublink>http://BillionUploads.com/gooiiw0dh68s</sublink>
<sublink>http://www.putlocker.com/file/57ACC7F1F445BF37</sublink>
</link> 
<thumbnail>http://thetvdb.com/banners/posters/73244-6.jpg</thumbnail>
</item>

<item>
<title>The Office (US) S01E04</title>
<link>
<sublink>http://BillionUploads.com/n1fkoxok2n6n</sublink>
<sublink>http://www.putlocker.com/file/59CB9997B11E61C5</sublink>
</link> 
<thumbnail>http://thetvdb.com/banners/posters/73244-6.jpg</thumbnail>
</item>

<item>
<title>The Office (US) S01E05</title>
<link>
<sublink>http://BillionUploads.com/9wq5iw52nfxc</sublink>
<sublink>http://www.putlocker.com/file/AEE027A8529783E8</sublink>
</link> 
<thumbnail>http://thetvdb.com/banners/posters/73244-6.jpg</thumbnail>
</item>

<item>
<title>The Office (US) S01E06</title>
<link>
<sublink>http://BillionUploads.com/p1l1r9adsxa5</sublink>
<sublink>http://www.putlocker.com/file/2929A324C4131E3F</sublink>
</link> 
<thumbnail>http://thetvdb.com/banners/posters/73244-6.jpg</thumbnail>
</item>

<item>
<title>The Office (US) S02E01</title>
<link>
<sublink>http://BillionUploads.com/xqo6hr03p9dt</sublink>
<sublink>http://www.putlocker.com/file/EA2C694EFF505113</sublink>
</link> 
<thumbnail>http://thetvdb.com/banners/posters/73244-6.jpg</thumbnail>
</item>

<item>
<title>The Office (US) S02E02</title>
<link>
<sublink>http://BillionUploads.com/vg4nezzv1e96</sublink>
<sublink>http://www.putlocker.com/file/4EB554A300BB8BA7</sublink>
</link> 
<thumbnail>http://thetvdb.com/banners/posters/73244-6.jpg</thumbnail>
</item>

<item>
<title>The Office (US) S02E03</title>
<link>
<sublink>http://BillionUploads.com/qx7gmg9007pj</sublink>
<sublink>http://www.putlocker.com/file/4E761992B5DC4EFC</sublink>
</link> 
<thumbnail>http://thetvdb.com/banners/posters/73244-6.jpg</thumbnail>
</item>

<item>
<title>The Office (US) S02E04</title>
<link>
<sublink>http://BillionUploads.com/sm1hp8xwcdjk</sublink>
<sublink>http://www.putlocker.com/file/BCCDCA0689A808FD</sublink>
</link> 
<thumbnail>http://thetvdb.com/banners/posters/73244-6.jpg</thumbnail>
</item>

<item>
<title>The Office (US) S02E05</title>
<link>
<sublink>http://BillionUploads.com/6jwzi0m0bngi</sublink>
<sublink>http://www.putlocker.com/file/C421229CB2FBCCB9</sublink>
</link> 
<thumbnail>http://thetvdb.com/banners/posters/73244-6.jpg</thumbnail>
</item>

<item>
<title>The Office (US) S02E06</title>
<link>
<sublink>http://BillionUploads.com/7d2ry90mv2eh</sublink>
<sublink>http://www.putlocker.com/file/8932B39F95A95F10</sublink>
</link> 
<thumbnail>http://thetvdb.com/banners/posters/73244-6.jpg</thumbnail>
</item>

<item>
<title>The Office (US) S02E07</title>
<link>
<sublink>http://BillionUploads.com/l49k6kzg1aem</sublink>
<sublink>http://www.putlocker.com/file/1FC17FD5E4B6789E</sublink>
</link> 
<thumbnail>http://thetvdb.com/banners/posters/73244-6.jpg</thumbnail>
</item>

<item>
<title>The Office (US) S02E08</title>
<link>
<sublink>http://BillionUploads.com/z33jg8i7zl5q</sublink>
<sublink>http://www.putlocker.com/file/9E01B79E94F4B6BD</sublink>
</link> 
<thumbnail>http://thetvdb.com/banners/posters/73244-6.jpg</thumbnail>
</item>

<item>
<title>The Office (US) S02E09</title>
<link>
<sublink>http://BillionUploads.com/5y3ldr47bll9</sublink>
<sublink>http://www.putlocker.com/file/D6A2CAA734ED41FA</sublink>
</link> 
<thumbnail>http://thetvdb.com/banners/posters/73244-6.jpg</thumbnail>
</item>

<item>
<title>The Office (US) S02E10</title>
<link>
<sublink>http://BillionUploads.com/4a9uutwha3b8</sublink>
<sublink>http://www.putlocker.com/file/9225DB85C8A36DB5</sublink>
</link> 
<thumbnail>http://thetvdb.com/banners/posters/73244-6.jpg</thumbnail>
</item>

<item>
<title>The Office (US) S02E11</title>
<link>
<sublink>http://BillionUploads.com/rm2lbk3cb26g</sublink>
<sublink>http://www.putlocker.com/file/9D9D743A831B5156</sublink>
</link> 
<thumbnail>http://thetvdb.com/banners/posters/73244-6.jpg</thumbnail>
</item>

<item>
<title>The Office (US) S02E12</title>
<link>
<sublink>http://BillionUploads.com/nh2ahhokoybz</sublink>
<sublink>http://www.putlocker.com/file/3561D86D5A44B757</sublink>
</link> 
<thumbnail>http://thetvdb.com/banners/posters/73244-6.jpg</thumbnail>
</item>

<item>
<title>The Office (US) S02E13</title>
<link>
<sublink>http://BillionUploads.com/93bfxabp036d</sublink>
<sublink>http://www.putlocker.com/file/F45B15152D3803BF</sublink>
</link> 
<thumbnail>http://thetvdb.com/banners/posters/73244-6.jpg</thumbnail>
</item>

<item>
<title>The Office (US) S02E14</title>
<link>
<sublink>http://BillionUploads.com/qvp93g3ibj6w</sublink>
<sublink>http://www.putlocker.com/file/3DFCA31884CD7C6D</sublink>
</link> 
<thumbnail>http://thetvdb.com/banners/posters/73244-6.jpg</thumbnail>
</item>

<item>
<title>The Office (US) S02E15</title>
<link>
<sublink>http://BillionUploads.com/2rkfbckkqov3</sublink>
<sublink>http://www.putlocker.com/file/A186182DCA7E5F85</sublink>
</link> 
<thumbnail>http://thetvdb.com/banners/posters/73244-6.jpg</thumbnail>
</item>

<item>
<title>The Office (US) S02E16</title>
<link>
<sublink>http://BillionUploads.com/ugtmqi6i68r4</sublink>
<sublink>http://www.putlocker.com/file/B85DA3807C6E5E6F</sublink>
</link> 
<thumbnail>http://thetvdb.com/banners/posters/73244-6.jpg</thumbnail>
</item>

<item>
<title>The Office (US) S02E17</title>
<link>
<sublink>http://BillionUploads.com/lttl0clstu3k</sublink>
<sublink>http://www.putlocker.com/file/9179C01AB45ABCF5</sublink>
</link> 
<thumbnail>http://thetvdb.com/banners/posters/73244-6.jpg</thumbnail>
</item>

<item>
<title>The Office (US) S02E18</title>
<link>
<sublink>http://BillionUploads.com/c25f748htgda</sublink>
<sublink>http://www.putlocker.com/file/2BEC093EBDCA5332</sublink>
</link> 
<thumbnail>http://thetvdb.com/banners/posters/73244-6.jpg</thumbnail>
</item>

<item>
<title>The Office (US) S02E19</title>
<link>
<sublink>http://BillionUploads.com/47u0q9b0caw3</sublink>
<sublink>http://www.putlocker.com/file/01E969DE63EC6706</sublink>
</link> 
<thumbnail>http://thetvdb.com/banners/posters/73244-6.jpg</thumbnail>
</item>

<item>
<title>The Office (US) S02E20</title>
<link>
<sublink>http://BillionUploads.com/fiq4820qp4j0</sublink>
<sublink>http://www.putlocker.com/file/7310A9173EEAED89</sublink>
</link> 
<thumbnail>http://thetvdb.com/banners/posters/73244-6.jpg</thumbnail>
</item>

<item>
<title>The Office (US) S02E21</title>
<link>
<sublink>http://BillionUploads.com/pqp313mxeyt7</sublink>
<sublink>http://www.putlocker.com/file/2E036C4D08B0A338</sublink>
</link> 
<thumbnail>http://thetvdb.com/banners/posters/73244-6.jpg</thumbnail>
</item>

<item>
<title>The Office (US) S02E22</title>
<link>
<sublink>http://BillionUploads.com/6j00vfmrnbkx</sublink>
<sublink>http://www.putlocker.com/file/E2C1B3C482704981</sublink>
</link> 
<thumbnail>http://thetvdb.com/banners/posters/73244-6.jpg</thumbnail>
</item>

<item>
<title>The Office (US) S03E01</title>
<link>
<sublink>http://BillionUploads.com/3ki0ly1lwuj0</sublink>
<sublink>http://www.putlocker.com/file/710CB184CE0A88E8</sublink>
</link> 
<thumbnail>http://thetvdb.com/banners/posters/73244-6.jpg</thumbnail>
</item>

<item>
<title>The Office (US) S03E02</title>
<link>
<sublink>http://BillionUploads.com/sqlbd0nafiew</sublink>
<sublink>http://www.putlocker.com/file/571F57979C53C905</sublink>
</link> 
<thumbnail>http://thetvdb.com/banners/posters/73244-6.jpg</thumbnail>
</item>

<item>
<title>The Office (US) S03E03</title>
<link>
<sublink>http://BillionUploads.com/rgd40pjqra02</sublink>
<sublink>http://www.putlocker.com/file/AD66D9D9A1F6387D</sublink>
</link> 
<thumbnail>http://thetvdb.com/banners/posters/73244-6.jpg</thumbnail>
</item>

<item>
<title>The Office (US) S03E04</title>
<link>
<sublink>http://BillionUploads.com/yeuisygt73xy</sublink>
<sublink>http://www.putlocker.com/file/1E94C311D9E61973</sublink>
</link> 
<thumbnail>http://thetvdb.com/banners/posters/73244-6.jpg</thumbnail>
</item>

<item>
<title>The Office (US) S03E05</title>
<link>
<sublink>http://BillionUploads.com/20xipcuf03m2</sublink>
<sublink>http://www.putlocker.com/file/89A8AAB1506F70AE</sublink>
</link> 
<thumbnail>http://thetvdb.com/banners/posters/73244-6.jpg</thumbnail>
</item>

<item>
<title>The Office (US) S03E06</title>
<link>
<sublink>http://BillionUploads.com/oy8h9knz6skw</sublink>
<sublink>http://www.putlocker.com/file/EB58EFF171D9B0A2</sublink>
</link> 
<thumbnail>http://thetvdb.com/banners/posters/73244-6.jpg</thumbnail>
</item>

<item>
<title>The Office (US) S03E07</title>
<link>
<sublink>http://BillionUploads.com/18pvwnkj5ijb</sublink>
<sublink>http://www.putlocker.com/file/0E5F4F0D365B2174</sublink>
</link> 
<thumbnail>http://thetvdb.com/banners/posters/73244-6.jpg</thumbnail>
</item>

<item>
<title>The Office (US) S03E08</title>
<link>
<sublink>http://BillionUploads.com/hvcjxc7gan9v</sublink>
<sublink>http://www.putlocker.com/file/399B1CDB21068306</sublink>
</link> 
<thumbnail>http://thetvdb.com/banners/posters/73244-6.jpg</thumbnail>
</item>

<item>
<title>The Office (US) S03E09</title>
<link>
<sublink>http://BillionUploads.com/rshzhv2zus6z</sublink>
<sublink>http://www.putlocker.com/file/3B94704971F185C7</sublink>
</link> 
<thumbnail>http://thetvdb.com/banners/posters/73244-6.jpg</thumbnail>
</item>

<item>
<title>The Office (US) S03E10</title>
<link>
<sublink>http://BillionUploads.com/uv59gxi4ypdq</sublink>
<sublink>http://www.putlocker.com/file/2B2C4BF0CE44AE0E</sublink>
</link> 
<thumbnail>http://thetvdb.com/banners/posters/73244-6.jpg</thumbnail>
</item>

<item>
<title>The Office (US) S03E11</title>
<link>
<sublink>http://BillionUploads.com/3jocapyy4h13</sublink>
<sublink>http://www.putlocker.com/file/20CFD40A1327C4A5</sublink>
</link> 
<thumbnail>http://thetvdb.com/banners/posters/73244-6.jpg</thumbnail>
</item>

<item>
<title>The Office (US) S03E12</title>
<link>
<sublink>http://BillionUploads.com/vv4xaxtzwrwo</sublink>
<sublink>http://www.putlocker.com/file/97A133305FEFB513</sublink>
</link> 
<thumbnail>http://thetvdb.com/banners/posters/73244-6.jpg</thumbnail>
</item>

<item>
<title>The Office (US) S03E13</title>
<link>
<sublink>http://BillionUploads.com/kykouurt418e</sublink>
<sublink>http://www.putlocker.com/file/0CBC459F59CA1570</sublink>
</link> 
<thumbnail>http://thetvdb.com/banners/posters/73244-6.jpg</thumbnail>
</item>

<item>
<title>The Office (US) S03E14</title>
<link>
<sublink>http://BillionUploads.com/2ec9fni72nw8</sublink>
<sublink>http://www.putlocker.com/file/F609729993BBC041</sublink>
</link> 
<thumbnail>http://thetvdb.com/banners/posters/73244-6.jpg</thumbnail>
</item>

<item>
<title>The Office (US) S03E15</title>
<link>
<sublink>http://BillionUploads.com/shoqww2xtis3</sublink>
<sublink>http://www.putlocker.com/file/F38C9953E8491A07</sublink>
</link> 
<thumbnail>http://thetvdb.com/banners/posters/73244-6.jpg</thumbnail>
</item>

<item>
<title>The Office (US) S03E16</title>
<link>
<sublink>http://BillionUploads.com/840qqn3ha72c</sublink>
<sublink>http://www.putlocker.com/file/5D711F83CE18F926</sublink>
</link> 
<thumbnail>http://thetvdb.com/banners/posters/73244-6.jpg</thumbnail>
</item>

<item>
<title>The Office (US) S03E17</title>
<link>
<sublink>http://BillionUploads.com/0pig8678fqj9</sublink>
<sublink>http://www.putlocker.com/file/D61220C4D367F1A9</sublink>
</link> 
<thumbnail>http://thetvdb.com/banners/posters/73244-6.jpg</thumbnail>
</item>

<item>
<title>The Office (US) S03E18</title>
<link>
<sublink>http://BillionUploads.com/ng3o60x2dlc5</sublink>
<sublink>http://www.putlocker.com/file/F04E1E4BB8DE288D</sublink>
</link> 
<thumbnail>http://thetvdb.com/banners/posters/73244-6.jpg</thumbnail>
</item>

<item>
<title>The Office (US) S03E19</title>
<link>
<sublink>http://BillionUploads.com/wcqis5s0400z</sublink>
<sublink>http://www.putlocker.com/file/1CAEF10F51730A14</sublink>
</link> 
<thumbnail>http://thetvdb.com/banners/posters/73244-6.jpg</thumbnail>
</item>

<item>
<title>The Office (US) S03E20</title>
<link>
<sublink>http://BillionUploads.com/fa5x70pqhihf</sublink>
<sublink>http://www.putlocker.com/file/8F13BB752CED7858</sublink>
</link> 
<thumbnail>http://thetvdb.com/banners/posters/73244-6.jpg</thumbnail>
</item>

<item>
<title>The Office (US) S03E21</title>
<link>
<sublink>http://BillionUploads.com/y7gw7mv613p4</sublink>
<sublink>http://www.putlocker.com/file/C71304689A3037F4</sublink>
</link> 
<thumbnail>http://thetvdb.com/banners/posters/73244-6.jpg</thumbnail>
</item>

<item>
<title>The Office (US) S03E22</title>
<link>
<sublink>http://BillionUploads.com/cu5g4z5y5cpi</sublink>
<sublink>http://www.putlocker.com/file/F973C36A9B645D4D</sublink>
</link> 
<thumbnail>http://thetvdb.com/banners/posters/73244-6.jpg</thumbnail>
</item>

<item>
<title>The Office (US) S03E23</title>
<link>
<sublink>http://BillionUploads.com/ow586ohdzhlp</sublink>
<sublink>http://www.putlocker.com/file/C99DB804C402CFE6</sublink>
</link> 
<thumbnail>http://thetvdb.com/banners/posters/73244-6.jpg</thumbnail>
</item>

<item>
<title>The Office (US) S04E01</title>
<link>
<sublink>http://BillionUploads.com/qrgqhpw4zz3h</sublink>
<sublink>http://www.putlocker.com/file/E5D90ABFE331B7CF</sublink>
</link> 
<thumbnail>http://thetvdb.com/banners/posters/73244-6.jpg</thumbnail>
</item>

<item>
<title>The Office (US) S04E02</title>
<link>
<sublink>http://BillionUploads.com/i4qmkdfs7gad</sublink>
<sublink>http://www.putlocker.com/file/0C52582963C62479</sublink>
</link> 
<thumbnail>http://thetvdb.com/banners/posters/73244-6.jpg</thumbnail>
</item>

<item>
<title>The Office (US) S04E03</title>
<link>
<sublink>http://BillionUploads.com/cej3vteqayx4</sublink>
<sublink>http://www.putlocker.com/file/4BFC5D2559F5F426</sublink>
</link> 
<thumbnail>http://thetvdb.com/banners/posters/73244-6.jpg</thumbnail>
</item>

<item>
<title>The Office (US) S04E04</title>
<link>
<sublink>http://BillionUploads.com/bdon643xmemo</sublink>
<sublink>http://www.putlocker.com/file/B9526D6D764B2D47</sublink>
</link> 
<thumbnail>http://thetvdb.com/banners/posters/73244-6.jpg</thumbnail>
</item>

<item>
<title>The Office (US) S04E05</title>
<link>
<sublink>http://BillionUploads.com/81o06vyslv2s</sublink>
<sublink>http://www.putlocker.com/file/C700024D5DD37CFF</sublink>
</link> 
<thumbnail>http://thetvdb.com/banners/posters/73244-6.jpg</thumbnail>
</item>

<item>
<title>The Office (US) S04E06</title>
<link>
<sublink>http://BillionUploads.com/yoph9axow593</sublink>
<sublink>http://www.putlocker.com/file/A61697053D075A9F</sublink>
</link> 
<thumbnail>http://thetvdb.com/banners/posters/73244-6.jpg</thumbnail>
</item>

<item>
<title>The Office (US) S04E07</title>
<link>
<sublink>http://BillionUploads.com/htdtih116991</sublink>
<sublink>http://www.putlocker.com/file/884ECD75D02FCE96</sublink>
</link> 
<thumbnail>http://thetvdb.com/banners/posters/73244-6.jpg</thumbnail>
</item>

<item>
<title>The Office (US) S04E08</title>
<link>
<sublink>http://BillionUploads.com/vx2lg1zenavg</sublink>
<sublink>http://www.putlocker.com/file/024E745F350D3E91</sublink>
</link> 
<thumbnail>http://thetvdb.com/banners/posters/73244-6.jpg</thumbnail>
</item>

<item>
<title>The Office (US) S04E09</title>
<link>
<sublink>http://BillionUploads.com/mypwhh74ufw7</sublink>
<sublink>http://www.putlocker.com/file/78B82098E0BF2CBB</sublink>
</link> 
<thumbnail>http://thetvdb.com/banners/posters/73244-6.jpg</thumbnail>
</item>

<item>
<title>The Office (US) S04E10</title>
<link>
<sublink>http://BillionUploads.com/zdkeu72syp66</sublink>
<sublink>http://www.putlocker.com/file/95268F80EC863DC5</sublink>
</link> 
<thumbnail>http://thetvdb.com/banners/posters/73244-6.jpg</thumbnail>
</item>

<item>
<title>The Office (US) S04E11</title>
<link>
<sublink>http://BillionUploads.com/xoixmo6p1t2b</sublink>
<sublink>http://www.putlocker.com/file/8CCF59F06EB07384</sublink>
</link> 
<thumbnail>http://thetvdb.com/banners/posters/73244-6.jpg</thumbnail>
</item>

<item>
<title>The Office (US) S04E12</title>
<link>
<sublink>http://BillionUploads.com/ym9i0hj5gzyg</sublink>
<sublink>http://www.putlocker.com/file/5EABB28845ADFE25</sublink>
</link> 
<thumbnail>http://thetvdb.com/banners/posters/73244-6.jpg</thumbnail>
</item>

<item>
<title>The Office (US) S04E13</title>
<link>
<sublink>http://BillionUploads.com/5ny3no8iswwh</sublink>
<sublink>http://www.putlocker.com/file/7DDB952645B20969</sublink>
</link> 
<thumbnail>http://thetvdb.com/banners/posters/73244-6.jpg</thumbnail>
</item>

<item>
<title>The Office (US) S04E14</title>
<link>
<sublink>http://BillionUploads.com/quftyzklw3fl</sublink>
<sublink>http://www.putlocker.com/file/72B675B60A32AD85</sublink>
</link> 
<thumbnail>http://thetvdb.com/banners/posters/73244-6.jpg</thumbnail>
</item>

<item>
<title>The Office (US) S05E01</title>
<link>
<sublink>http://BillionUploads.com/8vlhz42hycw2</sublink>
<sublink>http://www.putlocker.com/file/1F3A326E3B616176</sublink>
</link> 
<thumbnail>http://thetvdb.com/banners/posters/73244-6.jpg</thumbnail>
</item>

<item>
<title>The Office (US) S05E02</title>
<link>
<sublink>http://BillionUploads.com/j7f48wzz4k4n</sublink>
<sublink>http://www.putlocker.com/file/B819FDD5703ECD01</sublink>
</link> 
<thumbnail>http://thetvdb.com/banners/posters/73244-6.jpg</thumbnail>
</item>

<item>
<title>The Office (US) S05E03</title>
<link>
<sublink>http://BillionUploads.com/bujvw2uc4ad8</sublink>
<sublink>http://www.putlocker.com/file/88259F01DA210571</sublink>
</link> 
<thumbnail>http://thetvdb.com/banners/posters/73244-6.jpg</thumbnail>
</item>

<item>
<title>The Office (US) S05E04</title>
<link>
<sublink>http://BillionUploads.com/w93oemgwy7q0</sublink>
<sublink>http://www.putlocker.com/file/71102336856304FB</sublink>
</link> 
<thumbnail>http://thetvdb.com/banners/posters/73244-6.jpg</thumbnail>
</item>

<item>
<title>The Office (US) S05E05</title>
<link>
<sublink>http://BillionUploads.com/2e3rp3yal8md</sublink>
<sublink>http://www.putlocker.com/file/8CD9C4EC0332555D</sublink>
</link> 
<thumbnail>http://thetvdb.com/banners/posters/73244-6.jpg</thumbnail>
</item>

<item>
<title>The Office (US) S05E06</title>
<link>
<sublink>http://BillionUploads.com/wbtqpbgirsjy</sublink>
<sublink>http://www.putlocker.com/file/97E6B4C8DE4C0039</sublink>
</link> 
<thumbnail>http://thetvdb.com/banners/posters/73244-6.jpg</thumbnail>
</item>

<item>
<title>The Office (US) S05E07</title>
<link>
<sublink>http://BillionUploads.com/04231lnip4hx</sublink>
<sublink>http://www.putlocker.com/file/CBC797941A61C1AE</sublink>
</link> 
<thumbnail>http://thetvdb.com/banners/posters/73244-6.jpg</thumbnail>
</item>

<item>
<title>The Office (US) S05E08</title>
<link>
<sublink>http://BillionUploads.com/x07y5lqpxj9j</sublink>
<sublink>http://www.putlocker.com/file/AA478BD2ECE9C220</sublink>
</link> 
<thumbnail>http://thetvdb.com/banners/posters/73244-6.jpg</thumbnail>
</item>

<item>
<title>The Office (US) S05E09</title>
<link>
<sublink>http://BillionUploads.com/xuuhjljf6haa</sublink>
<sublink>http://www.putlocker.com/file/43D43046770ED827</sublink>
</link> 
<thumbnail>http://thetvdb.com/banners/posters/73244-6.jpg</thumbnail>
</item>

<item>
<title>The Office (US) S05E10</title>
<link>
<sublink>http://BillionUploads.com/9izgxjhdzxxh</sublink>
<sublink>http://www.putlocker.com/file/EA0E7F148866D770</sublink>
</link> 
<thumbnail>http://thetvdb.com/banners/posters/73244-6.jpg</thumbnail>
</item>

<item>
<title>The Office (US) S05E11</title>
<link>
<sublink>http://BillionUploads.com/ajqm3414lyku</sublink>
<sublink>http://www.putlocker.com/file/2D83C388E4C7CE2E</sublink>
</link> 
<thumbnail>http://thetvdb.com/banners/posters/73244-6.jpg</thumbnail>
</item>

<item>
<title>The Office (US) S05E12</title>
<link>
<sublink>http://BillionUploads.com/8zkckw6i375z</sublink>
<sublink>http://www.putlocker.com/file/0F5B9A241B59AFEF</sublink>
</link> 
<thumbnail>http://thetvdb.com/banners/posters/73244-6.jpg</thumbnail>
</item>

<item>
<title>The Office (US) S05E13</title>
<link>
<sublink>http://BillionUploads.com/j7ie7dmz6zoj</sublink>
<sublink>http://www.putlocker.com/file/DEC9805040ED13F8</sublink>
</link> 
<thumbnail>http://thetvdb.com/banners/posters/73244-6.jpg</thumbnail>
</item>

<item>
<title>The Office (US) S05E14</title>
<link>
<sublink>http://BillionUploads.com/z7833fjro0gz</sublink>
<sublink>http://www.putlocker.com/file/9A6E00120AAC0013</sublink>
</link> 
<thumbnail>http://thetvdb.com/banners/posters/73244-6.jpg</thumbnail>
</item>

<item>
<title>The Office (US) S05E15</title>
<link>
<sublink>http://BillionUploads.com/7fk70mgc8f5p</sublink>
<sublink>http://www.putlocker.com/file/0203B0D9BA5132BF</sublink>
</link> 
<thumbnail>http://thetvdb.com/banners/posters/73244-6.jpg</thumbnail>
</item>

<item>
<title>The Office (US) S05E16</title>
<link>
<sublink>http://BillionUploads.com/kqli0k09fhe1</sublink>
<sublink>http://www.putlocker.com/file/7C4BA20D507D12EB</sublink>
</link> 
<thumbnail>http://thetvdb.com/banners/posters/73244-6.jpg</thumbnail>
</item>

<item>
<title>The Office (US) S05E17</title>
<link>
<sublink>http://BillionUploads.com/bnqkgibteoje</sublink>
<sublink>http://www.putlocker.com/file/18B6F2C05220B2A2</sublink>
</link> 
<thumbnail>http://thetvdb.com/banners/posters/73244-6.jpg</thumbnail>
</item>

<item>
<title>The Office (US) S05E18</title>
<link>
<sublink>http://BillionUploads.com/azr0783dfw83</sublink>
<sublink>http://www.putlocker.com/file/D3F380412CF83D69</sublink>
</link> 
<thumbnail>http://thetvdb.com/banners/posters/73244-6.jpg</thumbnail>
</item>

<item>
<title>The Office (US) S05E19</title>
<link>
<sublink>http://BillionUploads.com/8uh5av4lmvyc</sublink>
<sublink>http://www.putlocker.com/file/3114020734B241A4</sublink>
</link> 
<thumbnail>http://thetvdb.com/banners/posters/73244-6.jpg</thumbnail>
</item>

<item>
<title>The Office (US) S05E20</title>
<link>
<sublink>http://BillionUploads.com/qgpfkim06lts</sublink>
<sublink>http://www.putlocker.com/file/4D48789683A1E4FA</sublink>
</link> 
<thumbnail>http://thetvdb.com/banners/posters/73244-6.jpg</thumbnail>
</item>

<item>
<title>The Office (US) S05E21</title>
<link>
<sublink>http://BillionUploads.com/n3zzq3vg00rw</sublink>
<sublink>http://www.putlocker.com/file/A4F1C95615CAC7B6</sublink>
</link> 
<thumbnail>http://thetvdb.com/banners/posters/73244-6.jpg</thumbnail>
</item>

<item>
<title>The Office (US) S05E22</title>
<link>
<sublink>http://BillionUploads.com/17hdwzmsu8zr</sublink>
<sublink>http://www.putlocker.com/file/FD4EFC4AA9C40594</sublink>
</link> 
<thumbnail>http://thetvdb.com/banners/posters/73244-6.jpg</thumbnail>
</item>

<item>
<title>The Office (US) S05E23</title>
<link>
<sublink>http://BillionUploads.com/qxpq37o5ppam</sublink>
<sublink>http://www.putlocker.com/file/F459A244ADFAE266</sublink>
</link> 
<thumbnail>http://thetvdb.com/banners/posters/73244-6.jpg</thumbnail>
</item>

<item>
<title>The Office (US) S05E24</title>
<link>
<sublink>http://BillionUploads.com/1omxt7hhb5xt</sublink>
<sublink>http://www.putlocker.com/file/51428063C90D6892</sublink>
</link> 
<thumbnail>http://thetvdb.com/banners/posters/73244-6.jpg</thumbnail>
</item>

<item>
<title>The Office (US) S05E25</title>
<link>
<sublink>http://BillionUploads.com/xpmmx1ljemkl</sublink>
<sublink>http://www.putlocker.com/file/5849D3405293B802</sublink>
</link> 
<thumbnail>http://thetvdb.com/banners/posters/73244-6.jpg</thumbnail>
</item>

<item>
<title>The Office (US) S05E26</title>
<link>
<sublink>http://BillionUploads.com/eetnn3ovbqyz</sublink>
<sublink>http://www.putlocker.com/file/3BD0FEC43967F7C7</sublink>
</link> 
<thumbnail>http://thetvdb.com/banners/posters/73244-6.jpg</thumbnail>
</item>

<item>
<title>The Office (US) S06E01</title>
<link>
<sublink>http://BillionUploads.com/a0rxuba0jlfb</sublink>
<sublink>http://www.putlocker.com/file/8E2AC704F6331DBA</sublink>
</link> 
<thumbnail>http://thetvdb.com/banners/posters/73244-6.jpg</thumbnail>
</item>

<item>
<title>The Office (US) S06E02</title>
<link>
<sublink>http://BillionUploads.com/ik59ppqy60uu</sublink>
<sublink>http://www.putlocker.com/file/7F44C92FB17F67BD</sublink>
</link> 
<thumbnail>http://thetvdb.com/banners/posters/73244-6.jpg</thumbnail>
</item>

<item>
<title>The Office (US) S06E03</title>
<link>
<sublink>http://BillionUploads.com/az95m7jj876z</sublink>
<sublink>http://www.putlocker.com/file/2BDC99315C47E991</sublink>
</link> 
<thumbnail>http://thetvdb.com/banners/posters/73244-6.jpg</thumbnail>
</item>

<item>
<title>The Office (US) S06E04</title>
<link>
<sublink>http://BillionUploads.com/7sv76f6twf08</sublink>
<sublink>http://www.putlocker.com/file/3C89D19A9C582029</sublink>
</link> 
<thumbnail>http://thetvdb.com/banners/posters/73244-6.jpg</thumbnail>
</item>

<item>
<title>The Office (US) S06E05</title>
<link>
<sublink>http://BillionUploads.com/plwxvzbjbl94</sublink>
<sublink>http://www.putlocker.com/file/608FF1A86BEB8B09</sublink>
</link> 
<thumbnail>http://thetvdb.com/banners/posters/73244-6.jpg</thumbnail>
</item>

<item>
<title>The Office (US) S06E06</title>
<link>
<sublink>http://BillionUploads.com/4fenmqvjt2yd</sublink>
<sublink>http://www.putlocker.com/file/E76ED3ED23CE924D</sublink>
</link> 
<thumbnail>http://thetvdb.com/banners/posters/73244-6.jpg</thumbnail>
</item>

<item>
<title>The Office (US) S06E07</title>
<link>
<sublink>http://BillionUploads.com/i9wct7lssm3w</sublink>
<sublink>http://www.putlocker.com/file/5F11512131543859</sublink>
</link> 
<thumbnail>http://thetvdb.com/banners/posters/73244-6.jpg</thumbnail>
</item>

<item>
<title>The Office (US) S06E08</title>
<link>
<sublink>http://BillionUploads.com/b2on56s0nogq</sublink>
<sublink>http://www.putlocker.com/file/A87F0406D5B389F2</sublink>
</link> 
<thumbnail>http://thetvdb.com/banners/posters/73244-6.jpg</thumbnail>
</item>

<item>
<title>The Office (US) S06E09</title>
<link>
<sublink>http://BillionUploads.com/yw2mze6okbo6</sublink>
<sublink>http://www.putlocker.com/file/008B0E5C6B0C0FFD</sublink>
</link> 
<thumbnail>http://thetvdb.com/banners/posters/73244-6.jpg</thumbnail>
</item>

<item>
<title>The Office (US) S06E10</title>
<link>
<sublink>http://BillionUploads.com/uqmlm7ssm0u5</sublink>
<sublink>http://www.putlocker.com/file/F36B2D1A6D2B2C33</sublink>
</link> 
<thumbnail>http://thetvdb.com/banners/posters/73244-6.jpg</thumbnail>
</item>

<item>
<title>The Office (US) S06E11</title>
<link>
<sublink>http://BillionUploads.com/ihrlicntawcv</sublink>
<sublink>http://www.putlocker.com/file/DB9820323D94ECDF</sublink>
</link> 
<thumbnail>http://thetvdb.com/banners/posters/73244-6.jpg</thumbnail>
</item>

<item>
<title>The Office (US) S06E12</title>
<link>
<sublink>http://BillionUploads.com/3jhnsxb79slp</sublink>
<sublink>http://www.putlocker.com/file/C518616C36655D52</sublink>
</link> 
<thumbnail>http://thetvdb.com/banners/posters/73244-6.jpg</thumbnail>
</item>

<item>
<title>The Office (US) S06E13</title>
<link>
<sublink>http://BillionUploads.com/lizeh89d1oda</sublink>
<sublink>http://www.putlocker.com/file/0F6B720A74347551</sublink>
</link> 
<thumbnail>http://thetvdb.com/banners/posters/73244-6.jpg</thumbnail>
</item>

<item>
<title>The Office (US) S06E14</title>
<link>
<sublink>http://BillionUploads.com/8k9p49kfiwdh</sublink>
<sublink>http://www.putlocker.com/file/8B76AEB924DB6A1A</sublink>
</link> 
<thumbnail>http://thetvdb.com/banners/posters/73244-6.jpg</thumbnail>
</item>

<item>
<title>The Office (US) S06E15</title>
<link>
<sublink>http://BillionUploads.com/jyai17tphopy</sublink>
<sublink>http://www.putlocker.com/file/AB9A458CCB25EE58</sublink>
</link> 
<thumbnail>http://thetvdb.com/banners/posters/73244-6.jpg</thumbnail>
</item>

<item>
<title>The Office (US) S06E16</title>
<link>
<sublink>http://BillionUploads.com/qq93ln9e94rq</sublink>
<sublink>http://www.putlocker.com/file/B51CDBE9CDBEC9C8</sublink>
</link> 
<thumbnail>http://thetvdb.com/banners/posters/73244-6.jpg</thumbnail>
</item>

<item>
<title>The Office (US) S06E17</title>
<link>
<sublink>http://BillionUploads.com/n54jg02ilung</sublink>
<sublink>http://www.putlocker.com/file/6DACBC7957CADCB3</sublink>
</link> 
<thumbnail>http://thetvdb.com/banners/posters/73244-6.jpg</thumbnail>
</item>

<item>
<title>The Office (US) S06E18</title>
<link>
<sublink>http://BillionUploads.com/kbg9pdag98sn</sublink>
<sublink>http://www.putlocker.com/file/B21D16B531707401</sublink>
</link> 
<thumbnail>http://thetvdb.com/banners/posters/73244-6.jpg</thumbnail>
</item>

<item>
<title>The Office (US) S06E19</title>
<link>
<sublink>http://BillionUploads.com/8zh2shh01s6u</sublink>
<sublink>http://www.putlocker.com/file/ED5270DD3F35EF7D</sublink>
</link> 
<thumbnail>http://thetvdb.com/banners/posters/73244-6.jpg</thumbnail>
</item>

<item>
<title>The Office (US) S06E20</title>
<link>
<sublink>http://BillionUploads.com/htrjmvolpuyo</sublink>
<sublink>http://www.putlocker.com/file/63ADF1DACB0BA568</sublink>
</link> 
<thumbnail>http://thetvdb.com/banners/posters/73244-6.jpg</thumbnail>
</item>

<item>
<title>The Office (US) S06E21</title>
<link>
<sublink>http://BillionUploads.com/a5wcrcjp7m9u</sublink>
<sublink>http://www.putlocker.com/file/76ABB00C9E6CB1CF</sublink>
</link> 
<thumbnail>http://thetvdb.com/banners/posters/73244-6.jpg</thumbnail>
</item>

<item>
<title>The Office (US) S06E22</title>
<link>
<sublink>http://BillionUploads.com/3caley0b3uqu</sublink>
<sublink>http://www.putlocker.com/file/4A6C1184AF126552</sublink>
</link> 
<thumbnail>http://thetvdb.com/banners/posters/73244-6.jpg</thumbnail>
</item>

<item>
<title>The Office (US) S06E23</title>
<link>
<sublink>http://BillionUploads.com/n7g49zcuph9p</sublink>
<sublink>http://www.putlocker.com/file/0BFE6FFECE3C72ED</sublink>
</link> 
<thumbnail>http://thetvdb.com/banners/posters/73244-6.jpg</thumbnail>
</item>

<item>
<title>The Office (US) S06E24</title>
<link>
<sublink>http://BillionUploads.com/ujymlh7pvtuk</sublink>
<sublink>http://www.putlocker.com/file/B5B3DB39528A1C80</sublink>
</link> 
<thumbnail>http://thetvdb.com/banners/posters/73244-6.jpg</thumbnail>
</item>

<item>
<title>The Office (US) S06E25</title>
<link>
<sublink>http://BillionUploads.com/ktuigi3nxfyk</sublink>
<sublink>http://www.putlocker.com/file/5243812D3C46CE17</sublink>
</link> 
<thumbnail>http://thetvdb.com/banners/posters/73244-6.jpg</thumbnail>
</item>

<item>
<title>The Office (US) S06E26</title>
<link>
<sublink>http://BillionUploads.com/ocgoo8g7750j</sublink>
<sublink>http://www.putlocker.com/file/F76C4D70404B34E7</sublink>
</link> 
<thumbnail>http://thetvdb.com/banners/posters/73244-6.jpg</thumbnail>
</item>

<item>
<title>The Office (US) S07E00</title>
<link>
<sublink>http://BillionUploads.com/nynen6xg0gtp</sublink>
<sublink>http://www.putlocker.com/file/E073F831E917AC15</sublink>
</link> 
<thumbnail>http://thetvdb.com/banners/posters/73244-6.jpg</thumbnail>
</item>

<item>
<title>The Office (US) S07E01</title>
<link>
<sublink>http://BillionUploads.com/ylituwck3xt5</sublink>
<sublink>http://www.putlocker.com/file/C9E2AF5A034910B7</sublink>
</link> 
<thumbnail>http://thetvdb.com/banners/posters/73244-6.jpg</thumbnail>
</item>

<item>
<title>The Office (US) S07E02</title>
<link>
<sublink>http://BillionUploads.com/xz6w1s54d53e</sublink>
<sublink>http://www.putlocker.com/file/E92B27A698C12DB1</sublink>
</link> 
<thumbnail>http://thetvdb.com/banners/posters/73244-6.jpg</thumbnail>
</item>

<item>
<title>The Office (US) S07E03</title>
<link>
<sublink>http://BillionUploads.com/g5mbgwizelyh</sublink>
<sublink>http://www.putlocker.com/file/F035DE1F7F6EF26A</sublink>
</link> 
<thumbnail>http://thetvdb.com/banners/posters/73244-6.jpg</thumbnail>
</item>

<item>
<title>The Office (US) S07E04</title>
<link>
<sublink>http://BillionUploads.com/qfosfq73gbbg</sublink>
<sublink>http://www.putlocker.com/file/018BDF67F95EE9BD</sublink>
</link> 
<thumbnail>http://thetvdb.com/banners/posters/73244-6.jpg</thumbnail>
</item>

<item>
<title>The Office (US) S07E05</title>
<link>
<sublink>http://BillionUploads.com/duttaz0afg04</sublink>
<sublink>http://www.putlocker.com/file/16050FFD1F258BAE</sublink>
</link> 
<thumbnail>http://thetvdb.com/banners/posters/73244-6.jpg</thumbnail>
</item>

<item>
<title>The Office (US) S07E06</title>
<link>
<sublink>http://BillionUploads.com/yntylhlkmi8e</sublink>
<sublink>http://www.putlocker.com/file/C1416F3DFC517663</sublink>
</link> 
<thumbnail>http://thetvdb.com/banners/posters/73244-6.jpg</thumbnail>
</item>

<item>
<title>The Office (US) S07E07</title>
<link>
<sublink>http://BillionUploads.com/vu5ub25t1y2z</sublink>
<sublink>http://www.putlocker.com/file/98A46310ECB841C1</sublink>
</link> 
<thumbnail>http://thetvdb.com/banners/posters/73244-6.jpg</thumbnail>
</item>

<item>
<title>The Office (US) S07E08</title>
<link>
<sublink>http://BillionUploads.com/mkubcjat3wmj</sublink>
<sublink>http://www.putlocker.com/file/867B0ABF58A3BCD2</sublink>
</link> 
<thumbnail>http://thetvdb.com/banners/posters/73244-6.jpg</thumbnail>
</item>

<item>
<title>The Office (US) S07E09</title>
<link>
<sublink>http://BillionUploads.com/6l7djzgpkyw5</sublink>
<sublink>http://www.putlocker.com/file/5DD8D0A944C17C7F</sublink>
</link> 
<thumbnail>http://thetvdb.com/banners/posters/73244-6.jpg</thumbnail>
</item>

<item>
<title>The Office (US) S07E10</title>
<link>
<sublink>http://BillionUploads.com/gdpiab1807qo</sublink>
<sublink>http://www.putlocker.com/file/96A1708091F6923F</sublink>
</link> 
<thumbnail>http://thetvdb.com/banners/posters/73244-6.jpg</thumbnail>
</item>

<item>
<title>The Office (US) S07E11</title>
<link>
<sublink>http://BillionUploads.com/sak6nvcf1q3p</sublink>
<sublink>http://www.putlocker.com/file/2724CE3417B0027C</sublink>
</link> 
<thumbnail>http://thetvdb.com/banners/posters/73244-6.jpg</thumbnail>
</item>

<item>
<title>The Office (US) S07E12</title>
<link>
<sublink>http://BillionUploads.com/kzsgt93ytpva</sublink>
<sublink>http://www.putlocker.com/file/52C2CA6F93CF75CB</sublink>
</link> 
<thumbnail>http://thetvdb.com/banners/posters/73244-6.jpg</thumbnail>
</item>

<item>
<title>The Office (US) S07E13</title>
<link>
<sublink>http://BillionUploads.com/oyqkj6kdimr2</sublink>
<sublink>http://www.putlocker.com/file/46F2CC4BFB228354</sublink>
</link> 
<thumbnail>http://thetvdb.com/banners/posters/73244-6.jpg</thumbnail>
</item>

<item>
<title>The Office (US) S07E14</title>
<link>
<sublink>http://BillionUploads.com/4qdwv0dxoywr</sublink>
<sublink>http://www.putlocker.com/file/A72E83961D22FFAC</sublink>
</link> 
<thumbnail>http://thetvdb.com/banners/posters/73244-6.jpg</thumbnail>
</item>

<item>
<title>The Office (US) S07E15</title>
<link>
<sublink>http://BillionUploads.com/w9n71uhsolqp</sublink>
<sublink>http://www.putlocker.com/file/F2A282F85FC2CA47</sublink>
</link> 
<thumbnail>http://thetvdb.com/banners/posters/73244-6.jpg</thumbnail>
</item>

<item>
<title>The Office (US) S07E16</title>
<link>
<sublink>http://BillionUploads.com/hbzsm31xinuf</sublink>
<sublink>http://www.putlocker.com/file/B2896C021FEE3D1D</sublink>
</link> 
<thumbnail>http://thetvdb.com/banners/posters/73244-6.jpg</thumbnail>
</item>

<item>
<title>The Office (US) S07E17</title>
<link>
<sublink>http://BillionUploads.com/prxahrp324tc</sublink>
<sublink>http://www.putlocker.com/file/F713B2D28ADBA7AA</sublink>
</link> 
<thumbnail>http://thetvdb.com/banners/posters/73244-6.jpg</thumbnail>
</item>

<item>
<title>The Office (US) S07E18</title>
<link>
<sublink>http://BillionUploads.com/bx22388hs58e</sublink>
<sublink>http://www.putlocker.com/file/D7587EF0F5AD174D</sublink>
</link> 
<thumbnail>http://thetvdb.com/banners/posters/73244-6.jpg</thumbnail>
</item>

<item>
<title>The Office (US) S07E19</title>
<link>
<sublink>http://BillionUploads.com/6jvgmdyn0ms4</sublink>
<sublink>http://www.putlocker.com/file/B1664A0DF0F69A05</sublink>
</link> 
<thumbnail>http://thetvdb.com/banners/posters/73244-6.jpg</thumbnail>
</item>

<item>
<title>The Office (US) S07E20</title>
<link>
<sublink>http://BillionUploads.com/jcl9rrp1cbrv</sublink>
<sublink>http://www.putlocker.com/file/AEAC29E63DFE176B</sublink>
</link> 
<thumbnail>http://thetvdb.com/banners/posters/73244-6.jpg</thumbnail>
</item>

<item>
<title>The Office (US) S07E21</title>
<link>
<sublink>http://BillionUploads.com/vqqvbrtte5x1</sublink>
<sublink>http://www.putlocker.com/file/D7D16FA93FAD60C7</sublink>
</link> 
<thumbnail>http://thetvdb.com/banners/posters/73244-6.jpg</thumbnail>
</item>

<item>
<title>The Office (US) S07E22</title>
<link>
<sublink>http://BillionUploads.com/dmm5jg8ybq8a</sublink>
<sublink>http://www.putlocker.com/file/78E915F4EBADAA07</sublink>
</link> 
<thumbnail>http://thetvdb.com/banners/posters/73244-6.jpg</thumbnail>
</item>

<item>
<title>The Office (US) S07E23</title>
<link>
<sublink>http://BillionUploads.com/0891ai8f2zya</sublink>
<sublink>http://www.putlocker.com/file/5B443FF4F47CD549</sublink>
</link> 
<thumbnail>http://thetvdb.com/banners/posters/73244-6.jpg</thumbnail>
</item>

<item>
<title>The Office (US) S07E24</title>
<link>
<sublink>http://BillionUploads.com/2td4letqwq1h</sublink>
<sublink>http://www.putlocker.com/file/D3FBF25D1534438D</sublink>
</link> 
<thumbnail>http://thetvdb.com/banners/posters/73244-6.jpg</thumbnail>
</item>

<item>
<title>The Office (US) S07E25</title>
<link>
<sublink>http://BillionUploads.com/rrkndci7ozms</sublink>
<sublink>http://www.putlocker.com/file/35A081DB895EA9D1</sublink>
</link> 
<thumbnail>http://thetvdb.com/banners/posters/73244-6.jpg</thumbnail>
</item>

<item>
<title>The Office (US) S07E26</title>
<link>
<sublink>http://BillionUploads.com/thss65v5l8hp</sublink>
<sublink>http://www.putlocker.com/file/1416837A76E9C17A</sublink>
</link> 
<thumbnail>http://thetvdb.com/banners/posters/73244-6.jpg</thumbnail>
</item>

<item>
<title>The Office (US) S08E01</title>
<link>
<sublink>http://BillionUploads.com/a2dtkj5gdjd2</sublink>
<sublink>http://www.putlocker.com/file/7125EE1DDA621A3B</sublink>
</link> 
<thumbnail>http://thetvdb.com/banners/posters/73244-6.jpg</thumbnail>
</item>

<item>
<title>The Office (US) S08E02</title>
<link>
<sublink>http://BillionUploads.com/5o55pk2ug8y5</sublink>
<sublink>http://www.putlocker.com/file/6FD8DA8FB355CE9A</sublink>
</link> 
<thumbnail>http://thetvdb.com/banners/posters/73244-6.jpg</thumbnail>
</item>

<item>
<title>The Office (US) S08E03</title>
<link>
<sublink>http://BillionUploads.com/ovrj3ee33dwj</sublink>
<sublink>http://www.putlocker.com/file/9D7111D8133B2734</sublink>
</link> 
<thumbnail>http://thetvdb.com/banners/posters/73244-6.jpg</thumbnail>
</item>

<item>
<title>The Office (US) S08E04</title>
<link>
<sublink>http://BillionUploads.com/ftf1hf6ecxaq</sublink>
<sublink>http://www.putlocker.com/file/512A0F8F17E0616A</sublink>
</link> 
<thumbnail>http://thetvdb.com/banners/posters/73244-6.jpg</thumbnail>
</item>

<item>
<title>The Office (US) S08E05</title>
<link>
<sublink>http://BillionUploads.com/1vowpwvsa1ay</sublink>
<sublink>http://www.putlocker.com/file/B8289635790D88E8</sublink>
</link> 
<thumbnail>http://thetvdb.com/banners/posters/73244-6.jpg</thumbnail>
</item>

<item>
<title>The Office (US) S08E06</title>
<link>
<sublink>http://BillionUploads.com/6hirfpctibda</sublink>
<sublink>http://www.putlocker.com/file/4D5759395D33D3E9</sublink>
</link> 
<thumbnail>http://thetvdb.com/banners/posters/73244-6.jpg</thumbnail>
</item>

<item>
<title>The Office (US) S08E07</title>
<link>
<sublink>http://BillionUploads.com/eplwdy7x3rym</sublink>
<sublink>http://www.putlocker.com/file/4D06CFFD6D06AC93</sublink>
</link> 
<thumbnail>http://thetvdb.com/banners/posters/73244-6.jpg</thumbnail>
</item>

<item>
<title>The Office (US) S08E08</title>
<link>
<sublink>http://BillionUploads.com/t4dsn4aetcq5</sublink>
<sublink>http://www.putlocker.com/file/C44A86A55331C574</sublink>
</link> 
<thumbnail>http://thetvdb.com/banners/posters/73244-6.jpg</thumbnail>
</item>

<item>
<title>The Office (US) S08E09</title>
<link>
<sublink>http://BillionUploads.com/7gwrqgfuctd0</sublink>
<sublink>http://www.putlocker.com/file/EAB5DED9E0217CB9</sublink>
</link> 
<thumbnail>http://thetvdb.com/banners/posters/73244-6.jpg</thumbnail>
</item>

<item>
<title>The Office (US) S08E10</title>
<link>
<sublink>http://BillionUploads.com/vlbphw19evsj</sublink>
<sublink>http://www.putlocker.com/file/D2C05A97A59A2160</sublink>
</link> 
<thumbnail>http://thetvdb.com/banners/posters/73244-6.jpg</thumbnail>
</item>

<item>
<title>The Office (US) S08E11</title>
<link>
<sublink>http://BillionUploads.com/g74zajfqo6j2</sublink>
<sublink>http://www.putlocker.com/file/75E11C66797D492A</sublink>
</link> 
<thumbnail>http://thetvdb.com/banners/posters/73244-6.jpg</thumbnail>
</item>

<item>
<title>The Office (US) S08E12</title>
<link>
<sublink>http://BillionUploads.com/6hqkf5kjp0tq</sublink>
<sublink>http://www.putlocker.com/file/9ACC9EF0754CF70F</sublink>
</link> 
<thumbnail>http://thetvdb.com/banners/posters/73244-6.jpg</thumbnail>
</item>

<item>
<title>The Office (US) S08E13</title>
<link>
<sublink>http://BillionUploads.com/9unr3zi3mbrv</sublink>
<sublink>http://www.putlocker.com/file/7F9171870C95384F</sublink>
</link> 
<thumbnail>http://thetvdb.com/banners/posters/73244-6.jpg</thumbnail>
</item>

<item>
<title>The Office (US) S08E14</title>
<link>
<sublink>http://BillionUploads.com/aw7prvh2ic8l</sublink>
<sublink>http://www.putlocker.com/file/4875DA3D3C2F65DD</sublink>
</link> 
<thumbnail>http://thetvdb.com/banners/posters/73244-6.jpg</thumbnail>
</item>

<item>
<title>The Office (US) S08E15</title>
<link>
<sublink>http://BillionUploads.com/3rucun3vxbwk</sublink>
<sublink>http://www.putlocker.com/file/5F47C24F3B37C6ED</sublink>
</link> 
<thumbnail>http://thetvdb.com/banners/posters/73244-6.jpg</thumbnail>
</item>

<item>
<title>The Office (US) S08E16</title>
<link>
<sublink>http://BillionUploads.com/b1ajog2xjk5q</sublink>
<sublink>http://www.putlocker.com/file/FD342EB1247C2515</sublink>
</link> 
<thumbnail>http://thetvdb.com/banners/posters/73244-6.jpg</thumbnail>
</item>

<item>
<title>The Office (US) S08E17</title>
<link>
<sublink>http://BillionUploads.com/2tenb4z8xvrl</sublink>
<sublink>http://www.putlocker.com/file/588C4F5083844878</sublink>
</link> 
<thumbnail>http://thetvdb.com/banners/posters/73244-6.jpg</thumbnail>
</item>

<item>
<title>The Office (US) S08E18</title>
<link>
<sublink>http://BillionUploads.com/0fah7sseo9lm</sublink>
<sublink>http://www.putlocker.com/file/DA76CF90EDF4D296</sublink>
</link> 
<thumbnail>http://thetvdb.com/banners/posters/73244-6.jpg</thumbnail>
</item>

<item>
<title>The Office (US) S08E19</title>
<link>
<sublink>http://BillionUploads.com/ka3hv80xhi51</sublink>
<sublink>http://www.putlocker.com/file/0DF89E0745183030</sublink>
</link> 
<thumbnail>http://thetvdb.com/banners/posters/73244-6.jpg</thumbnail>
</item>

<item>
<title>The Office (US) S08E20</title>
<link>
<sublink>http://BillionUploads.com/n5bfhu3kfloc</sublink>
<sublink>http://www.putlocker.com/file/4D0B8E1D2645A500</sublink>
</link> 
<thumbnail>http://thetvdb.com/banners/posters/73244-6.jpg</thumbnail>
</item>

<item>
<title>The Office (US) S08E21</title>
<link>
<sublink>http://BillionUploads.com/hrz9q2k70o3k</sublink>
<sublink>http://www.putlocker.com/file/C3762AEB61B47750</sublink>
</link> 
<thumbnail>http://thetvdb.com/banners/posters/73244-6.jpg</thumbnail>
</item>

<item>
<title>The Office (US) S08E22</title>
<link>
<sublink>http://BillionUploads.com/di9t4xw8qnm9</sublink>
<sublink>http://www.putlocker.com/file/BBBBA5E396149044</sublink>
</link> 
<thumbnail>http://thetvdb.com/banners/posters/73244-6.jpg</thumbnail>
</item>

<item>
<title>The Office (US) S08E23</title>
<link>
<sublink>http://BillionUploads.com/ffeoi569oryj</sublink>
<sublink>http://www.putlocker.com/file/E0B219750DBFA632</sublink>
</link> 
<thumbnail>http://thetvdb.com/banners/posters/73244-6.jpg</thumbnail>
</item>

<item>
<title>The Office (US) S08E24</title>
<link>
<sublink>http://BillionUploads.com/sjk6x2zskbwo</sublink>
<sublink>http://www.putlocker.com/file/9467A03DDD719D18</sublink>
</link> 
<thumbnail>http://thetvdb.com/banners/posters/73244-6.jpg</thumbnail>
</item>

<item>
<title>The Office (US) S09E01</title>
<link>
<sublink>http://BillionUploads.com/o2b1wwf2hern</sublink>
<sublink>http://www.putlocker.com/file/203CB0507662F16C</sublink>
</link> 
<thumbnail>http://thetvdb.com/banners/posters/73244-6.jpg</thumbnail>
</item>

<item>
<title>The Office (US) S09E02</title>
<link>
<sublink>http://BillionUploads.com/aiw8wm95fxr2</sublink>
<sublink>http://www.putlocker.com/file/29E689F4A39283E2</sublink>
</link> 
<thumbnail>http://thetvdb.com/banners/posters/73244-6.jpg</thumbnail>
</item>

<item>
<title>The Office (US) S09E03</title>
<link>
<sublink>http://BillionUploads.com/a60awrsqoee6</sublink>
<sublink>http://www.putlocker.com/file/307C8B26735D3C86</sublink>
</link> 
<thumbnail>http://thetvdb.com/banners/posters/73244-6.jpg</thumbnail>
</item>

<item>
<title>The Office (US) S09E04</title>
<link>
<sublink>http://BillionUploads.com/okogbs8kdwl5</sublink>
<sublink>http://www.putlocker.com/file/70FF9BBC979B3476</sublink>
</link> 
<thumbnail>http://thetvdb.com/banners/posters/73244-6.jpg</thumbnail>
</item>

<item>
<title>The Office (US) S09E05</title>
<link>
<sublink>http://BillionUploads.com/5y929feohc6w</sublink>
<sublink>http://www.putlocker.com/file/91D4C07A4CF5296E</sublink>
</link> 
<thumbnail>http://thetvdb.com/banners/posters/73244-6.jpg</thumbnail>
</item>

<item>
<title>The Office (US) S09E06</title>
<link>
<sublink>http://BillionUploads.com/uuwp86e80dgh</sublink>
<sublink>http://www.putlocker.com/file/A06C5251D4BA99D1</sublink>
</link> 
<thumbnail>http://thetvdb.com/banners/posters/73244-6.jpg</thumbnail>
</item>

<item>
<title>The Office (US) S09E07</title>
<link>
<sublink>http://BillionUploads.com/55ngyhfipzb3</sublink>
<sublink>http://www.putlocker.com/file/606864F4C7C70608</sublink>
</link> 
<thumbnail>http://thetvdb.com/banners/posters/73244-6.jpg</thumbnail>
</item>

<item>
<title>The Office (US) S09E08</title>
<link>
<sublink>http://BillionUploads.com/vjn6dzriahgk</sublink>
<sublink>http://www.putlocker.com/file/1AFB0B67B89358AB</sublink>
</link> 
<thumbnail>http://thetvdb.com/banners/posters/73244-6.jpg</thumbnail>
</item>

<item>
<title>The Office (US) S09E09</title>
<link>
<sublink>http://BillionUploads.com/rgvj1rv5jq2n</sublink>
<sublink>http://www.putlocker.com/file/D14F5091B97EBE28</sublink>
</link> 
<thumbnail>http://thetvdb.com/banners/posters/73244-6.jpg</thumbnail>
</item>

<item>
<title>The Office (US) S09E10</title>
<link>
<sublink>http://BillionUploads.com/k4eynwivj8i8</sublink>
<sublink>http://www.putlocker.com/file/1B13C429BAF99133</sublink>
</link> 
<thumbnail>http://thetvdb.com/banners/posters/73244-6.jpg</thumbnail>
</item>

<item>
<title>The Office (US) S09E11</title>
<link>
<sublink>http://BillionUploads.com/sucq3kb9oe2g</sublink>
<sublink>http://www.putlocker.com/file/CB2FBD2CB3D0A197</sublink>
</link> 
<thumbnail>http://thetvdb.com/banners/posters/73244-6.jpg</thumbnail>
</item>

<item>
<title>The Office (US) S09E12</title>
<link>
<sublink>http://BillionUploads.com/doucwzygezk3</sublink>
<sublink>http://www.putlocker.com/file/F4439DC27AA28E69</sublink>
</link> 
<thumbnail>http://thetvdb.com/banners/posters/73244-6.jpg</thumbnail>
</item>

<item>
<title>The Office (US) S09E13</title>
<link>
<sublink>http://BillionUploads.com/jh9duee5pi0q</sublink>
<sublink>http://www.putlocker.com/file/ECA99E73ABADC541</sublink>
</link> 
<thumbnail>http://thetvdb.com/banners/posters/73244-6.jpg</thumbnail>
</item>

<item>
<title>The Office (US) S09E14</title>
<link>
<sublink>http://BillionUploads.com/r34ardcpjmns</sublink>
<sublink>http://www.putlocker.com/file/B21435FA01020071</sublink>
</link> 
<thumbnail>http://thetvdb.com/banners/posters/73244-6.jpg</thumbnail>
</item>

<item>
<title>The Office (US) S09E15</title>
<link>
<sublink>http://BillionUploads.com/kawgi9h3uke4</sublink>
<sublink>http://www.putlocker.com/file/CBD2A64D747AEF9C</sublink>
</link> 
<thumbnail>http://thetvdb.com/banners/posters/73244-6.jpg</thumbnail>
</item>

<item>
<title>The Office (US) S09E16</title>
<link>
<sublink>http://BillionUploads.com/5z043qqdywn7</sublink>
<sublink>http://www.putlocker.com/file/592D819A6768B5E7</sublink>
</link> 
<thumbnail>http://thetvdb.com/banners/posters/73244-6.jpg</thumbnail>
</item>

<item>
<title>The Office (US) S09E17</title>
<link>
<sublink>http://BillionUploads.com/as68d0rt9msa</sublink>
<sublink>http://www.putlocker.com/file/7C40858B18211954</sublink>
</link> 
<thumbnail>http://thetvdb.com/banners/posters/73244-6.jpg</thumbnail>
</item>

<item>
<title>The Office (US) S09E18</title>
<link>
<sublink>http://BillionUploads.com/sxolv45x6jtq</sublink>
<sublink>http://www.putlocker.com/file/5ECE85E7641BE5CA</sublink>
</link> 
<thumbnail>http://thetvdb.com/banners/posters/73244-6.jpg</thumbnail>
</item>

<item>
<title>The Office (US) S09E19</title>
<link>
<sublink>http://BillionUploads.com/ae30kok4nfx3</sublink>
<sublink>http://www.putlocker.com/file/D1502A9ABE5B8F79</sublink>
</link> 
<thumbnail>http://thetvdb.com/banners/posters/73244-6.jpg</thumbnail>
</item>

<item>
<title>The Office (US) S09E20</title>
<link>
<sublink>http://BillionUploads.com/m7srk8vl0qge</sublink>
<sublink>http://www.putlocker.com/file/CF7563498B49C29A</sublink>
</link> 
<thumbnail>http://thetvdb.com/banners/posters/73244-6.jpg</thumbnail>
</item>

<item>
<title>The Office (US) S09E21</title>
<link>
<sublink>http://BillionUploads.com/gehadlzfivkn</sublink>
<sublink>http://www.putlocker.com/file/72897B7543FC4C4C</sublink>
</link> 
<thumbnail>http://thetvdb.com/banners/posters/73244-6.jpg</thumbnail>
</item>

<item>
<title>The Office (US) S09E22</title>
<link>
<sublink>http://BillionUploads.com/7xvp1dd16uqf</sublink>
<sublink>http://www.putlocker.com/file/38DE7304EF8D7778</sublink>
</link> 
<thumbnail>http://thetvdb.com/banners/posters/73244-6.jpg</thumbnail>
</item>

<item>
<title>The Office (US) S09E23</title>
<link>
<sublink>http://BillionUploads.com/sv8zqvrqvg4n</sublink>
<sublink>http://www.putlocker.com/file/74BF2A15E454D262</sublink>
</link> 
<thumbnail>http://thetvdb.com/banners/posters/73244-6.jpg</thumbnail>
</item>
