#######################################################################################################################################
<poster>HackerMil</poster>
<fanart>http://www.sino-us.com/UploadFiles/2013/5/26/201305262023538299.jpg</fanart>
#######################################################################################################################################

<info>
<message>[COLOR red]** [/COLOR][COLOR aqua]LATEST EPISODES OF CURRENTLY AIRING SHOWS IN HD[/COLOR][COLOR red] **[/COLOR]</message>
<thumbnail>http://i1367.photobucket.com/albums/r795/HackerMil/Icons/shows_zps719051e4.jpg</thumbnail>
</info>

#########################################################################################################


<item>
<title>The Blacklist S01E02 [COLOR red]*New*[/COLOR]</title>
<link>
<sublink>http://billionuploads.com/wcgzwyppw5h0</sublink>
<sublink>http://billionuploads.com/wcgzwyppw5h0</sublink>
<sublink>http://hugefiles.net/berkkgesncsm</sublink>
<sublink>http://180upload.com/k8wmkipm4aaa</sublink>
<sublink>http://180upload.com/irtd02s1ilg7</sublink>
<sublink>http://epicshare.net/rfijjolc0555</sublink>
<sublink></sublink>
<sublink></sublink>
<sublink></sublink>
</link>
<thumbnail>http://thetvdb.com/banners/posters/266189-3.jpg</thumbnail>
</item>

<item>
<title>Hostages S01E02 [COLOR red]*New*[/COLOR]</title>
<link>
<sublink>http://hugefiles.net/8hilbq0xtpka</sublink>
<sublink>http://hugefiles.net/khlbxyeqzzbg</sublink>
<sublink>http://movreel.com/7bwcsjinmtkl</sublink>
<sublink>http://movreel.com/qd7zejneaqyg</sublink>
<sublink>http://180upload.com/p1i0shny59xc</sublink>
<sublink>http://180upload.com/alxbo7fyznia</sublink>
<sublink>http://epicshare.net/uovnjdd00c7j</sublink>
<sublink>http://epicshare.net/cu3dfajxg3jf</sublink>
</link>
<thumbnail>http://thetvdb.com/banners/posters/269642-4.jpg</thumbnail>
</item>

<item>
<title>Sleepy Hollow S01E03 [COLOR red]*New*[/COLOR]</title>
<link>
<sublink>http://hugefiles.net/05ag9gqy7qch</sublink>
<sublink>http://hugefiles.net/vvgdbuzhey7i</sublink>
<sublink>http://billionuploads.com/xij3sh0d9xqn</sublink>
<sublink>http://movreel.com/5brvpegtjgzp</sublink>
<sublink>http://movreel.com/x3wq35lhr2pp</sublink>
<sublink>http://180upload.com/rcj3bkqqwgtr</sublink>
<sublink>http://180upload.com/wob5fhakveh3</sublink>
<sublink>http://epicshare.net/ev5815zqvits</sublink>
</link>
<thumbnail>http://thetvdb.com/banners/posters/269578-2.jpg</thumbnail>
</item>

<item>
<title>Breaking Bad S05E16</title>
<link>
<sublink>http://billionuploads.com/s3fl5tyiujc7</sublink>
<sublink>http://billionuploads.com/lvqmdmgg2kjz</sublink>
<sublink>http://hugefiles.net/63im30pdy6fh</sublink>
<sublink>http://hugefiles.net/bmm3dhqo9y4w</sublink>
<sublink>http://movreel.com/02nipdx8pwxh</sublink>
<sublink>http://movreel.com/v3zc377ce3pl</sublink>
<sublink>http://180upload.com/ttyb3g2tt1j1</sublink>
<sublink>http://epicshare.net/z1qsmitxgc36</sublink>
</link>
<thumbnail>http://fanart.tv/fanart/tv/81189/tvposter/breaking-bad-5219573896340.jpg</thumbnail>
</item>

<item>
<title>Boardwalk Empire S04E04</title>
<link>
<sublink>http://billionuploads.com/m6j1eldtl9hu</sublink>
<sublink>http://movreel.com/ee6ukx6g8cgh</sublink>
<sublink>http://180upload.com/l6whjvzpvm2j</sublink>
<sublink>http://180upload.com/okkaa8e89bbh</sublink>
<sublink></sublink>
<sublink></sublink>
<sublink></sublink>
<sublink></sublink>
</link>
<thumbnail>http://thetvdb.com/banners/posters/84947-3.jpg</thumbnail>
</item>

<item>
<title>Sons of Anarchy S06E03 </title>
<link>
<sublink>http://billionuploads.com/nticcwv6l33w</sublink>
<sublink>http://epicshare.net/7axm0mhgon52</sublink>
<sublink>http://hugefiles.net/hul4xemoo4xi</sublink>
<sublink></sublink>
<sublink></sublink>
<sublink></sublink>
<sublink></sublink>
</link>
<thumbnail>http://thetvdb.com/banners/posters/82696-4.jpg</thumbnail>
</item>

<item>
<title>Agents of S.H.I.E.L.D. S01E01 </title>
<link>
<sublink>http://billionuploads.com/nemohbno1iy9</sublink>
<sublink>http://billionuploads.com/odiq478zgcoa</sublink>
<sublink>http://movreel.com/rsfsy6qxf2kr</sublink>
<sublink>http://hugefiles.net/l1fl6vj24ez2</sublink>
<sublink>http://180upload.com/uc0q0h79mzsz</sublink>
<sublink>http://180upload.com/d8imxtclpaa2</sublink>
<sublink>http://epicshare.net/7338jtoesz1r</sublink>
<sublink></sublink>
</link>
<thumbnail>http://thetvdb.com/banners/posters/263365-3.jpg</thumbnail>
</item>



<item>
<title>Breaking Bad S05E15</title>
<link>
<sublink>http://billionuploads.com/jjaki1e2xhon</sublink>
<sublink>http://hugefiles.net/duyu8vkx6hkg</sublink>
<sublink>http://180upload.com/ac6slx2ph4sg</sublink>
<sublink>http://epicshare.net/0yg6bmbbeymt</sublink>
<sublink>http://movreel.com/wb99mhtvdmq3</sublink>
</link>
<thumbnail>http://fanart.tv/fanart/tv/81189/tvposter/breaking-bad-5219573896340.jpg</thumbnail>
</item>

<item>
<title>Boardwalk Empire S04E03</title>
<link>
<sublink>http://billionuploads.com/801s058o0wly</sublink>
<sublink>http://billionuploads.com/xcagcfmqtwn3</sublink>
<sublink>http://hugefiles.net/eh1jpx3i6bnc</sublink>
<sublink>http://hugefiles.net/v1dmtan35ewp</sublink>
<sublink>http://180upload.com/skcva62ct0kk</sublink>
<sublink>http://180upload.com/ego1fxj5b7c8</sublink>
<sublink>http://epicshare.net/aktj8tnn1ejw</sublink>
<sublink>http://epicshare.net/regie57mfdqt</sublink>  
</link>
<thumbnail>http://thetvdb.com/banners/posters/84947-3.jpg</thumbnail>
</item>

<item>
<title>Peaky Blinders S01E02</title>
<link>
<sublink>http://billionuploads.com/j0nkqjwzzk01</sublink>
<sublink>http://www.putlocker.com/file/FFF12D2A234448A4</sublink>
<sublink>http://hugefiles.net/rhr1pfhowllo</sublink>
<sublink>http://mightyupload.com/hstj0ygsdw5r</sublink>
<sublink>http://180upload.com/f0hm2h0b8qzi</sublink>
<sublink>http://epicshare.net/qatzjjfoncq5</sublink>
</link>
<thumbnail>http://i1367.photobucket.com/albums/r795/HackerMil/Posters/MV5BMTQxODYzNTQzOV5BMl5BanBnXkFtZTgwMTI2MDYwMDE_V1_SX600_SY869_.jpg</thumbnail>
</item>

<item>
<title>Master Of Sex S01E02</title>
<link>
<sublink>http://billionuploads.com/9tl7d8u65ms7</sublink>
<sublink>http://www.putlocker.com/file/4E294550F060E7DB</sublink>
<sublink>http://hugefiles.net/a12u23xablfv</sublink>
<sublink>http://mightyupload.com/aymtgm23v3rb</sublink>
<sublink>http://180upload.com/b3xl3vtu5c64</sublink>
<sublink>http://epicshare.net/rn1yx3m1nqi5</sublink>
</link>
<thumbnail>http://thetvdb.com/banners/posters/261557-2.jpg</thumbnail>
</item>























