#######################################################################################################################################
<poster>HackerMil</poster>
<fanart>http://farm6.staticflickr.com/5460/10217454264_7eda59c6f3_o.png</fanart>
#######################################################################################################################################

<popup>
<name>[COLOR red]CLICK HERE[/COLOR] [COLOR aqua]FOR INFO ON JOINING THE VIP CLUB AND DETAILS[/COLOR]</name>
<popImage>http://farm3.staticflickr.com/2851/10218170123_bb90f51c7e_o.png</popImage>
<thumbnail>http://farm6.staticflickr.com/5510/10217412394_e1da1b6fcc_o.jpg</thumbnail>
</popup>


###############################################################################################################
[COLOR blue]Movie[/COLOR] 
[COLOR blue]Episode[/COLOR] 
[COLOR blue]Event[/COLOR] 
[COLOR blue]Fight[/COLOR] 
[COLOR blue]Documentary[/COLOR] 
[COLOR blue]Standup[/COLOR] 
[COLOR blue]KidsMovie[/COLOR] 
 [COLOR lime][/COLOR]

###############################################################################################################


<item>
<title>[COLOR blue]Episode[/COLOR] American Horror Story S03E10 HD [COLOR lime]1/8[/COLOR]</title>
<link>
<sublink>http://billionuploads.com/uqruw7irycbq</sublink>
<sublink>http://hugefiles.net/ndc5ewgrg5z5</sublink>
<sublink>http://180upload.com/f13gpr7bhdex</sublink>
<sublink>http://epicshare.net/5kpknj0jefo8</sublink>
<sublink>http://movreel.com/2bljhz55oole</sublink>
</link> 
<thumbnail>http://thetvdb.com/banners/posters/250487-15.jpg</thumbnail>
</item>

<item>
<title>[COLOR blue]Movie[/COLOR] Grudge Match (2013) CAM [COLOR lime]1/8[/COLOR]</title>
<link>
<sublink>http://billionuploads.com/6iju0lvyvr1l</sublink>
<sublink>http://hugefiles.net/ro839inkqxgt</sublink>
<sublink>http://180upload.com/ufkv2szs5vui</sublink>
<sublink>http://www.putlocker.com/file/30CDCDCE96A502C5</sublink>
<sublink>http://movreel.com/vmg302sn8iot.html</sublink>
<sublink></sublink>
<sublink></sublink>
</link>
<thumbnail>http://image.tmdb.org/t/p/original/m7tCLFtU5TlbWbjsrAS34yODw2M.jpg</thumbnail>
</item>

<item>
<title>[COLOR blue]Movie[/COLOR] The Wolf of Wall Street (2013) DVDScr [COLOR lime]1/8[/COLOR]</title>
<link>
<sublink>http://bayfiles.net/file/13hX3/S4ANEo/Gur.Jbys.bs.Jnyy.Fgerrg.2013..DVDScr.divx</sublink>
<sublink>http://BillionUploads.com/hb29elru2syq</sublink>
<sublink>http://hugefiles.net/h6mfo251fnpm</sublink>
<sublink>http://epicshare.net/2y4cgcapqfsu/Gur.Jbys.bs.Jnyy.Fgerrg.2013..DVDScr.divx.html</sublink>
<sublink>http://megarelease.org/2y4cgcapqfsu</sublink>
<sublink>http://megarelease.org/4hrtojnxktws</sublink>
</link>
<thumbnail>http://image.tmdb.org/t/p/original/utfEHZ9jG1emGdvJ4GgfMcHoznp.jpg</thumbnail>
</item>

<item>
<title>[COLOR blue]Movie[/COLOR] Short Term 12 (2013) HD [COLOR lime]1/8[/COLOR]</title>
<link>
<sublink>http://billionuploads.com/rzdtiqa59xts</sublink>
<sublink>http://hugefiles.net/lbx53onerhan</sublink>
<sublink>http://180upload.com/pgy2xfbaej09</sublink>
<sublink>http://movreel.com/r1slcvz5m9or</sublink>
</link>
<thumbnail>http://image.tmdb.org/t/p/original/1bg6bhR2HSebsMsP4kR39hnlgDr.jpg</thumbnail>
</item>

<item>
<title>[COLOR blue]Movie[/COLOR] The Necessary Death Of Charlie Countryman (2013) HD [COLOR lime]1/8[/COLOR]</title>
<link>
<sublink>http://billionuploads.com/bnbf5gxiu4zw</sublink>
<sublink>http://hugefiles.net/i5px27xqw9ak</sublink>
<sublink>http://180upload.com/mw8k43ucnush</sublink>
<sublink>http://www.putlocker.com/file/75CBC53D3A281A18</sublink>
</link>
<thumbnail>http://image.tmdb.org/t/p/original/6sRzGtV89CnxdihwYUCb97h9xuq.jpg</thumbnail>
</item>

<item>
<title>[COLOR blue]Movie[/COLOR] August: Osage County (2014) DVDScr [COLOR lime]1/8[/COLOR]</title>
<link>
<sublink>http://billionuploads.com/rd12yrh22d52</sublink>
<sublink>http://hugefiles.net/rd940b8rkkbo</sublink>
<sublink>http://megarelease.org/aesdcjixo1er</sublink>
<sublink>http://180upload.com/jaibnbm662k8</sublink>
<sublink>http://epicshare.net/aesdcjixo1er</sublink>
<sublink>http://movreel.com/4hwqdvnetz5w</sublink>
<sublink></sublink>
<sublink></sublink>
</link>
<thumbnail>http://image.tmdb.org/t/p/original/pzWObM6rGffLwpaKDzOY4ykhzvu.jpg</thumbnail>
</item>

<item>
<title>[COLOR blue]Movie[/COLOR] Her (2013) DVDScr [COLOR lime]1/8[/COLOR]</title>
<link>
<sublink>http://billionuploads.com/bv5ywugxmqzs</sublink>
<sublink>http://hugefiles.net/0q6prma1dfn9</sublink>
<sublink>http://megarelease.org/p79vndn4yg5s</sublink>
<sublink>http://180upload.com/ulhl317b9yfe</sublink>
<sublink>http://epicshare.net/eqhs0bi57zu8</sublink>
<sublink>http://movreel.com/4ol49503jijg</sublink>
<sublink></sublink>
<sublink></sublink>
</link>
<thumbnail>http://image.tmdb.org/t/p/original/zbVhV2v1j69nvwHp2r8kjawI6H9.jpg</thumbnail>
</item>

<item>
<title>[COLOR blue]Movie[/COLOR] Captain Phillips (2013) HD [COLOR lime]1/8[/COLOR]</title>
<link>
<sublink>http://billionuploads.com/l0fsdsiub5tl</sublink>
<sublink>http://hugefiles.net/dhj8nw1auhex</sublink>
<sublink>http://180upload.com/rb7to05kwmth</sublink>
<sublink>http://epicshare.net/9l2e19c3f7es</sublink>
<sublink>http://movreel.com/tchifmezdjsb</sublink>
<sublink>http://megarelease.org/9l2e19c3f7es</sublink>
</link>
<thumbnail>http://d3gtl9l2a4fn1j.cloudfront.net/t/p/original/lILIOfZkVlpx7m503z8t0oPhjCa.jpg</thumbnail>
</item>

<item>
<title>[COLOR blue]Movie[/COLOR] Escape Plan (2013) HD [COLOR lime]1/8[/COLOR]</title>
<link>
<sublink>http://billionuploads.com/exfqxahtsj3k</sublink>
<sublink>http://hugefiles.net/un9yx5sse00s</sublink>
<sublink>http://180upload.com/vvhgacd9brgj</sublink>
<sublink>http://movreel.com/74u3cpndf0lz</sublink>
</link>
<thumbnail>http://d3gtl9l2a4fn1j.cloudfront.net/t/p/original/6tWNWbSv4pmPzJQV25XHGeV6kQX.jpg</thumbnail>
</item>

<item>
<title>[COLOR blue]ForeignMovie[/COLOR] On the Job (2013) DVD [COLOR lime]1/8[/COLOR]</title>
<link>
<sublink>http://billionuploads.com/wew7joyzfcpq</sublink>
<sublink>http://hugefiles.net/m60c66y54ba3</sublink>
<sublink>http://megarelease.org/6hc7vzaj9v76</sublink>
<sublink>http://180upload.com/m9tron2y0h06</sublink>
<sublink>http://180upload.com/m9tron2y0h06</sublink>
<sublink>http://movreel.com/e2l9wpw3gowu</sublink>
<sublink></sublink>
<sublink></sublink>
</link>
<thumbnail>http://image.tmdb.org/t/p/original/3SbN1pncHW7c7dCepfb4AEkJYC.jpg</thumbnail>
</item>

<item>
<title>[COLOR blue]Standup[/COLOR] Jim Jefferies: Fully Functional (2012) [COLOR lime]1/8[/COLOR]</title>
<link>
<sublink>http://billionuploads.com/vq0t744tbafe</sublink>
<sublink>http://hugefiles.net/nsnii2um5sxh</sublink>
<sublink>http://180upload.com/xuyr1zzoy13s</sublink>
<sublink>http://movreel.com/sz5cm9ldskv4</sublink>
</link>
<thumbnail>http://image.tmdb.org/t/p/original/3wV16zbhYGyas7zSDpa0WbfudgY.jpg</thumbnail>
</item>

<item>
<title>[COLOR blue]Documentary[/COLOR] Inequality for All (2013) [COLOR lime]1/8[/COLOR]</title>
<link>
<sublink>http://billionuploads.com/hhqm4gm2vf8t</sublink>
<sublink>http://hugefiles.net/gdj72spuwf8r</sublink>
<sublink>http://180upload.com/d7lssyh53gqz</sublink>
<sublink>http://megarelease.org/2qv4l5hhuzms</sublink>
<sublink>http://epicshare.net/2qv4l5hhuzms</sublink>
<sublink>http://movreel.com/i7lja1rq2dnm</sublink>
<sublink></sublink>
<sublink></sublink>
</link>
<thumbnail>http://image.tmdb.org/t/p/original/eNHLfgOvfe9ZgE3N3kuE61mOdmR.jpg</thumbnail>
</item>

<item>
<title>[COLOR blue]Movie[/COLOR] Frozen (2013) DVDScr [COLOR lime]1/8[/COLOR]</title>
<link>
<sublink>http://billionuploads.com/6ks59hk50g5h</sublink>
<sublink>http://hugefiles.net/bkrdmd3cre9h</sublink>
<sublink>http://180upload.com/2cx5d3rqeqtd</sublink>
<sublink>http://movreel.com/ma513a1ezgpq</sublink>
</link>
<thumbnail>http://d3gtl9l2a4fn1j.cloudfront.net/t/p/original/xYVunS2yloXIwq3ngQRhPFX2s7.jpg</thumbnail>
</item>

<item>
<title>[COLOR blue]Episode[/COLOR] Agents of S.H.I.E.L.D. S01E11 HD [COLOR lime]1/8[/COLOR]</title>
<link>
<sublink>http://billionuploads.com/odulwiknaz9c</sublink>
<sublink>http://hugefiles.net/l9c0iq8eexzd</sublink>
<sublink>http://megarelease.org/q9evm4scujin</sublink>
<sublink>http://180upload.com/e4stizc8asqm</sublink>
<sublink>http://epicshare.net/q9evm4scujin</sublink>
<sublink>http://movreel.com/aajpdas4dpsd</sublink>
</link>
<thumbnail>http://thetvdb.com/banners/posters/263365-3.jpg</thumbnail>
</item>
























<item>
<title>[COLOR blue]Episode[/COLOR] Shameless (US) S04E01 HD [COLOR lime]1/6[/COLOR]</title>
<link>
<sublink>http://billionuploads.com/x3afuzhg5jpn</sublink>
<sublink>http://hugefiles.net/f4z0pyropliz</sublink>
<sublink>http://180upload.com/py2v185zfhb0</sublink>
<sublink>http://movreel.com/ndgtntbyvmwh</sublink>
<sublink>http://billionuploads.com/5176s5tlt6uw</sublink>
<sublink>http://hugefiles.net/btpzvjjw5ivs</sublink>
<sublink>http://180upload.com/fktqilavcjhq</sublink>
<sublink>http://movreel.com/dcioq60my5wg</sublink>  
</link> 
<thumbnail>http://thetvdb.com/banners/posters/161511-6.jpg</thumbnail>
</item>

<item>
<title>[COLOR blue]Episode[/COLOR] Hostages S01E14 HD [COLOR lime]1/6[/COLOR]</title>
<link>
<sublink>http://billionuploads.com/oom38m9pm4s4</sublink>
<sublink>http://hugefiles.net/bsl30bw3onka</sublink>
<sublink>http://180upload.com/wi8qnpnlhpib</sublink>
<sublink>http://epicshare.net/8ug7ouptvi38</sublink>
<sublink>http://epicshare.net/8ug7ouptvi38</sublink>
<sublink>http://megarelease.org/8ug7ouptvi38</sublink>
<sublink>http://lemuploads.com/4krfg23i6f04</sublink>
</link>
<thumbnail>http://thetvdb.com/banners/posters/269642-4.jpg</thumbnail>
</item>

<item>
<title>[COLOR blue]Episode[/COLOR] Hostages S01E15 HD [COLOR lime]1/6[/COLOR]</title>
<link>
<sublink>http://billionuploads.com/xxxklf2utk1g</sublink>
<sublink>http://hugefiles.net/pecm5sxu8jo0</sublink>
<sublink>http://180upload.com/77qj6zhxxqer</sublink>
<sublink>http://epicshare.net/83xf501lutrm</sublink>
<sublink>http://movreel.com/83wm68rrend8</sublink>
<sublink>http://megarelease.org/83xf501lutrm</sublink>
</link>
<thumbnail>http://thetvdb.com/banners/posters/269642-4.jpg</thumbnail>
</item>

<item>
<title>[COLOR blue]Episode[/COLOR] Almost Human S01E07 HD [COLOR lime]1/6[/COLOR]</title>
<link>
<sublink>http://billionuploads.com/96p0p01eyytp</sublink>
<sublink>http://hugefiles.net/5h357ajamy1s</sublink>
<sublink>http://180upload.com/qgxm7yn9q5xq</sublink>
<sublink>http://epicshare.net/4qdxdplysoqo</sublink>
<sublink>http://movreel.com/g6asxrwbnb5m</sublink>
<sublink>http://movreel.com/g6asxrwbnb5m</sublink>
</link>
<thumbnail>http://thetvdb.com/banners/posters/267702-4.jpg</thumbnail>
</item>










<item>
<title>[COLOR blue]Movie[/COLOR] Carrie (2013) 1080P [COLOR lime]1/5[/COLOR]</title>
<link>
<sublink>http://billionuploads.com/4jm0nubbp4y9</sublink>
<sublink>http://hugefiles.net/w6rut4sejmcl</sublink>
<sublink>http://180upload.com/xqozvqei0dwe</sublink>
</link>
<thumbnail>http://d3gtl9l2a4fn1j.cloudfront.net/t/p/original/xU8lJawYVuvhaR9wxwhlmq5lEsM.jpg</thumbnail>
</item>

<item>
<title>[COLOR blue]Movie[/COLOR] Carrie (2013) HD [COLOR lime]1/5[/COLOR]</title>
<link>
<sublink>http://37.58.68.221/index.php?file=2740&start=0&hd=0&auth=0&type=flv&tv=0</sublink>
<sublink>http://billionuploads.com/16il6gfxynj8</sublink>
<sublink>http://hugefiles.net/y4ay691ye3fd</sublink>
<sublink>http://180upload.com/iptmohiamipa</sublink>
<sublink>http://epicshare.net/2199nk7pgl7h</sublink>
<sublink>http://movreel.com/rbpe1on1y4vr</sublink>
<sublink>http://megarelease.org/2199nk7pgl7h</sublink>
<sublink>http://lemuploads.com/2199nk7pgl7h</sublink>
</link>
<thumbnail>http://d3gtl9l2a4fn1j.cloudfront.net/t/p/original/xU8lJawYVuvhaR9wxwhlmq5lEsM.jpg</thumbnail>
</item>



<item>
<title>[COLOR blue]Movie[/COLOR] The Spectacular Now (2013) HD [COLOR lime]1/5[/COLOR]</title>
<link>
http://37.58.68.221/index.php?file=2686&start=0&hd=0&auth=0&type=flv&tv=0
<sublink>http://billionuploads.com/g0thynneh420</sublink>
<sublink>http://hugefiles.net/j1ut315it02y</sublink>
<sublink>http://180upload.com/klg5i5krzopu</sublink>
<sublink>http://movreel.com/pcxjbeupyfzc</sublink>
</link>
<thumbnail>http://image.tmdb.org/t/p/original/q82YNrWCwYQZAHvCdlXOORQ3Mdj.jpg</thumbnail>
</item>




<item>
<title>[COLOR blue]Movie[/COLOR] The Adventurer: The Curse of the Midas Box (2014) SD [COLOR lime]1/5[/COLOR]</title>
<link>
<sublink>http://billionuploads.com/spt8h0gg4kn5</sublink>
<sublink>http://180upload.com/sxmsmuem1zvb</sublink>
<sublink>http://180upload.com/19181ddgylsn</sublink>
<sublink>http://www.putlocker.com/file/B165074B848E0ED5#</sublink>
<sublink>http://www.sockshare.com/file/2096766FF1D91BA4</sublink>
<sublink></sublink>
<sublink></sublink>
<sublink></sublink>
</link>
<thumbnail>http://image.tmdb.org/t/p/original/mpJu9ZTLibtR71yrlhcksX01Tbl.jpg</thumbnail>
</item>

<item>
<title>[COLOR blue]Movie[/COLOR] The Secret Life of Walter Mitty (2013) CAM [COLOR lime]1/5[/COLOR]</title>
<link>
<sublink>http://billionuploads.com/79gahgwa0m4x</sublink>
<sublink>http://billionuploads.com/3lz834iiotxw/The.Secret.Life.of.Walter.Mitty.2013.CAM.AAC.x264-SSDD.mp4</sublink>
<sublink>http://hugefiles.net/f38eqg24xqj0</sublink>
<sublink>http://hugefiles.net/dnfh0uiz0k2k</sublink>
<sublink>http://180upload.com/onwss7yoapcx</sublink>
<sublink>http://www.putlocker.com/file/B9526EAAB5304F8A</sublink>
<sublink>http://movreel.com/1803waez7rpg.html</sublink>
<sublink></sublink>
</link>
<thumbnail>http://image.tmdb.org/t/p/original/9TzcuIuJoJaM91GKDni9CWdi2qo.jpg</thumbnail>
</item>

<item>
<title>[COLOR blue]Movie[/COLOR] Blue Jasmine (2013) DVDScr [COLOR lime]1/5[/COLOR]</title>
<link>
<sublink>http://billionuploads.com/iak7buysupe4</sublink>
<sublink>http://hugefiles.net/q5na9zwujlzj</sublink>
<sublink>http://180upload.com/7uulwreslk8a</sublink>
<sublink>http://epicshare.net/5mgazpsyayal</sublink>
<sublink>http://movreel.com/nzv7g9l3pk1z</sublink>
<sublink>http://megarelease.org/5mgazpsyayal</sublink>
<sublink></sublink>
<sublink></sublink>
</link>
<thumbnail>http://image.tmdb.org/t/p/original/6TBS5ZBf5ADIkUBhTg53tezVbUZ.jpg</thumbnail>
</item>


<item>
<title>[COLOR blue]Fight[/COLOR] UFC Fight Night: 34 Saffiedine vs Lim HD [COLOR lime]1/5[/COLOR]</title>
<link>
<sublink>http://hugefiles.net/7hy6wojqfidw</sublink>
<sublink>http://180upload.com/6rxc1ccy28d1</sublink>
</link>
<thumbnail>http://upload.wikimedia.org/wikipedia/en/0/0b/New_UFN_34_poster.jpg</thumbnail>
</item>

<item>
<title>[COLOR blue]Episode[/COLOR] Dracula S01E07 HD [COLOR lime]1/3[/COLOR]</title>
<link>
<sublink>http://billionuploads.com/34jo7ue9ndgm</sublink>
<sublink>http://hugefiles.net/j50nfiv44fdd</sublink>
<sublink>http://180upload.com/nb4ytd7dose8</sublink>
<sublink>http://epicshare.net/rx6ko0rvqv3i</sublink>
<sublink>http://epicshare.net/rx6ko0rvqv3i</sublink>
</link>
<thumbnail>http://thetvdb.com/banners/posters/263724-1.jpg</thumbnail>
</item>

<item>
<title>[COLOR blue]Movie[/COLOR] You're Next (2013) 1080P [COLOR lime]1/3[/COLOR]</title>
<link>
<sublink>http://billionuploads.com/bomvvc66gchj</sublink>
<sublink>http://hugefiles.net/1hpr07bkpy4d</sublink>
<sublink>http://180upload.com/mk5r8kcnpq5a</sublink>
</link>
<thumbnail>http://d3gtl9l2a4fn1j.cloudfront.net/t/p/original/iP4NC9Ycj8yKh4ktxjJLWZmBKZK.jpg</thumbnail>
</item>

<item>
<title>[COLOR blue]Movie[/COLOR] You're Next (2013) HD [COLOR lime]1/3[/COLOR]</title>
<link>
<sublink>http://billionuploads.com/crsd9gvqnnzg</sublink>
<sublink>http://hugefiles.net/gowlon7fndfy</sublink>
<sublink>http://180upload.com/6og87g506n5h</sublink>
<sublink>http://www.putlocker.com/file/E7FCC521336B02B8</sublink>
<sublink>http://www.sockshare.com/file/BB952861CC2B9EE1</sublink>
</link>
<thumbnail>http://d3gtl9l2a4fn1j.cloudfront.net/t/p/original/iP4NC9Ycj8yKh4ktxjJLWZmBKZK.jpg</thumbnail>
</item>

<item>
<title>[COLOR blue]Movie[/COLOR] Lone Survivor (2014) HD [COLOR lime]1/3[/COLOR]</title>
<link>
<sublink>http://billionuploads.com/8qplrh5k204z</sublink>
<sublink>http://hugefiles.net/cpq65b5tguee</sublink>
<sublink>http://180upload.com/47hqa04n9ezn</sublink>
<sublink>http://movreel.com/e8lmo31d9ksm</sublink>
<sublink>http://vidhog.com/e38x1le0gkc1</sublink>
<sublink>http://180upload.com/47hqa04n9ezn</sublink>
</link>
<thumbnail>http://image.tmdb.org/t/p/original/tVq4EVixCwSDiPojlbafoHfTsU4.jpg</thumbnail>
</item>2014-01-10

<item>
<title>[COLOR blue]Movie[/COLOR] Twelve Years a Slave (2013) DVDScr [COLOR lime]1/3[/COLOR]</title>
<link>
<sublink>http://37.58.68.221/index.php?file=2732&start=0&hd=0&auth=0&type=flv&tv=0</sublink>
</link>
<thumbnail>http://d3gtl9l2a4fn1j.cloudfront.net/t/p/original/xosImeLYPS0Q1I2OOKXh1pjmnGQ.jpg</thumbnail>
</item>



<item>
<title>[COLOR blue]Movie[/COLOR] Jackass Presents: Bad Grandpa (2013) HD [COLOR lime]1/3[/COLOR]</title>
<link>
<sublink>http://37.58.68.221/index.php?file=2741&start=0&hd=0&auth=0&type=flv&tv=0</sublink>
<sublink>http://billionuploads.com/kahkoo6v5rrd</sublink>
<sublink>http://hugefiles.net/ptkc49oorzea</sublink>
<sublink>http://180upload.com/z15mpcvxsztm</sublink>
<sublink>http://epicshare.net/37xwrgw4skc2</sublink>
<sublink>http://movreel.com/in29hdjfp4nv</sublink>
<sublink>http://megarelease.org/37xwrgw4skc2</sublink>
<sublink>http://lemuploads.com/37xwrgw4skc2</sublink>
</link>
<thumbnail>http://d3gtl9l2a4fn1j.cloudfront.net/t/p/original/cJiThVkLmb6yZZvH2lSSz8gOEm8.jpg</thumbnail>
</item>

<item>
<title>[COLOR blue]Movie[/COLOR] Dallas Buyers Club (2013) DVDScr [COLOR lime]1/3[/COLOR]</title>
<link>
<sublink>http://billionuploads.com/pvval2kwstrx</sublink>
<sublink>http://hugefiles.net/mu6ri8924q1i</sublink>
<sublink>http://180upload.com/r8qn1r4f0882</sublink>
<sublink>http://epicshare.net/a0vbof3kll2l</sublink>
<sublink>http://epicshare.net/a0vbof3kll2l</sublink>
<sublink>http://megarelease.org/a0vbof3kll2l</sublink>
<sublink>http://megarelease.org/a0vbof3kll2l</sublink>
<sublink></sublink>
</link>
<thumbnail>http://image.tmdb.org/t/p/original/tc8QxMmMsKwGJ7Jw4c8UOZbxFTU.jpg</thumbnail>
</item>


<item>
<title>[COLOR blue]Movie[/COLOR] About Time (2013) HD [COLOR lime]1/2[/COLOR]</title>
<link>
<sublink>http://37.58.68.221/index.php?file=2730&start=0&hd=0&auth=0&type=flv&tv=0</sublink>
<sublink>http://billionuploads.com/dwfzll5xym62</sublink>
<sublink>http://hugefiles.net/z4o7n4yw208w</sublink>
<sublink>http://180upload.com/ji3vpy4zoigr</sublink>
<sublink>http://movreel.com/4urkm2m2k4dm</sublink>
</link>
<thumbnail>http://image.tmdb.org/t/p/original/rQvmW5HMS0odyW52QpqpzBpAmaf.jpg</thumbnail>
</item>

<item>
<title>[COLOR blue]Movie[/COLOR] Freezer (2014) HD [COLOR lime]12/31[/COLOR]</title>
<link>
<sublink>http://hugefiles.net/aq4aqn9akhd4</sublink>
<sublink>http://180upload.com/3vdsfp8psy7y</sublink>
<sublink>http://movreel.com/lpileyt8ypti</sublink>
<sublink></sublink>
</link>
<thumbnail>http://image.tmdb.org/t/p/original/eELqMf6wWQdHA4cEwUdGshqyHDl.jpg</thumbnail>
</item>2014-01-17

<item>
<title>[COLOR blue]Movie[/COLOR] Last Vegas (2013) HDCAM [COLOR lime]12/31[/COLOR]</title>
<link>
<sublink>http://billionuploads.com/fatjctcbwdvh</sublink>
<sublink>http://hugefiles.net/x3kf7m0ijsd7</sublink>
<sublink>http://www.putlocker.com/file/8B77808E3969E82F</sublink>
<sublink>http://movreel.com/b3s4e4xkyiwh.html</sublink>
<sublink>http://sharesix.com/nzebjw2jwc2x</sublink>
<sublink></sublink>
<sublink></sublink>
<sublink></sublink>
</link>
<thumbnail>http://image.tmdb.org/t/p/original/tBiAdXNAesfe8cpuUd54pgsqGkI.jpg</thumbnail>
</item> 2013-11-01



<item>
<title>[COLOR blue]Movie[/COLOR] All Is Lost (2013) HDRip [COLOR lime]12/31[/COLOR]</title>
<link>
<sublink>http://billionuploads.com/xrbs5c2qbbvb</sublink>
<sublink>http://hugefiles.net/s9ngyw1ocwo2</sublink>
<sublink>http://movreel.com/zb8daslsjp5a.html</sublink>
<sublink>http://www.putlocker.com/file/CEED0A1D19CA68D6</sublink>
<sublink>http://180upload.com/0qleyavpbcdh</sublink>
<sublink></sublink>
<sublink></sublink>
<sublink></sublink>
</link>
<thumbnail>http://image.tmdb.org/t/p/original/wqLXT6Q8BcDWOHdPi0key8IMEmY.jpg</thumbnail>
</item> 2013-10-18

<item>
<title>[COLOR blue]Movie[/COLOR] Enough Said (2013) DVD [COLOR lime]12/31[/COLOR]</title>
<link>
<sublink>http://billionuploads.com/e1t3f7qd2c96</sublink>
<sublink>http://billionuploads.com/k2h72yz3m2f0</sublink>
<sublink>http://hugefiles.net/sex1qi969p58</sublink>
<sublink>http://hugefiles.net/qv9lh8tsvpi8</sublink>
<sublink>http://180upload.com/a3s3hey9al27</sublink>
<sublink>http://180upload.com/a3s3hey9al27</sublink>
<sublink>http://movreel.com/x6lq1etbctu3</sublink>
<sublink>http://movreel.com/x6lq1etbctu3</sublink>
</link>
<thumbnail>http://image.tmdb.org/t/p/original/iwg42td071ROQpfI9T5DEpZYArm.jpg</thumbnail>
</item>

<item>
<title>[COLOR blue]Movie[/COLOR] A.C.O.D. (2013) HD [COLOR lime]12/31[/COLOR]</title>
<link>
<sublink>http://hugefiles.net/9maa9jmjlbo6</sublink>
<sublink>http://hugefiles.net/9vjgm3cbmfwn</sublink>
<sublink>http://180upload.com/p6hvomm5binu</sublink>
<sublink>http://180upload.com/eqom0fhvjmum</sublink>
<sublink>http://movreel.com/bfh0grtevfl6</sublink>
<sublink>http://movreel.com/40hw28bh6hsm</sublink>
<sublink></sublink>
<sublink></sublink>
</link>
<thumbnail>http://image.tmdb.org/t/p/original/cO87I4zTfEGyKqeTiMNRkYjmdzK.jpg</thumbnail>
</item>2013-10-04







<item>
<title>[COLOR blue]Movie[/COLOR] American Hustle (2013) SD [COLOR lime]12/30[/COLOR]</title>
<link>
<sublink>http://37.58.68.221/index.php?file=2691&start=0&hd=0&auth=0&type=flv&tv=0</sublink>
<sublink>http://billionuploads.com/6gf0nhnfe4uk</sublink>
<sublink>http://billionuploads.com/7j0fh7leo0w0</sublink>
<sublink>http://billionuploads.com/zbmmdghte6ug</sublink>
<sublink>http://billionuploads.com/zbmmdghte6ug</sublink>
<sublink>http://hugefiles.net/a8whbc8m6ie7</sublink>
<sublink>http://hugefiles.net/3zyms612fwgz</sublink>
<sublink>http://180upload.com/rqz6sibpc7cb</sublink>
<sublink>http://180upload.com/oq4idb1up492</sublink>
<sublink>http://180upload.com/9fuc5fybwggq</sublink>
<sublink>http://180upload.com/x0vpkfdreur1</sublink>
<sublink>http://epicshare.net/lm2a3dc0twig</sublink>
<sublink>http://epicshare.net/j186i6r93583</sublink>
<sublink>http://movreel.com/wdn5ei4capsd</sublink>
<sublink>http://movreel.com/u4svn2rfgjew</sublink>
<sublink></sublink>
<sublink></sublink>
</link>
<thumbnail>http://image.tmdb.org/t/p/original/8sar0KkBnJQ2UMMRw9L1spv2qkP.jpg</thumbnail>
</item>



<item>
<title>[COLOR blue]Movie[/COLOR] Rush (2013) HD [COLOR lime]12/30[/COLOR]</title>
<link>
<sublink>http://37.58.68.221/index.php?file=2728&start=0&hd=0&auth=0&type=flv&tv=0</sublink>
<sublink>http://billionuploads.com/fkl5ur2moe1o</sublink>
<sublink>http://hugefiles.net/3w232oq05z0i</sublink>
<sublink>http://180upload.com/bej2a2j6golq</sublink>
<sublink>http://180upload.com/jgou5hmpbgy5</sublink>
<sublink>http://movreel.com/k0g1z1enuxfz</sublink>
</link>
<thumbnail>http://d3gtl9l2a4fn1j.cloudfront.net/t/p/original/cjEepHZOZAwmK6nAj5jis6HV75E.jpg</thumbnail>
</item>

<item>
<title>[COLOR blue]Event[/COLOR] UFC 168: Weidman vs. Silva II Dec. 28, 2013 [COLOR lime]12/28[/COLOR]</title>
<link>
<sublink>http://bayfiles.net/file/12G8x/zTmWJ9/HSP.168.Jrvqzna.if.Fvyin.VV.HDTV.divx</sublink>
<sublink>http://BillionUploads.com/vl7t6g1nxc4k</sublink>
<sublink>http://180upload.com/2y5rzziabbya</sublink>
</link>
<thumbnail>http://upload.wikimedia.org/wikipedia/en/4/47/UFC_168_event_poster.jpg</thumbnail>
</item>

<item>
<title>[COLOR blue]ForeignMovie[/COLOR] Badges of Fury (2013) HD [COLOR lime]12/28[/COLOR]</title>
<link>
<sublink>http://billionuploads.com/8s8eiiqse4gq</sublink>
<sublink>http://movreel.com/2lws4ytjh52s</sublink>
<sublink>http://180upload.com/dc1pn4j9jmpz</sublink>
<sublink>http://180upload.com/1q5lg1g9rh5i</sublink>
</link>
<thumbnail>http://image.tmdb.org/t/p/original/bXd9v2fSVZih0frr2kv2Mt1LBHq.jpg</thumbnail>
</item>

<item>
<title>[COLOR blue]Movie[/COLOR] Saving Mr. Banks (2013) DVDScr [COLOR lime]12/28[/COLOR]</title>
<link>
<sublink>http://37.58.68.221/index.php?file=2679&start=0&hd=0&auth=0&type=flv&tv=0</sublink>
<sublink>http://hugefiles.net/ph11qc5rcquw</sublink>
<sublink>http://hugefiles.net/lcd27s1ui67u</sublink>
<sublink>http://180upload.com/6fr385plc8ex</sublink>
<sublink>http://180upload.com/yzw4swdha1xu</sublink>
<sublink>http://epicshare.net/nssoc6peoifr</sublink>
<sublink>http://movreel.com/6bpd4k5ozbjl</sublink>
<sublink>http://movreel.com/xu3shuveb7mr</sublink>
</link>
<thumbnail>http://image.tmdb.org/t/p/original/aG33huZ8MJJNUsDrBK22cIuiuUM.jpg</thumbnail>
</item>

<item>
<title>[COLOR blue]Documentary[/COLOR] Terms and Conditions May Apply (2013) [COLOR lime]12/28[/COLOR]</title>
<link>
<sublink>http://billionuploads.com/58pw6gvsywdo</sublink>
<sublink>http://180upload.com/jk4xzdg7y7tu</sublink>
<sublink>http://movreel.com/1h4xo28578e2</sublink>
<sublink>http://hugefiles.net/000gc9ws9w8t</sublink>
</link>
<thumbnail>http://image.tmdb.org/t/p/original/72TNDeUsUupWXtw8pCdQhu6yD9.jpg</thumbnail>
</item>



<item>
<title>[COLOR blue]Movie[/COLOR] Walking With Dinosaurs (2013) CAM [COLOR lime]12/28[/COLOR]</title>
<link>
<sublink>http://billionuploads.com/r9dqi6171vya</sublink>
<sublink>http://billionuploads.com/0oo6j5vrvhjy/WalkingwithDinosaurs2013CAMx246AAC-Maremaid.mkv</sublink>
<sublink>http://hugefiles.net/fnhdwevnbd09</sublink>
<sublink>http://180upload.com/tailu7jm5of4</sublink>
<sublink>http://mightyupload.com/07atn9c81uc9/Walking_with_Dinosaurs_2013_CAM_x246_AAC.mkv.html</sublink>
</link>
<thumbnail>http://image.tmdb.org/t/p/original/syrPo4XWmrEaA8YeGLaKWOmT2a1.jpg</thumbnail>
</item>

<item>
<title>[COLOR blue]Movie[/COLOR] Walking With Dinosaurs (2013) CAM [COLOR lime]12/28[/COLOR]</title>
<link>
<sublink>http://billionuploads.com/r9dqi6171vya</sublink>
<sublink>http://billionuploads.com/0oo6j5vrvhjy/WalkingwithDinosaurs2013CAMx246AAC-Maremaid.mkv</sublink>
<sublink>http://hugefiles.net/fnhdwevnbd09</sublink>
<sublink>http://180upload.com/tailu7jm5of4</sublink>
<sublink>http://mightyupload.com/07atn9c81uc9/Walking_with_Dinosaurs_2013_CAM_x246_AAC.mkv.html</sublink>
</link>
<thumbnail>http://image.tmdb.org/t/p/original/syrPo4XWmrEaA8YeGLaKWOmT2a1.jpg</thumbnail>
</item>

<item>
<title>[COLOR blue]Movie[/COLOR] The Hobbit: The Desolation of Smaug (2013) DVDScr  [COLOR lime]12/28[/COLOR]</title>
<link>
<sublink>http://37.58.68.221/index.php?file=2681&start=0&hd=0&auth=0&type=flv&tv=0</sublink>
<sublink>http://billionuploads.com/su1fx2g2ou55</sublink>
<sublink>http://billionuploads.com/su1fx2g2ou55</sublink>
<sublink>http://billionuploads.com/7s6goddr7umm</sublink>
<sublink>http://billionuploads.com/sw07cvnlmdy7</sublink>
<sublink>http://hugefiles.net/ka8v76a27qtv</sublink>
<sublink>http://hugefiles.net/xaacyl3p8n3w</sublink>
<sublink>http://hugefiles.net/369fn95dj7c6</sublink>
<sublink>http://hugefiles.net/nagnyx22g3sy</sublink>
<sublink>http://epicshare.net/8hc9ymzpy15m</sublink>
<sublink>http://epicshare.net/aposquuernjm</sublink>
<sublink>http://180upload.com/w52rcr5qh7s7</sublink>
<sublink>http://180upload.com/6bsa773ldh6q</sublink>
<sublink>http://180upload.com/96p8rou87hg8</sublink>
<sublink>http://180upload.com/zsy4emvd2nwy</sublink>
<sublink>http://movreel.com/jvkrpvr7wjxe</sublink>
<sublink>http://movreel.com/96jtalom2ffz</sublink>
</link>
<thumbnail>http://image.tmdb.org/t/p/original/ouIvgaSFqBMMailxU9zZiVIXXeV.jpg</thumbnail>
</item>

<item>
<title>[COLOR blue]Standup[/COLOR] Norm MacDonald: Me Doing Standup (2011) [COLOR lime]12/28[/COLOR]</title>
<link>
<sublink>http://billionuploads.com/7y4pnket43i3</sublink>
<sublink>http://hugefiles.net/57mnlvmcz03x</sublink>
<sublink>http://180upload.com/twswqrcrpj0b</sublink>
<sublink>http://movreel.com/p6bi0l57r9uw</sublink>
</link>
<thumbnail>http://image.tmdb.org/t/p/original/cnhWmcfhsqWJLQCmgEKVZHnBHpf.jpg</thumbnail>
</item>

<item>
<title>[COLOR blue]Movie[/COLOR] Gravity (2013) HD [COLOR lime]12/27[/COLOR]</title>
<link>
<sublink>http://billionuploads.com/m4v5slwusxqt</sublink>
<sublink>http://hugefiles.net/03ixyoauizqg</sublink>
<sublink>http://180upload.com/fx14n73ypwm5</sublink>
<sublink>http://movreel.com/hv4wimw1y5ev</sublink>
</link>
<thumbnail>http://d3gtl9l2a4fn1j.cloudfront.net/t/p/original/2gPjLWIyrWlAn2DgKMOKTBnZYyO.jpg</thumbnail>
</item>



<item>
<title>[COLOR blue]Movie[/COLOR] Voodoo Possession (2014) SD [COLOR lime]12/26[/COLOR]</title>
<link>
<sublink>http://billionuploads.com/hb3geqjhs5c0</sublink>
<sublink>http://billionuploads.com/y317quj2915t</sublink>
<sublink>http://billionuploads.com/dp8jnr8yf3ar</sublink>
<sublink>http://billionuploads.com/6o6sshlwiztr</sublink>
<sublink>http://hugefiles.net/h9er30tdqkek</sublink>
<sublink>http://hugefiles.net/xulcpj4vebn9</sublink>
<sublink>http://hugefiles.net/4v4psz5jx6ey</sublink>
<sublink>http://hugefiles.net/az92l9olxl87</sublink>
<sublink>http://180upload.com/brjug8apo549</sublink>
<sublink>http://180upload.com/ofi2gf4udqyp</sublink>
<sublink>http://180upload.com/ofi2gf4udqyp</sublink>
<sublink>http://180upload.com/tdj58s3fcxg2</sublink>
<sublink>http://epicshare.net/qv3fspwxjk2p</sublink>
<sublink>http://movreel.com/vkj0km278up4</sublink>
<sublink>http://movreel.com/l5a5yee2hj74</sublink>
<sublink></sublink>
</link>
<thumbnail>http://image.tmdb.org/t/p/original/pJKEFRDKH24ahbkuEQgcFT6rDiH.jpg</thumbnail>
</item>

<item>
<title>[COLOR blue]Movie[/COLOR] Down and Dangerous (2014) HD [COLOR lime]12/26[/COLOR]</title>
<link>
<sublink>http://billionuploads.com/2tb960qc21k7</sublink>
<sublink>http://hugefiles.net/2ko0gmik9vuy</sublink>
<sublink>http://hugefiles.net/cwtwk01js0v1</sublink>
<sublink>http://hugefiles.net/9217zxe433j3</sublink>
<sublink>http://180upload.com/leesmoviqj7z</sublink>
<sublink>http://180upload.com/leesmoviqj7z</sublink>
<sublink></sublink>
<sublink></sublink>
</link>
<thumbnail>http://image.tmdb.org/t/p/original/hSWDq3FyotPwSC3PvcMbHnNulZO.jpg</thumbnail>
</item>

<item>
<title>[COLOR blue]Movie[/COLOR] Closed Circuit (2013) 1080P [COLOR lime]12/26[/COLOR]</title>
<link>
<sublink>http://billionuploads.com/0ozxbiw355sa/Closed.Circuit.2013.1080p.BluRay.x264.YIFY.mp4</sublink>
<sublink>http://hugefiles.net/7cxcjeaflguw</sublink>
<sublink>http://movreel.com/srkr20b7je3x.html</sublink>
<sublink>http://mightyupload.com/aun01ktax8w3/Closed.Circuit.2013.1080p.BluRay.x264.YIFY.mp4.html</sublink>
</link>
<thumbnail>http://d3gtl9l2a4fn1j.cloudfront.net/t/p/original/9yGO5J1Kn6ZH3gWIjQnHc0yvxJX.jpg</thumbnail>
</item>

<item>
<title>[COLOR blue]Movie[/COLOR] Closed Circuit (2013) HD [COLOR lime]12/26[/COLOR]</title>
<link>
<sublink>http://37.58.68.221/index.php?file=2677&start=0&hd=0&auth=0&type=flv&tv=0</sublink>
<sublink>http://billionuploads.com/xfidqx6pwl24</sublink>
<sublink>http://billionuploads.com/pcjpz58di3lm</sublink>
<sublink>http://hugefiles.net/cutf1fs5agnu</sublink>
<sublink>http://hugefiles.net/s8obcmibjwg9</sublink>
<sublink>http://hugefiles.net/8mvgouqofa3m</sublink>
<sublink>http://hugefiles.net/1pqj5hrhonn2</sublink>
<sublink>http://180upload.com/zpk282pjlwok</sublink>
<sublink>http://180upload.com/grnzodcn8nnp</sublink>
<sublink>http://180upload.com/wjp7qdi5j2k4</sublink>
</link>
<thumbnail>http://d3gtl9l2a4fn1j.cloudfront.net/t/p/original/9yGO5J1Kn6ZH3gWIjQnHc0yvxJX.jpg</thumbnail>
</item>

<item>
<title>[COLOR blue]Movie[/COLOR] Blinder (2013) 1080P [COLOR lime]12/26[/COLOR]</title>
<link>
<sublink>http://billionuploads.com/ro68pzicms90/Blinder.2013.1080p.BluRay.x264.YIFY.mp4</sublink>
<sublink>http://hugefiles.net/q71xxs2r6g3j</sublink>
<sublink>http://movreel.com/cdiw4inmz0e8.html</sublink>
<sublink>http://mightyupload.com/hue9ud41yx3u/Blinder.2013.1080p.BluRay.x264.YIFY.mp4.html</sublink>
</link>
<thumbnail>http://image.tmdb.org/t/p/original/89JbUveJE7tdL66rMR5JwMVv9AU.jpg</thumbnail>
</item>

<item>
<title>[COLOR blue]Movie[/COLOR] Blinder (2013) HD [COLOR lime]12/26[/COLOR]</title>
<link>
<sublink>http://37.58.68.221/index.php?file=2675&start=0&hd=0&auth=0&type=flv&tv=0</sublink>
<sublink>http://billionuploads.com/r42bzvjl7g4g</sublink>
<sublink>http://hugefiles.net/b831lc6ru6zm</sublink>
<sublink>http://180upload.com/nqsc4l2vghjp</sublink>
<sublink>http://billionuploads.com/omi1ryx57ose/Blinder.2013.720p.BluRay.x264.YIFY.mp4</sublink>
<sublink>http://hugefiles.net/8fr160awnpt0</sublink>
<sublink>http://mightyupload.com/qonrbnudn847/Blinder.2013.720p.BluRay.x264.YIFY.mp4.html</sublink>
<sublink>http://movreel.com/q4k35lrj7qrq.html</sublink>
<sublink></sublink>
</link>
<thumbnail>http://image.tmdb.org/t/p/original/89JbUveJE7tdL66rMR5JwMVv9AU.jpg</thumbnail>
</item>

<item>
<title>[COLOR blue]Movie[/COLOR] Tyler Perry's A Madea Christmas (2013) CAM [COLOR lime]12/26[/COLOR]</title>
<link>
<sublink>http://billionuploads.com/iw1ybv4mp7g7</sublink>
<sublink>http://hugefiles.net/664vcsqutxjd</sublink>
<sublink>http://movreel.com/4g6sbm93p26p.html</sublink>
<sublink>http://www.putlocker.com/file/145222F71219DB2F</sublink>
<sublink>http://billionuploads.com/fey8oi01e77m/AMC-2LOW.avi</sublink>
<sublink>http://hugefiles.net/pibybqe77bp6</sublink>
<sublink>http://180upload.com/2cdikih5ul7a</sublink>
<sublink></sublink>
</link>
<thumbnail>http://image.tmdb.org/t/p/original/sAIgC7ov0zy1iHEgsbrNh4wSpFS.jpg</thumbnail>
</item>

<item>
<title>[COLOR blue]Movie[/COLOR] Essex Boys Retribution (2013) HD [COLOR lime]12/26[/COLOR]</title>
<link>
<sublink>http://hugefiles.net/g2dgc84vp6ft</sublink>
<sublink>http://hugefiles.net/opj0v2purfug</sublink>
<sublink>http://180upload.com/m4umbu0emvo5</sublink>
<sublink>http://epicshare.net/rjxwn80dpxby</sublink>
</link>
<thumbnail>http://image.tmdb.org/t/p/original/771wrYsn4IkqsEJNOx6KZQ0V9ec.jpg</thumbnail>
</item>

<item>
<title>[COLOR blue]Documentary[/COLOR] Best Kept Secret (2013) [COLOR lime]12/26[/COLOR]</title>
<link>
<sublink>http://billionuploads.com/vhk4ka1l3pzt</sublink>
<sublink>http://hugefiles.net/aimcjoxaa4g9</sublink>
<sublink>http://180upload.com/ydmvkndlgzd6</sublink>
<sublink>http://epicshare.net/nif77zr5z2nk</sublink>
</link>
<thumbnail>http://image.tmdb.org/t/p/original/nyaFGiFCcw8MHbWQbVPw7wcaDFH.jpg</thumbnail>
</item>




<item>
<title>[COLOR blue]Movie[/COLOR] Anchorman 2: The Legend Continues (2013) CAM [COLOR lime]12/23[/COLOR]</title>
<link>
<sublink>http://billionuploads.com/7v4cbik1w1cu</sublink>
<sublink>http://hugefiles.net/vkg4f596z8a4</sublink>
<sublink>http://www.putlocker.com/file/E507DE05F8C0BA80</sublink>
<sublink>http://180upload.com/0bw2qynvmdi0</sublink>
<sublink>http://vidto.me/czi31r361qhk.html</sublink>
</link>
<thumbnail>http://image.tmdb.org/t/p/original/8HweezekJmUn4Rth0CoHa1pVKdC.jpg</thumbnail>
</item>
